Workbook

Sheet Home
L14: Dados Históricos / Historical Data
M18: INDICADORES / KPI | R18: EBITDA | W18: BS CONSOLIDADO
M24: DRE /INCOME STATEMENT | R24: BALANÇO / BALANCE SHEET | W24: P&l CONSOLIDADO
R29: RECEITA / REVENUE

Sheet Indicadores | KPI
B1: Principais Indicadores | C1: Main KPIs
D2: 1T15 | E2: 2T15 | F2: 3T15 | G2: 4T15 | H2: 2015 | I2: 1T16 | J2: 2T16 | K2: 3T16 | L2: 4T16 | M2: 2016 | N2: 1T17 | O2: 2T17 | P2: 3T17 | Q2: 4T17 | R2: 2017 | S2: 1T18 | T2: 2T18 | U2: 3T18 | V2: 4T18 | W2: 2018 | X2: 1T19 | Y2: 2T19 | Z2: 3T19 | AA2: 4T19 | AB2: 2019 | AC2: 1T20 | AD2: 2T20 | AE2: 3T20 | AF2: 4T20 | AG2: 2020 | AH2: 1T21 | AI2: 2T21 | AJ2: 3T21 | AK2: 4T21 | AL2: 2021 | AM2: 1T22 | AN2: 2T22 | AO2: 3T22 | AP2: 4T22 | AQ2: 2022 | AR2: 1T23 | AS2: 2T23 | AT2: 3T23 | AU2: 4T23 | AV2: 2023 | AW2: 1T24 | AX2: 2T24 | AY2: 3T24 | AZ2: 4T24 | BA2: 2024 | BB2: 1T25 | BC2: 2T25 | BD2: 3T25 | BE2: 4T25 | BF2: 2025 | BG2: 1T26 | BH2: 2T26
B3: Receita Líquida | C3: Net Revenue | D3: 1555436.2 | E3: 1665054.9 | F3: 1790312.4 | G3: 1835652.6 | H3: =SUM(D3:G3) -> 6846456.1 | I3: 1782357 | J3: 1760127.5 | K3: 1595510.5 | L3: 1678459 | M3: =SUM(I3:L3) -> 6816454 | N3: 1699036 | O3: 1901808.9 | P3: 1932450.6 | Q3: 1954644 | R3: =SUM(N3:Q3) -> 7487939.5 | S3: 2143752 | T3: 2399485 | U3: 2617310 | V3: 2455752 | W3: =SUM(S3:V3) -> 9616299 | X3: 2468119 | Y3: 2667331 | Z3: 2542311 | AA3: 2338634 | AB3: =SUM(X3:AA3) -> 10016395 | AC3: 2224560 | AD3: 1171844 | AE3: 2514756 | AF3: 2849408 | AG3: =SUM(AC3:AF3) -> 8760568 | AH3: 3133096 | AI3: 3183882.4 | AJ3: 3583978 | AK3: 3787410 | AL3: =SUM(AH3:AK3) -> 13688366 | AM3: 4277191 | AN3: 4192384 | AO3: 4318339 | AP3: 4159955 | AQ3: =SUM(AM3:AP3) -> 16947869 | AR3: 3998153 | AS3: 3801203 | AT3: 3672363 | AU3: 3483501 | AV3: =SUM(AR3:AU3) -> 14955220 | AW3: 3595766 | AX3: 3844568 | AY3: 3982373 | AZ3: 3909106 | BA3: =SUM(AW3:AZ3) -> 15331813 | BB3: 3938050 | BC3: 4106968 | BD3: 3802399 | BE3: 3519120 | BF3: 15366537 | BG3: ='DRE- Income Statement'!BF5 -> 3807333 | BH3: ='DRE- Income Statement'!BG5 -> 4012470
B4: Lucro Bruto | C4: Gross Profit | D4: 190482.77 | E4: 218305.08 | F4: 251434.1 | G4: 231806.17 | H4: 892028.13 | I4: 226582.07 | J4: 256257 | K4: 234387.25 | L4: 254561.61 | M4: 971787.94 | N4: 242779.1 | O4: 298208.28 | P4: 318429.58 | Q4: 295560.72 | R4: 1154977.7 | S4: 294852.89 | T4: 337791.45 | U4: 379382.1 | V4: 306249.02 | W4: 1318275.5 | X4: 298308.43 | Y4: 336575.05 | Z4: 322690.28 | AA4: 227643.2 | AB4: 1185217 | AC4: 184356.3 | AD4: -136336.3 | AE4: 255675.35 | AF4: 261618 | AG4: 565313.35 | AH4: 409716 | AI4: 420717.52 | AJ4: 495590.7 | AK4: 378098 | AL4: 1704122.2 | AM4: 611000.02 | AN4: 534650.23 | AO4: 338956.14 | AP4: 324035.51 | AQ4: 1808641.9 | AR4: 341086.1 | AS4: 424728.07 | AT4: 362191.08 | AU4: 380239.27 | AV4: 1508244.5 | AW4: 384128.76 | AX4: 476556 | AY4: 477737 | AZ4: 483011 | BA4: 1338421.8 | BB4: 443732 | BC4: 534617 | BD4: 460315 | BE4: 412108 | BF4: 1850772 | BG4: ='DRE- Income Statement'!BF11 -> 441538 | BH4: ='DRE- Income Statement'!BG11 -> 485543
B5: Lucro (Prejuízo) Líquido | C5: Net Income (Loss) | D5: -6678.3554 | E5: 70241.068 | F5: 2433.691 | G5: -16630.655 | H5: 449602.13 | I5: 6982.0714 | J5: -7192.2873 | K5: 4892.54 | L5: 16847.611 | M5: =SUM(I5:L5) -> 21529.935 | N5: -1250.3134 | O5: 24570.316 | P5: -28721.421 | Q5: 11804.725 | R5: =SUM(N5:Q5) -> 6403.3058 | S5: -12966.111 | T5: 44134.451 | U5: 93479.1 | V5: 76677.02 | W5: =SUM(S5:V5) -> 201324.46 | X5: 63096.433 | Y5: 110390.05 | Z5: 124838.28 | AA5: 39109.203 | AB5: =SUM(X5:AA5) -> 337433.97 | AC5: 9150.2979 | AD5: -352353.3 | AE5: -18876.646 | AF5: -129700 | AG5: =SUM(AC5:AF5) -> -491779.65 | AH5: 51502 | AI5: 214786.52 | AJ5: 177015.7 | AK5: 93916 | AL5: =SUM(AH5:AK5) -> 537220.21 | AM5: 160206.02 | AN5: 190485.23 | AO5: 69387.722 | AP5: -141146.49 | AQ5: =SUM(AM5:AP5) -> 278932.48 | AR5: -16340.903 | AS5: 59360.073 | AT5: -4784.9222 | AU5: -7501.7261 | AV5: =SUM(AR5:AU5) -> 30732.522 | AW5: 50257 | AX5: 36925 | AY5: 109172 | AZ5: 68366 | BA5: =SUM(AW5:AZ5) -> 264720 | BB5: 10892 | BC5: 86822 | BD5: 35067 | BE5: -34398 | BF5: 98383 | BG5: ='DRE- Income Statement'!BF32 -> 3920 | BH5: ='DRE- Income Statement'!BG32 -> 86869
B6: EBITDA | C6: EBITDA | D6: 139833.52 | E6: 242501.9 | F6: 204669.95 | G6: 164061.6 | H6: =SUM(D6:G6) -> 751066.97 | I6: 236295.42 | J6: 179570.95 | K6: 191109.14 | L6: 189249.51 | M6: =SUM(I6:L6) -> 796225.02 | N6: 185393.84 | O6: 194139.02 | P6: 220254.57 | Q6: 198765.91 | R6: =SUM(N6:Q6) -> 798553.34 | S6: 227112.85 | T6: 275408.5 | U6: 311999.73 | V6: 242554.66 | W6: =SUM(S6:V6) -> 1057075.7 | X6: 242587.39 | Y6: 304247.27 | Z6: 333779.69 | AA6: 215195.55 | AB6: =SUM(X6:AA6) -> 1095809.9 | AC6: 204967.46 | AD6: -199515.39 | AE6: 207676.01 | AF6: 159011.44 | AG6: =SUM(AC6:AF6) -> 372139.51 | AH6: 367938.26 | AI6: 592729.23 | AJ6: 489861.86 | AK6: 390803.28 | AL6: =SUM(AH6:AK6) -> 1841332.6 | AM6: 548151.67 | AN6: 534572.73 | AO6: 362701.61 | AP6: 291488.72 | AQ6: =SUM(AM6:AP6) -> 1736914.7 | AR6: 286760.45 | AS6: 363406.6 | AT6: 313322.08 | AU6: 289375.03 | AV6: =SUM(AR6:AU6) -> 1252864.2 | AW6: 316641.76 | AX6: 388931 | AY6: 440235 | AZ6: 378263 | BA6: =SUM(AW6:AZ6) -> 1524070.8 | BB6: 354362 | BC6: 450478 | BD6: 360435 | BE6: 328178 | BF6: 1493453 | BG6: 357046 | BH6: 417527
B7: Alavancagem | C7: Leverage | D7: =2546/637 -> 3.9968603 | E7: =2424/731 -> 3.3160055 | F7: =2728/768 -> 3.5520833 | G7: =2676/751 -> 3.563249 | H7: =2676/751 -> 3.563249 | I7: =2794/847 -> 3.2987013 | J7: =2578/784 -> 3.2882653 | K7: =2767/771 -> 3.5888457 | L7: =2628/796 -> 3.3015075 | M7: =2628/796 -> 3.3015075 | N7: =2128/745 -> 2.8563758 | O7: =2247/759 -> 2.9604743 | P7: =2282/789 -> 2.8922687 | Q7: =2299/798 -> 2.8809524 | R7: =2299/798 -> 2.8809524 | S7: =2230/840 -> 2.6547619 | T7: =2530/921 -> 2.7470141 | U7: =2602/1013 -> 2.5686081 | V7: =2326/1057 -> 2.2005676 | W7: =2326/1057 -> 2.2005676 | X7: =2727/1072 -> 2.5438433 | Y7: =2640/1101 -> 2.3978202 | Z7: =2668/1123 -> 2.3757792 | AA7: =2415/1095 -> 2.2054795 | AB7: =2415/1095 -> 2.2054795 | AC7: =3166/1058 -> 2.9924386 | AD7: =3636/554 -> 6.5631769 | AE7: =3738/428 -> 8.7336449 | AF7: 9.45 | AG7: 9.45 | AH7: =4057/535 -> 7.5831776 | AI7: =3981/1327 -> 3 | AJ7: =4522/1609 -> 2.8104413 | AK7: =4299/1841 -> 2.3351439 | AL7: =4299/1841 -> 2.3351439 | AM7: 2.06 | AN7: 2.21 | AO7: 2.27 | AP7: 2.26 | AQ7: 2.26 | AR7: 2.77 | AS7: 2.72 | AT7: 2.85 | AU7: 2.93 | AV7: 2.93 | AW7: 2.95 | AX7: 2.97 | AY7: =2.59 -> 2.59 | AZ7: 2.39 | BA7: 2.39 | BB7: 2.34 | BC7: 2.34 | BD7: 2.38 | BE7: 2.55 | BF7: 2.65 | BG7: 2.49 | BH7: 2.52
B8: Liquidez | C8: Liquidity Ratio | AI8: 0.75 | AJ8: 0.54 | AK8: 0.73 | AL8: 0.73 | AM8: 0.669 | AN8: 1.48 | AO8: 1.66 | AP8: 2.67 | AQ8: 2.67 | AR8: 1.54 | AS8: 1.63 | AT8: 2 | AU8: 2.12

Sheet DRE- Income Statement
A3: Consolidado | B3: Consolidated
A4: DRE - R$ mil | B4: I.S - R$ thousand | C4: 1T15 | D4: 2T15 | E4: 3T15 | F4: 4T15 | G4: 2015 | H4: 1T16 | I4: 2T16 | J4: 3T16 | K4: 4T16 | L4: 2016 | M4: 1T17 | N4: 2T17 | O4: 3T17 | P4: 4T17 | Q4: 2017 | R4: 1T18 | S4: 2T18 | T4: 3T18 | U4: 4T18 | V4: 2018 | W4: 1T19 | X4: 2T19 | Y4: 3T19 | Z4: 4T19 | AA4: 2019 | AB4: 1T20 | AC4: 2T20 | AD4: 3T20 | AE4: 4T20 | AF4: 2020 | AG4: 1T21 | AH4: 2T21 | AI4: 3T21 | AJ4: 4T21 | AK4: 2021 | AL4: 1T22 | AM4: 2T22 | AN4: 3T22 | AO4: 4T22 | AP4: 2022 | AQ4: 1T23 | AR4: 2T23 | AS4: 3T23 | AT4: 4T23 | AU4: 2023 | AV4: 1T24 | AW4: 2T24 | AX4: 3T24 | AY4: 4T24 | AZ4: 2024 | BA4: 1T25 | BB4: 2T25 | BC4: 3T25 | BD4: 4T25 | BE4: 2025 | BF4: 1T26 | BG4: 2T26
A5: Receita Operacional Líquida | B5: Net Operating Revenue | C5: 1555436.2 | D5: 1665054.9 | E5: 1790312.4 | F5: 1835652.6 | G5: =SUM(C5:F5) -> 6846456.1 | H5: 1782357 | I5: 1760127.5 | J5: 1595510.5 | K5: 1678459 | L5: =SUM(H5:K5) -> 6816454 | M5: 1699036 | N5: 1901808.9 | O5: 1932450.6 | P5: 1954644 | Q5: =SUM(M5:P5) -> 7487939.5 | R5: 2143752 | S5: 2399485 | T5: 2617310 | U5: 2455752 | V5: =SUM(R5:U5) -> 9616299 | W5: 2468119 | X5: 2667331 | Y5: 2542311 | Z5: 2338634 | AA5: =SUM(W5:Z5) -> 10016395 | AB5: 2224560 | AC5: 1171844 | AD5: 2514756 | AE5: 2849408 | AF5: =SUM(AB5:AE5) -> 8760568 | AG5: 3133096 | AH5: 3183882.4 | AI5: 3583978 | AJ5: 3787410 | AK5: =SUM(AG5:AJ5) -> 13688366 | AL5: 4277191 | AM5: 4192384 | AN5: 4318339 | AO5: 4159955 | AP5: =SUM(AL5:AO5) -> 16947869 | AQ5: 3998153 | AR5: 3801203 | AS5: 3672363 | AT5: 3483501 | AU5: =SUM(AQ5:AT5) -> 14955220 | AV5: 3595766 | AW5: 3844568 | AX5: 3982373 | AY5: ='P&L - Consolidado'!O3 -> 3909106 | AZ5: =SUM(AV5:AY5) -> 15331813 | BA5: ='P&L - Consolidado'!M3 -> 3938050 | BB5: ='P&L - Consolidado'!L3 -> 4106968 | BC5: ='P&L - Consolidado'!J3 -> 3802399 | BD5: ='P&L - Consolidado'!H3 -> 3519120 | BE5: =SUM(BA5:BD5) -> 15366537 | BF5: ='P&L - Consolidado'!F3 -> 3807333 | BG5: ='P&L - Consolidado'!E3 -> 4012470
A6: Custo dos Produtos Vendidos | B6: Cost of Goods Sold
A7: Matéria Prima | B7: Raw Material | C7: -821160.48 | D7: -886285.98 | E7: -929515.74 | F7: -949040.8 | G7: =SUM(C7:F7) -> -3586003 | H7: -903779.55 | I7: -876308.16 | J7: -781894.94 | K7: -828761.32 | L7: =SUM(H7:K7) -> -3390744 | M7: -875313.05 | N7: -988407.68 | O7: -994268.31 | P7: -1011167.5 | Q7: =SUM(M7:P7) -> -3869156.5 | R7: -1117554.5 | S7: -1271329.4 | T7: -1387085.1 | U7: -1275104.6 | V7: =SUM(R7:U7) -> -5051073.6 | W7: -1307644.1 | X7: -1436650.4 | Y7: -1313964.6 | Z7: -1205334.8 | AA7: =SUM(W7:Z7) -> -5263593.8 | AB7: -1170979.1 | AC7: -616023.5 | AD7: -1319747.5 | AE7: -1433279.3 | AF7: =SUM(AB7:AE7) -> -4540029.5 | AG7: -1576803.5 | AH7: -1629031.4 | AI7: -1921053.8 | AJ7: -2123870.9 | AK7: =SUM(AG7:AJ7) -> -7250759.5 | AL7: -2447332.4 | AM7: -2458703.8 | AN7: -2672667.8 | AO7: -2513181.9 | AP7: =SUM(AL7:AO7) -> -10091886 | AQ7: -2284634.4 | AR7: -2090441.8 | AS7: -2024418.9 | AT7: -1856329.6 | AU7: =SUM(AQ7:AT7) -> -8255824.8 | AV7: -1899035.4 | AW7: -1999447.2 | AX7: -2071783.4 | AY7: -1983810 | AZ7: =SUM(AV7:AY7) -> -7954076 | BA7: -1983429.8 | BB7: -2044159.2 | BC7: -2044159.2 | BD7: -1758035 | BE7: =SUM(BA7:BD7) -> -7829783.1 | BF7: -1924363 | BG7: -2042467.4
A8: Mão de Obra | B8: Labor | C8: -272878.38 | D8: -271677.32 | E8: -277797.7 | F8: -280736.91 | G8: =SUM(C8:F8) -> -1103090.3 | H8: -306898.46 | I8: -296137.01 | J8: -280055.85 | K8: -279714.24 | L8: =SUM(H8:K8) -> -1162805.6 | M8: -277041.8 | N8: -307368.45 | O8: -304900.2 | P8: -317091.1 | Q8: =SUM(M8:P8) -> -1206401.6 | R8: -341144.09 | S8: -377040.6 | T8: -389739.81 | U8: -401963.51 | V8: =SUM(R8:U8) -> -1509888 | W8: -412480.18 | X8: -425120.34 | Y8: -418805.19 | Z8: -421183.58 | AA8: =SUM(W8:Z8) -> -1677589.3 | AB8: -433727.73 | AC8: -311523.16 | AD8: -431134.19 | AE8: -482475.74 | AF8: =SUM(AB8:AE8) -> -1658860.8 | AG8: -521264.26 | AH8: -514603.15 | AI8: -517129.21 | AJ8: -544846.86 | AK8: =SUM(AG8:AJ8) -> -2097843.5 | AL8: -541564.5 | AM8: -518196.98 | AN8: -554266.42 | AO8: -563628.02 | AP8: =SUM(AL8:AO8) -> -2177655.9 | AQ8: -602659.22 | AR8: -575557.96 | AS8: -579825.62 | AT8: -555444.18 | AU8: =SUM(AQ8:AT8) -> -2313487 | AV8: -623433.1 | AW8: -651126.45 | AX8: -675676.32 | AY8: -657013 | AZ8: =SUM(AV8:AY8) -> -2607248.9 | BA8: -719033.4 | BB8: -740674.22 | BC8: -740674.22 | BD8: -652668 | BE8: =SUM(BA8:BD8) -> -2853049.8 | BF8: -713884 | BG8: -730470.25
A9: Outros | B9: Others | C9: -270914.57 | D9: -288786.54 | E9: -331564.89 | F9: -374068.69 | G9: =SUM(C9:F9) -> -1265334.7 | H9: -345096.92 | I9: -331425.29 | J9: -299172.5 | K9: -315421.83 | L9: =SUM(H9:K9) -> -1291116.5 | M9: -303902.06 | N9: -307824.47 | O9: -314852.54 | P9: -330824.7 | Q9: =SUM(M9:P9) -> -1257403.8 | R9: -390200.54 | S9: -413323.53 | T9: -461101.36 | U9: -472434.92 | V9: =SUM(R9:U9) -> -1737060.4 | W9: -449686.27 | X9: -468985.24 | Y9: -486850.93 | Z9: -484472.46 | AA9: =SUM(W9:Z9) -> -1889994.9 | AB9: -435496.82 | AC9: -380633.63 | AD9: -508198.94 | AE9: -672034.6 | AF9: =SUM(AB9:AE9) -> -1996364 | AG9: -625312.07 | AH9: -619530.42 | AI9: -650204.34 | AJ9: -740594.4 | AK9: =SUM(AG9:AJ9) -> -2635641.2 | AL9: -677294.1 | AM9: -680832.94 | AN9: -752448.63 | AO9: -759109.56 | AP9: =SUM(AL9:AO9) -> -2869685.2 | AQ9: -769773.25 | AR9: -710475.13 | AS9: -705927.38 | AT9: -691487.95 | AU9: =SUM(AQ9:AT9) -> -2877663.7 | AV9: -689168.73 | AW9: -717438.43 | AX9: -757176.19 | AY9: -785272 | AZ9: =SUM(AV9:AY9) -> -2949055.3 | BA9: -791855.07 | BB9: -787517.88 | BC9: -787517.88 | BD9: -696309 | BE9: =SUM(BA9:BD9) -> -3063199.8 | BF9: -727549 | BG9: -753989.35
C10: =SUM(C7:C9) -> -1364953.4 | D10: =SUM(D7:D9) -> -1446749.8 | E10: =SUM(E7:E9) -> -1538878.3 | F10: =SUM(F7:F9) -> -1603846.4 | G10: =SUM(C10:F10) -> -5954428 | H10: =SUM(H7:H9) -> -1555774.9 | I10: =SUM(I7:I9) -> -1503870.5 | J10: =SUM(J7:J9) -> -1361123.3 | K10: =SUM(K7:K9) -> -1423897.4 | L10: =SUM(H10:K10) -> -5844666.1 | M10: =SUM(M7:M9) -> -1456256.9 | N10: =SUM(N7:N9) -> -1603600.6 | O10: =SUM(O7:O9) -> -1614021 | P10: =SUM(P7:P9) -> -1659083.3 | Q10: =SUM(M10:P10) -> -6332961.8 | R10: =SUM(R7:R9) -> -1848899.1 | S10: =SUM(S7:S9) -> -2061693.5 | T10: =SUM(T7:T9) -> -2237926.3 | U10: =SUM(U7:U9) -> -2149503 | V10: =SUM(R10:U10) -> -8298021.9 | W10: =SUM(W7:W9) -> -2169810.6 | X10: =SUM(X7:X9) -> -2330755.9 | Y10: =SUM(Y7:Y9) -> -2219620.7 | Z10: -2110990.8 | AA10: =SUM(W10:Z10) -> -8831178 | AB10: -2040203.7 | AC10: =SUM(AC7:AC9) -> -1308180.3 | AD10: =SUM(AD7:AD9) -> -2259080.6 | AE10: -2587790 | AF10: =SUM(AB10:AE10) -> -8195254.6 | AG10: -2723380 | AH10: -2763164.9 | AI10: =SUM(AI7:AI9) -> -3088387.3 | AJ10: -3409312 | AK10: =SUM(AG10:AJ10) -> -11984244 | AL10: =SUM(AL7:AL9) -> -3666191 | AM10: =SUM(AM7:AM9) -> -3657733.8 | AN10: =SUM(AN7:AN9) -> -3979382.9 | AO10: =SUM(AO7:AO9) -> -3835919.5 | AP10: =SUM(AL10:AO10) -> -15139227 | AQ10: =SUM(AQ7:AQ9) -> -3657066.9 | AR10: =SUM(AR7:AR9) -> -3376474.9 | AS10: =SUM(AS7:AS9) -> -3310171.9 | AT10: =SUM(AT7:AT9) -> -3103261.7 | AU10: =SUM(AQ10:AT10) -> -13446975 | AV10: =SUM(AV7:AV9) -> -3211637.2 | AW10: -3368012 | AX10: -3504636 | AY10: ='P&L - Consolidado'!O4 -> -3426095 | AZ10: =SUM(AV10:AY10) -> -13510380 | BA10: ='P&L - Consolidado'!M4 -> -3494318 | BB10: ='P&L - Consolidado'!L4 -> -3572351 | BC10: ='P&L - Consolidado'!J4 -> -3342084 | BD10: ='P&L - Consolidado'!H4 -> -3107012 | BE10: =SUM(BA10:BD10) -> -13515765 | BF10: ='P&L - Consolidado'!F4 -> -3365795 | BG10: ='P&L - Consolidado'!E4 -> -3526927
A11: Lucro (Prejuízo) Bruto | B11: Gross Profit | C11: =C5+C10 -> 190482.77 | D11: =D5+D10 -> 218305.08 | E11: =E5+E10 -> 251434.1 | F11: =F5+F10 -> 231806.17 | G11: =SUM(C11:F11) -> 892028.13 | H11: =H5+H10 -> 226582.07 | I11: =I5+I10 -> 256257 | J11: =J5+J10 -> 234387.25 | K11: =K5+K10 -> 254561.61 | L11: =SUM(H11:K11) -> 971787.94 | M11: =M5+M10 -> 242779.1 | N11: =N5+N10 -> 298208.28 | O11: =O5+O10 -> 318429.58 | P11: =P5+P10 -> 295560.72 | Q11: =SUM(M11:P11) -> 1154977.7 | R11: =R5+R10 -> 294852.89 | S11: =S5+S10 -> 337791.45 | T11: 379382.1 | U11: =U5+U10 -> 306249.02 | V11: =SUM(R11:U11) -> 1318275.5 | W11: =W5+W10 -> 298308.43 | X11: =X5+X10 -> 336575.05 | Y11: =Y5+Y10 -> 322690.28 | Z11: =Z10+Z5 -> 227643.2 | AA11: =SUM(W11:Z11) -> 1185217 | AB11: 184356.3 | AC11: =AC5+AC10 -> -136336.3 | AD11: =AD5+AD10 -> 255675.35 | AE11: 261618 | AF11: =SUM(AB11:AE11) -> 565313.35 | AG11: 409716 | AH11: =AH10+AH5 -> 420717.52 | AI11: =AI10+AI5 -> 495590.7 | AJ11: =AJ10+AJ5 -> 378098 | AK11: =SUM(AG11:AJ11) -> 1704122.2 | AL11: =AL10+AL5 -> 611000.02 | AM11: =AM10+AM5 -> 534650.23 | AN11: =AN10+AN5 -> 338956.14 | AO11: =AO10+AO5 -> 324035.51 | AP11: =SUM(AL11:AO11) -> 1808641.9 | AQ11: =AQ10+AQ5 -> 341086.1 | AR11: =AR10+AR5 -> 424728.07 | AS11: =AS10+AS5 -> 362191.08 | AT11: =AT10+AT5 -> 380239.27 | AU11: =SUM(AQ11:AT11) -> 1508244.5 | AV11: =AV10+AV5 -> 384128.76 | AW11: 476556 | AX11: =AX5+AX10 -> 477737 | AY11: =AY5+AY10 -> 483011 | AZ11: =SUM(AV11:AY11) -> 1821432.8 | BA11: =BA10+BA5 -> 443732 | BB11: =BB10+BB5 -> 534617 | BC11: =BC10+BC5 -> 460315 | BD11: =BD10+BD5 -> 412108 | BE11: =SUM(BA11:BD11) -> 1850772 | BF11: =BF10+BF5 -> 441538 | BG11: =BG10+BG5 -> 485543
C12: =C11/C5 -> 0.12246261 | D12: =D11/D5 -> 0.13110984 | E12: =E11/E5 -> 0.14044147 | F12: =F11/F5 -> 0.12627998 | G12: =G11/G5 -> 0.13029049 | H12: =H11/H5 -> 0.12712497 | I12: =I11/I5 -> 0.14559003 | J12: =J11/J5 -> 0.14690423 | ... AA12: =AA11/AA5 -> 0.1183277 | AB12: 0.082873152 | AC12: =AC11/AC5 -> -0.11634339 | AD12: =AD11/AD5 -> 0.10167004 | AE12: =AE11/AE5 -> 0.091814861 | AF12: =AF11/AF5 -> 0.064529304 | AG12: 0.13077033 | AH12: =AH11/AH5 -> 0.13213978 | AI12: =AI11/AI5 -> 0.1382795 | AJ12: =AJ11/AJ5 -> 0.099830227 | AK12: =AK11/AK5 -> 0.1244942 | AL12: =AL11/AL5 -> 0.14285077 | AM12: =AM11/AM5 -> 0.12752893 | AN12: =AN11/AN5 -> 0.078492249 | AO12: =AO11/AO5 -> 0.077893994 | ... AV12: =AV11/AV5 -> 0.10682807 | AW12: 0.12395567 | AX12: =AX11/AX5 -> 0.1199629 | AY12: =AY11/AY5 -> 0.12356048 | AZ12: =AZ11/AZ5 -> 0.11880087 | BA12: =BA11/BA5 -> 0.1126781 | BB12: =BB11/BB5 -> 0.13017316 | BC12: =BC11/BC5 -> 0.1210591 | BD12: =BD11/BD5 -> 0.11710541 | BE12: =BE11/BE5 -> 0.12044171 | ... BG12: =BG11/BG5 -> 0.12100851
A13: Despesas Operacionais | B13: Operating Expenses
A14: Com vendas | B14: Selling expenses | C14: -31229 | D14: -35395 | E14: -39589 | F14: -49347 | G14: =SUM(C14:F14) -> -155560 | H14: -38745 | I14: -36594 | J14: -40025 | K14: -35567 | L14: =SUM(H14:K14) -> -150931 | M14: -35552 | N14: -42283 | O14: -42465 | P14: -41857 | Q14: =SUM(M14:P14) -> -162157 | R14: -9098 | S14: -10382 | T14: -17172 | U14: -38707 | V14: =SUM(R14:U14) -> -75359 | W14: -13873 | X14: -9142 | Y14: -17453 | Z14: -13310 | AA14: =SUM(W14:Z14) -> -53778 | AB14: -13258 | AC14: -13579 | AD14: -11754 | AE14: -23221 | AF14: =SUM(AB14:AE14) -> -61812 | AG14: -22412 | AH14: -12457 | AI14: -19100 | AJ14: -24517 | AK14: =SUM(AG14:AJ14) -> -78486 | AL14: -21317 | AM14: -21290 | AN14: -27130 | AO14: -26358 | AP14: =SUM(AL14:AO14) -> -96095 | AQ14: -17792 | AR14: -22335 | AS14: -20410 | AT14: -21137 | AU14: =SUM(AQ14:AT14) -> -81674 | AV14: -17805 | AW14: -19866 | AX14: -18907 | AY14: ='P&L - Consolidado'!O7 -> -19572 | AZ14: =SUM(AV14:AY14) -> -76150 | BA14: ='P&L - Consolidado'!M7 -> -20413 | BB14: ='P&L - Consolidado'!L7 -> -26065 | BC14: ='P&L - Consolidado'!J7 -> -21768 | BD14: ='P&L - Consolidado'!H7 -> -13183 | BE14: =SUM(BA14:BD14) -> -81429 | BF14: ='P&L - Consolidado'!F7 -> -21707 | BG14: ='P&L - Consolidado'!E7 -> -15375
A15: Gerais e Administrativas | B15: General and administrative | C15: -73640 | D15: -68051 | E15: -83208 | F15: -92659 | G15: =SUM(C15:F15) -> -317558 | H15: -92375 | I15: -91879 | J15: -86842 | K15: -97130 | L15: =SUM(H15:K15) -> -368226 | M15: -90648 | N15: -96244 | O15: -84723 | P15: -112791 | Q15: =SUM(M15:P15) -> -384406 | R15: -116383 | S15: -124074 | T15: -122830 | U15: -113825 | V15: =SUM(R15:U15) -> -477112 | W15: -123681 | X15: -119701 | Y15: -116338 | Z15: -123248 | AA15: =SUM(W15:Z15) -> -482968 | AB15: -113418 | AC15: -116217 | AD15: -120736 | AE15: -137350 | AF15: =SUM(AB15:AE15) -> -487721 | AG15: -156545 | AH15: -163153 | AI15: -153481 | AJ15: -172788 | AK15: =SUM(AG15:AJ15) -> -645967 | AL15: -142631 | AM15: -155940 | AN15: -150993 | AO15: -177959 | AP15: =SUM(AL15:AO15) -> -627523 | AQ15: -161089 | AR15: -166485 | AS15: -159265 | AT15: -171319 | AU15: =SUM(AQ15:AT15) -> -658158 | AV15: -155018 | AW15: -165615 | AX15: -168635 | AY15: ='P&L - Consolidado'!O9 -> -209265 | AZ15: =SUM(AV15:AY15) -> -698533 | BA15: ='P&L - Consolidado'!M9 -> -197143 | BB15: ='P&L - Consolidado'!L9 -> -208892 | BC15: ='P&L - Consolidado'!J9 -> -181161 | BD15: ='P&L - Consolidado'!H9 -> -206177 | BE15: =SUM(BA15:BD15) -> -793373 | BF15: ='P&L - Consolidado'!F9 -> -179874 | BG15: ='P&L - Consolidado'!E9 -> -189447
A16: Honorários da Administração | B16: Management fees | C16: -3372 | D16: -2827 | E16: -2706 | F16: -2719 | G16: =SUM(C16:F16) -> -11624 | H16: -5973 | I16: -2920 | J16: -4031 | K16: -3223 | L16: =SUM(H16:K16) -> -16147 | M16: -3511 | N16: -2892 | O16: -2467 | P16: -5532 | Q16: =SUM(M16:P16) -> -14402 | R16: -2878 | S16: -3511 | T16: -2806 | U16: -7921 | V16: =SUM(R16:U16) -> -17116 | W16: -3420 | X16: -4315 | Y16: -3104 | Z16: -8247 | AA16: =SUM(W16:Z16) -> -19086 | AB16: -3580 | AC16: -2569 | AD16: -2627 | AE16: -5334 | AF16: =SUM(AB16:AE16) -> -14110 | AG16: -2917 | AH16: -3526 | AI16: -2436 | AJ16: -7497 | AK16: =SUM(AG16:AJ16) -> -16376 | AL16: -4907 | AM16: -4383 | AN16: -3950 | AO16: -5731 | AP16: =SUM(AL16:AO16) -> -18971 | AQ16: -5978 | AR16: -4078 | AS16: -3595 | AT16: -4096 | AU16: =SUM(AQ16:AT16) -> -17747 | AV16: -5574 | AW16: -5740 | AX16: -5132 | AY16: ='P&L - Consolidado'!O10 -> -7406 | AZ16: =SUM(AV16:AY16) -> -23852 | BA16: ='P&L - Consolidado'!M10 -> -8545 | BB16: ='P&L - Consolidado'!L10 -> -9063 | BC16: ='P&L - Consolidado'!J10 -> -7301 | BD16: ='P&L - Consolidado'!H10 -> -5256 | BE16: =SUM(BA16:BD16) -> -30165 | BF16: ='P&L - Consolidado'!F10 -> -8738 | BG16: ='P&L - Consolidado'!E10 -> -9018
A17: Outras Despesas/Receitas | B17: Other | C17: -8778 | D17: -16015 | E17: -1526 | F17: -2013 | G17: =SUM(C17:F17) -> -28332 | H17: 66515 | I17: -15027 | J17: 24746 | K17: -4597 | L17: =SUM(H17:K17) -> 71637 | M17: -1866 | N17: -12181 | O17: -45808 | P17: -17645 | Q17: =SUM(M17:P17) -> -77500 | R17: -21965 | S17: -1545 | T17: -12436 | U17: 3207 | V17: =SUM(R17:U17) -> -32739 | W17: -5841 | X17: 1988 | Y17: 50859 | Z17: 23765 | AA17: =SUM(W17:Z17) -> 70771 | AB17: 25764 | AC17: -61064 | AD17: -49618 | AE17: -103516 | AF17: =SUM(AB17:AE17) -> -188434 | AG17: -5692 | AH17: 202057 | AI17: 26522 | AJ17: 61425 | AK17: =SUM(AG17:AJ17) -> 284312 | AL17: -26918 | AM17: 54834 | AN17: 78853 | AO17: 42417 | AP17: =SUM(AL17:AO17) -> 149186 | AQ17: 3676 | AR17: 10486 | AS17: 12574 | AT17: -9199 | AU17: =SUM(AQ17:AT17) -> 17537 | AV17: -5657 | AW17: -25158 | AX17: 14429 | AY17: ='P&L - Consolidado'!O12 -> -7745 | AZ17: =SUM(AV17:AY17) -> -24131 | BA17: ='P&L - Consolidado'!M12 -> -6068 | BB17: ='P&L - Consolidado'!L12 -> -2517 | BC17: ='P&L - Consolidado'!J12 -> -39348 | BD17: ='P&L - Consolidado'!H12 -> -6677 | BE17: =SUM(BA17:BD17) -> -54610 | BF17: ='P&L - Consolidado'!F12 -> -13934 | BG17: =SUM('P&L - Consolidado'!E12:E13) -> 2576
C18: =SUM(C14:C17) -> -117019 | D18: =SUM(D14:D17) -> -122288 | E18: =SUM(E14:E17) -> -127029 | F18: =SUM(F14:F17) -> -146738 | G18: =SUM(G14:G17) -> -513074 | H18: =SUM(H14:H17) -> -70578 | I18: =SUM(I14:I17) -> -146420 | J18: =SUM(J14:J17) -> -106152 | ... AA18: =SUM(AA14:AA17) -> -485061 | AB18: -104492 | AC18: =SUM(AC14:AC17) -> -193429 | AD18: =SUM(AD14:AD17) -> -184735 | AE18: =SUM(AE14:AE17) -> -269421 | AF18: =SUM(AF14:AF17) -> -752077 | AG18: -187566 | AH18: =SUM(AH14:AH17) -> 22921 | AI18: =SUM(AI14:AI17) -> -148495 | AJ18: =SUM(AJ14:AJ17) -> -143377 | AK18: =SUM(AK14:AK17) -> -456517 | AL18: =SUM(AL14:AL17) -> -195773 | AM18: =SUM(AM14:AM17) -> -126779 | AN18: =SUM(AN14:AN17) -> -103220 | AO18: =SUM(AO14:AO17) -> -167631 | ... AV18: =SUM(AV14:AV17) -> -184054 | AW18: -216379 | AX18: =SUM(AX14:AX17) -> -178245 | AY18: =SUM(AY14:AY17) -> -243988 | AZ18: =SUM(AV18:AY18) -> -822666 | BA18: =SUM(BA14:BA17) -> -232169 | BB18: =SUM(BB14:BB17) -> -246537 | BC18: =SUM(BC14:BC17) -> -249578 | BD18: =SUM(BD14:BD17) -> -231293 | BE18: =SUM(BA18:BD18) -> -959577 | BF18: =SUM(BF14:BF17) -> -224253 | BG18: =SUM(BG14:BG17) -> -211264
A19: Resultado de Equivalência Patrimonial | B19: Equity Income | C19: -556 | D19: 75528 | E19: 484 | F19: -4808 | G19: =SUM(C19:F19) -> 70648 | H19: -2929 | I19: -8714 | J19: -14059 | K19: -3097 | L19: =SUM(H19:K19) -> -28799 | M19: 4844 | N19: -23749 | O19: 1019 | P19: -2071 | Q19: =SUM(M19:P19) -> -19957 | R19: 2599 | S19: -8288 | T19: -4416 | U19: -4352 | V19: =SUM(R19:U19) -> -14457 | W19: -7728 | X19: -3753 | Y19: -9917 | Z19: -2504 | AA19: =SUM(W19:Z19) -> -23902 | AB19: 5632 | AC19: -2269 | AD19: 539 | AE19: -1859 | AF19: =SUM(AB19:AE19) -> 2043 | AG19: 931 | AH19: 10652 | AI19: 7568 | AJ19: 14728 | AK19: =SUM(AG19:AJ19) -> 33879 | AL19: 4674 | AM19: 6024 | AN19: 9760.5821 | AO19: 9986 | AP19: =SUM(AL19:AO19) -> 30444.582 | AQ19: 5857 | AR19: 3309 | AS19: 6410 | AT19: -1203 | AU19: =SUM(AQ19:AT19) -> 14373 | AV19: 815 | AW19: 6256 | AX19: 7072 | AY19: ='P&L - Consolidado'!O14 -> 8126 | AZ19: =SUM(AV19:AY19) -> 22269 | BA19: ='P&L - Consolidado'!M14 -> 5466 | BB19: ='P&L - Consolidado'!L14 -> 18776 | BC19: ='P&L - Consolidado'!J14 -> 11175 | BD19: ='P&L - Consolidado'!H14 -> 15302 | BE19: =SUM(BA19:BD19) -> 50719 | BF19: ='P&L - Consolidado'!F14 -> 1538 | BG19: ='P&L - Consolidado'!E14 -> 9434
A20: Lucro (Prejuízo) Operacional (EBIT) | B20: Operating Income (EBIT) | C20: =C18+C19+C11 -> 72907.773 | D20: =D18+D19+D11 -> 171545.08 | E20: =E18+E19+E11 -> 124889.1 | F20: =F18+F19+F11 -> 80260.165 | G20: =SUM(C20:F20) -> 449602.13 | H20: =H18+H19+H11 -> 153075.07 | I20: =I18+I19+I11 -> 101123 | J20: =J18+J19+J11 -> 114176.25 | K20: =K18+K19+K11 -> 110947.61 | L20: =SUM(H20:K20) -> 479321.94 | M20: =M18+M19+M11 -> 116046.1 | N20: =N18+N19+N11 -> 120859.28 | O20: =O18+O19+O11 -> 143985.58 | P20: =P18+P19+P11 -> 115664.72 | Q20: =SUM(M20:P20) -> 496555.68 | R20: =R18+R19+R11 -> 147127.89 | S20: =S18+S19+S11 -> 189991.45 | T20: =T18+T19+T11 -> 219722.1 | U20: =U18+U19+U11 -> 144651.02 | V20: =SUM(R20:U20) -> 701492.46 | W20: =W18+W19+W11 -> 143765.43 | X20: =X18+X19+X11 -> 201652.05 | Y20: =Y18+Y19+Y11 -> 226737.28 | Z20: =Z18+Z19+Z11 -> 104099.2 | AA20: =SUM(W20:Z20) -> 676253.97 | AB20: 85496.298 | AC20: =AC18+AC19+AC11 -> -332034.3 | AD20: =AD18+AD19+AD11 -> 71479.354 | AE20: =AE18+AE19+AE11 -> -9662 | AF20: =SUM(AB20:AE20) -> -184720.65 | AG20: 223081 | AH20: =AH18+AH19+AH11 -> 454290.52 | AI20: =AI18+AI19+AI11 -> 354663.7 | AJ20: =AJ18+AJ19+AJ11 -> 249449 | AK20: =SUM(AG20:AJ20) -> 1281484.2 | AL20: =AL18+AL19+AL11 -> 419901.02 | AM20: =AM18+AM19+AM11 -> 413895.23 | AN20: =AN18+AN19+AN11 -> 245496.72 | AO20: =AO18+AO19+AO11 -> 166390.51 | AP20: =SUM(AL20:AO20) -> 1245683.5 | AQ20: =AQ18+AQ19+AQ11 -> 165760.1 | AR20: =AR18+AR19+AR11 -> 245625.07 | AS20: =AS18+AS19+AS11 -> 197905.08 | AT20: =AT18+AT19+AT11 -> 173285.27 | AU20: =SUM(AQ20:AT20) -> 782575.52 | AV20: =AV18+AV19+AV11 -> 200889.76 | AW20: 266433 | AX20: =AX11+AX18+AX19 -> 306564 | AY20: =AY11+AY18+AY19 -> 247149 | AZ20: =SUM(AV20:AY20) -> 1021035.8 | BA20: =BA18+BA19+BA11 -> 217029 | BB20: =BB18+BB19+BB11 -> 306856 | BC20: =BC18+BC19+BC11 -> 221912 | BD20: =BD18+BD19+BD11 -> 196117 | BE20: =SUM(BA20:BD20) -> 941914 | BF20: =BF18+BF19+BF11 -> 218823 | BG20: =BG18+BG19+BG11 -> 283713
C21: =C20/C5 -> 0.046872879 | D21: =D20/D5 -> 0.10302668 | E21: =E20/E5 -> 0.069758273 | F21: =F20/F5 -> 0.043722961 | G21: =G20/G5 -> 0.065669321 | H21: =H20/H5 -> 0.085883508 | I21: =I20/I5 -> 0.05745209 | J21: =J20/J5 -> 0.071560951 | ... AA21: =AA20/AA5 -> 0.067514706 | AB21: 0.038432903 | AC21: =AC20/AC5 -> -0.28334343 | AD21: =AD20/AD5 -> 0.028423972 | AE21: =AE20/AE5 -> -0.0033908798 | AF21: =AF20/AF5 -> -0.021085465 | AG21: 0.071201457 | AH21: =AH20/AH5 -> 0.14268445 | AI21: =AI20/AI5 -> 0.098958112 | AJ21: =AJ20/AJ5 -> 0.065862687 | AK21: =AK20/AK5 -> 0.093618491 | AL21: =AL20/AL5 -> 0.098172146 | AM21: =AM20/AM5 -> 0.098725506 | AN21: =AN20/AN5 -> 0.056849803 | AO21: =AO20/AO5 -> 0.039998151 | ... AV21: =AV20/AV5 -> 0.055868418 | AW21: 0.069301154 | AX21: =AX20/AX5 -> 0.076980233 | AY21: =AY20/AY5 -> 0.063223919 | AZ21: =AZ20/AZ5 -> 0.066595892 | BA21: =BA20/BA5 -> 0.055110778 | BB21: =BB20/BB5 -> 0.074715946 | BC21: =BC20/BC5 -> 0.05836105 | BD21: =BD20/BD5 -> 0.055728989 | BE21: =BE20/BE5 -> 0.061296439 | ... BG21: =BG20/BG5 -> 0.070707818
A22: Resultado Financeiro | B22: Financial Results
A23: Receitas Financeiras | B23: Financial Revenue | C23: 14056 | D23: 5419 | E23: 8532 | F23: 9243 | G23: =SUM(C23:F23) -> 37250 | H23: 7051 | I23: 36526 | J23: 5984 | K23: 8276 | L23: =SUM(H23:K23) -> 57837 | M23: 7159 | N23: 16276 | O23: 8884 | P23: 22841 | Q23: =SUM(M23:P23) -> 55160 | R23: 4767 | S23: 8750 | T23: -2463 | U23: 3784 | V23: =SUM(R23:U23) -> 14838 | W23: 5792 | X23: 4680 | Y23: 30214 | Z23: 24658 | AA23: =SUM(W23:Z23) -> 65344 | AB23: 3421 | AC23: 7185 | AD23: 4346 | AE23: 18414 | AF23: =SUM(AB23:AE23) -> 33366 | AG23: 4640 | AH23: 67079 | AI23: 9307 | AJ23: 16827 | AK23: =SUM(AG23:AJ23) -> 97853 | AL23: 14402 | AM23: 24572 | AN23: 35162 | AO23: 40319 | AP23: =SUM(AL23:AO23) -> 114455 | AQ23: 49720 | AR23: 54793 | AS23: 50098 | AT23: 61540 | AU23: =SUM(AQ23:AT23) -> 216151 | AV23: 72201 | AW23: 44738 | AX23: 54759 | AY23: ='P&L - Consolidado'!O17 -> 252694 | AZ23: =SUM(AV23:AY23) -> 424392 | BA23: ='P&L - Consolidado'!M17 -> 34229 | BB23: ='P&L - Consolidado'!L17 -> 34225 | BC23: ='P&L - Consolidado'!J17 -> 33630 | BD23: ='P&L - Consolidado'!H17 -> 771438 | BE23: =SUM(BA23:BD23) -> 873522 | BF23: ='P&L - Consolidado'!F17 -> 28818 | BG23: ='P&L - Consolidado'!E17 -> 30357
A24: Despesas Financeiras | B24: Financial Expenses | C24: -73169 | D24: -90804 | E24: -93212 | F24: -97169 | G24: =SUM(C24:F24) -> -354354 | H24: -90135 | I24: -111061 | J24: -82632 | K24: -98425 | L24: =SUM(H24:K24) -> -382253 | M24: -73125 | N24: -64987 | O24: -159716 | P24: -96796 | Q24: =SUM(M24:P24) -> -394624 | R24: -66092 | S24: -70317 | T24: -49105 | U24: -53900 | V24: =SUM(R24:U24) -> -239414 | W24: -79180 | X24: -51480 | Y24: -54550 | Z24: -44914 | AA24: =SUM(W24:Z24) -> -230124 | AB24: -49399 | AC24: -75746 | AD24: -66936 | AE24: -70350 | AF24: =SUM(AB24:AE24) -> -262431 | AG24: -67805 | AH24: -124670 | AI24: -88614 | AJ24: -108327 | AK24: =SUM(AG24:AJ24) -> -389416 | AL24: -126473 | AM24: -141675 | AN24: -170613 | AO24: -274592 | AP24: =SUM(AL24:AO24) -> -713353 | AQ24: -177074 | AR24: -156962 | AS24: -174649 | AT24: -193674 | AU24: =SUM(AQ24:AT24) -> -702359 | AV24: -164427 | AW24: -159714 | AX24: -147954 | AY24: ='P&L - Consolidado'!O21 -> -169194 | AZ24: =SUM(AV24:AY24) -> -641289 | BA24: ='P&L - Consolidado'!M21 -> -168261 | BB24: ='P&L - Consolidado'!L21 -> -159902 | BC24: ='P&L - Consolidado'!J21 -> -165639 | BD24: ='P&L - Consolidado'!H21 -> -166630 | BE24: =SUM(BA24:BD24) -> -660432 | BF24: ='P&L - Consolidado'!F21 -> -155326 | BG24: ='P&L - Consolidado'!E21 -> -154863
A25: Variação cambial líquida | B25: Foreing exchange gains (losses) | C25: 8007 | D25: -4262 | E25: -12711 | F25: 9310 | G25: =SUM(C25:F25) -> 344 | H25: -14304 | I25: -6403 | J25: -9304 | K25: 9937 | L25: =SUM(H25:K25) -> -20074 | M25: -2513 | N25: -331 | O25: 1909 | P25: -6809 | Q25: =SUM(M25:P25) -> -7744 | R25: -3282 | S25: -3280 | T25: 2419 | U25: 7900 | V25: =SUM(R25:U25) -> 3757 | W25: -4414 | X25: -2904 | Y25: 231 | Z25: 1963 | AA25: =SUM(W25:Z25) -> -5124 | AB25: -3602 | AC25: -15560 | AD25: 20350 | AE25: -5109 | AF25: =SUM(AB25:AE25) -> -3921 | AG25: 4123 | AH25: -10952 | AI25: 551 | AJ25: -26776 | AK25: =SUM(AG25:AJ25) -> -33054 | AL25: -10181 | AM25: 4737 | AN25: -2326 | AO25: -10996 | AP25: =SUM(AL25:AO25) -> -18766 | AQ25: -4535 | AR25: -20239 | AS25: 5621 | AT25: -12515 | AU25: =SUM(AQ25:AT25) -> -31668 | AV25: -2930 | AW25: -1502 | AX25: -5991 | AY25: ='P&L - Consolidado'!O22 -> -208253 | AZ25: =SUM(AV25:AY25) -> -218676 | BA25: ='P&L - Consolidado'!M22 -> -5959 | BB25: ='P&L - Consolidado'!L22 -> -25694 | BC25: ='P&L - Consolidado'!J22 -> -12557 | BD25: ='P&L - Consolidado'!H22 -> -747155 | BE25: =SUM(BA25:BD25) -> -791365 | BF25: ='P&L - Consolidado'!F22 -> -19773 | BG25: ='P&L - Consolidado'!E22 -> 7464
C26: =SUM(C23:C25) -> -51106 | D26: =SUM(D23:D25) -> -89647 | E26: =SUM(E23:E25) -> -97391 | F26: =SUM(F23:F25) -> -78616 | G26: =SUM(G23:G25) -> -316760 | H26: =SUM(H23:H25) -> -97388 | I26: =SUM(I23:I25) -> -80938 | J26: =SUM(J23:J25) -> -85952 | ... AA26: =SUM(AA23:AA25) -> -169904 | AB26: -49580 | AC26: =SUM(AC23:AC25) -> -84121 | AD26: =SUM(AD23:AD25) -> -42240 | AE26: =SUM(AE23:AE25) -> -57045 | AF26: =SUM(AF23:AF25) -> -232986 | AG26: -59042 | AH26: =SUM(AH23:AH25) -> -68543 | AI26: =SUM(AI23:AI25) -> -78756 | AJ26: =SUM(AJ23:AJ25) -> -118276 | AK26: =SUM(AK23:AK25) -> -324617 | AL26: =SUM(AL23:AL25) -> -122252 | AM26: =SUM(AM23:AM25) -> -112366 | AN26: =SUM(AN23:AN25) -> -137777 | AO26: =SUM(AO23:AO25) -> -245269 | ... AV26: =SUM(AV23:AV25) -> -95156 | AW26: -116478 | AX26: =SUM(AX23:AX25) -> -99186 | AY26: =SUM(AY23:AY25) -> -124753 | AZ26: =SUM(AV26:AY26) -> -435573 | BA26: =SUM(BA23:BA25) -> -139991 | BB26: =SUM(BB23:BB25) -> -151371 | BC26: =SUM(BC23:BC25) -> -144566 | BD26: =SUM(BD23:BD25) -> -142347 | BE26: =SUM(BA26:BD26) -> -578275 | BF26: =SUM(BF23:BF25) -> -146281 | BG26: =SUM(BG23:BG25) -> -117042
A27: Lucro (Prejuízo) antes do Imp. de Renda e da CS | B27: Earnings After Financial Results | C27: =C20+C26 -> 21801.773 | D27: =D20+D26 -> 81898.084 | E27: =E20+E26 -> 27498.103 | F27: =F20+F26 -> 1644.1653 | G27: =SUM(C27:F27) -> 132842.13 | H27: =H20+H26 -> 55687.071 | I27: =I20+I26 -> 20185.001 | J27: =J20+J26 -> 28224.251 | K27: =K20+K26 -> 30735.611 | L27: =SUM(H27:K27) -> 134831.94 | M27: =M20+M26 -> 47567.098 | N27: =N20+N26 -> 71817.284 | O27: =O20+O26 -> -4937.4214 | P27: =P20+P26 -> 34900.725 | Q27: =SUM(M27:P27) -> 149347.68 | R27: =R20+R26 -> 82520.889 | S27: =S20+S26 -> 125144.45 | T27: =T20+T26 -> 170573.1 | U27: =U20+U26 -> 102435.02 | V27: =SUM(R27:U27) -> 480673.46 | W27: =W20+W26 -> 65963.433 | X27: =X20+X26 -> 151948.05 | Y27: =Y20+Y26 -> 202632.28 | Z27: =Z20+Z26 -> 85806.203 | AA27: =SUM(W27:Z27) -> 506349.97 | AB27: 35916.298 | AC27: =AC20+AC26 -> -416155.3 | AD27: =AD20+AD26 -> 29239.354 | AE27: =AE20+AE26 -> -66707 | AF27: =SUM(AB27:AE27) -> -417706.65 | AG27: 164039 | AH27: =AH20+AH26 -> 385747.52 | AI27: =AI20+AI26 -> 275907.7 | AJ27: =AJ20+AJ26 -> 131173 | AK27: =SUM(AG27:AJ27) -> 956867.21 | AL27: =AL20+AL26 -> 297649.02 | AM27: =AM20+AM26 -> 301529.23 | AN27: =AN20+AN26 -> 107719.72 | AO27: =AO20+AO26 -> -78878.49 | AP27: =SUM(AL27:AO27) -> 628019.48 | AQ27: =AQ20+AQ26 -> 33871.097 | AR27: =AR20+AR26 -> 123217.07 | AS27: =AS20+AS26 -> 78975.078 | AT27: =AT20+AT26 -> 28636.274 | AU27: =SUM(AQ27:AT27) -> 264699.52 | AV27: =AV20+AV26 -> 105733.76 | AW27: 149955 | AX27: =AX20+AX26 -> 207378 | AY27: =AY20+AY26 -> 122396 | AZ27: =SUM(AV27:AY27) -> 585462.76 | BA27: =BA20+BA26 -> 77038 | BB27: =BB20+BB26 -> 155485 | BC27: =BC20+BC26 -> 77346 | BD27: =BD20+BD26 -> 53770 | BE27: =SUM(BA27:BD27) -> 363639 | BF27: =BF20+BF26 -> 72542 | BG27: =BG20+BG26 -> 166671
C28: =C27/C5 -> 0.014016501 | D28: =D27/D5 -> 0.049186416 | E28: =E27/E5 -> 0.015359388 | F28: =F27/F5 -> 0.00089568437 | G28: =G27/G5 -> 0.019403049 | H28: =H27/H5 -> 0.0312435 | I28: =I27/I5 -> 0.01146792 | J28: =J27/J5 -> 0.017689793 | ... AA28: =AA27/AA5 -> 0.050552117 | AB28: 0.016145349 | AC28: =AC27/AC5 -> -0.35512858 | AD28: =AD27/AD5 -> 0.011627114 | AE28: =AE27/AE5 -> -0.023410828 | AF28: =AF27/AF5 -> -0.047680315 | AG28: 0.052356838 | AH28: =AH27/AH5 -> 0.12115633 | AI28: =AI27/AI5 -> 0.076983647 | AJ28: =AJ27/AJ5 -> 0.034633958 | AK28: =AK27/AK5 -> 0.069903682 | AL28: =AL27/AL5 -> 0.069589836 | AM28: =AM27/AM5 -> 0.071923095 | AN28: =AN27/AN5 -> 0.024944712 | AO28: =AO27/AO5 -> -0.018961381 | ... AV28: =AV27/AV5 -> 0.029405072 | AW28: 0.039004382 | AX28: =AX27/AX5 -> 0.052073977 | AY28: =AY27/AY5 -> 0.031310484 | AZ28: =AZ27/AZ5 -> 0.03818614 | BA28: =BA27/BA5 -> 0.019562474 | BB28: =BB27/BB5 -> 0.037858829 | BC28: =BC27/BC5 -> 0.020341369 | BD28: =BD27/BD5 -> 0.015279388 | BE28: =BE27/BE5 -> 0.023664343 | ... BG28: =BG27/BG5 -> 0.041538254
A29: Imp. de Renda / Contrib. Social | B29: Income Taxes | C29: -12099.447 | D29: 1746.2678 | E29: -14932.497 | F29: 12292.3 | G29: =SUM(C29:F29) -> -12993.377 | H29: -32944 | I29: -5983.1559 | J29: -9933.8441 | K29: 3159 | L29: =SUM(H29:K29) -> -45702 | M29: -34646.521 | N29: -32522.366 | O29: -4448 | P29: 2478 | Q29: =SUM(M29:P29) -> -69138.886 | R29: -74940 | S29: -60029 | T29: -58279 | U29: 18716 | V29: =SUM(R29:U29) -> -174532 | W29: 15089 | X29: -21886 | Y29: -55824 | Z29: -22315 | AA29: =SUM(W29:Z29) -> -84936 | AB29: -5590 | AC29: 64469 | AD29: -34932 | AE29: -26154 | AF29: =SUM(AB29:AE29) -> -2207 | AG29: -86037 | AH29: -150726 | AI29: -71865 | AJ29: -21302 | AK29: =SUM(AG29:AJ29) -> -329930 | AL29: -108937 | AM29: -82338 | AN29: -18131 | AO29: -14442 | AP29: =SUM(AL29:AO29) -> -223848 | AQ29: -33469 | AR29: -41112 | AS29: -72542 | AT29: -11686 | AU29: =SUM(AQ29:AT29) -> -158809 | AV29: -23910 | AW29: -78459 | AX29: -77798 | AY29: ='P&L - Consolidado'!O24 -> -25212 | AZ29: =SUM(AV29:AY29) -> -205379 | BA29: ='P&L - Consolidado'!M24 -> -41506 | BB29: ='P&L - Consolidado'!L24 -> -45152 | BC29: ='P&L - Consolidado'!J24 -> -3850 | BD29: ='P&L - Consolidado'!H24 -> -55996 | BE29: =SUM(BA29:BD29) -> -146504 | BF29: ='P&L - Consolidado'!F24 -> -35437 | BG29: ='P&L - Consolidado'!E24 -> -43399
A30: Participação de Não Controladores | B30: Minority Shareholders | C30: -16380.681 | D30: -13403.283 | E30: -10131.915 | F30: -30567.121 | G30: =SUM(C30:F30) -> -70483 | H30: -15761 | I30: -21394.133 | J30: -13397.867 | K30: -17047 | L30: =SUM(H30:K30) -> -67600 | M30: -14170.89 | N30: -14724.602 | O30: -19336 | P30: -25574 | Q30: =SUM(M30:P30) -> -73805.492 | R30: -20547 | S30: -20981 | T30: -18815 | U30: -44474 | V30: =SUM(R30:U30) -> -104817 | W30: -17956 | X30: -19672 | Y30: -21970 | Z30: -24382 | AA30: =SUM(W30:Z30) -> -83980 | AB30: -21176 | AC30: -667 | AD30: -13184 | AE30: -36839 | AF30: =SUM(AB30:AE30) -> -71866 | AG30: -26500 | AH30: -20235 | AI30: -27027 | AJ30: -15955 | AK30: =SUM(AG30:AJ30) -> -89717 | AL30: -28506 | AM30: -28706 | AN30: -20201 | AO30: -47826 | AP30: =SUM(AL30:AO30) -> -125239 | AQ30: -16743 | AR30: -22745 | AS30: -11218 | AT30: -24452 | AU30: =SUM(AQ30:AT30) -> -75158 | AV30: -31567 | AW30: -34571 | AX30: -20408 | AY30: -28818 | AZ30: =SUM(AV30:AY30) -> -115364 | BA30: -24640 | BB30: =-'P&L - Consolidado'!L33 -> -23510 | BC30: =-'P&L - Consolidado'!J33 -> -38429 | BD30: =-'P&L - Consolidado'!H33 -> -32172 | BE30: =SUM(BA30:BD30) -> -118751 | BF30: =-'P&L - Consolidado'!F33 -> -33185 | BG30: =-'P&L - Consolidado'!E33 -> -36403
A32: Lucro Líquido (Prejuízo) | B32: Net Income (Loss) | C32: =C27+C29+C30 -> -6678.3554 | D32: =D27+D29+D30 -> 70241.068 | E32: =E27+E29+E30 -> 2433.691 | F32: =F27+F29+F30 -> -16630.655 | G32: =SUM(C32:F32) -> 49365.749 | H32: =H27+H29+H30 -> 6982.0714 | I32: =I27+I29+I30 -> -7192.2873 | J32: =J27+J29+J30 -> 4892.54 | K32: =K27+K29+K30 -> 16847.611 | L32: =SUM(H32:K32) -> 21529.935 | M32: =M27+M29+M30 -> -1250.3134 | N32: =N27+N29+N30 -> 24570.316 | O32: =O27+O29+O30 -> -28721.421 | P32: =P27+P29+P30 -> 11804.725 | Q32: =SUM(M32:P32) -> 6403.3058 | R32: =R27+R29+R30 -> -12966.111 | S32: =S27+S29+S30 -> 44134.451 | T32: =T27+T29+T30 -> 93479.1 | U32: =U27+U29+U30 -> 76677.02 | V32: =SUM(R32:U32) -> 201324.46 | W32: =W27+W29+W30 -> 63096.433 | X32: =X27+X29+X30 -> 110390.05 | Y32: =Y27+Y29+Y30 -> 124838.28 | Z32: =Z27+Z29+Z30 -> 39109.203 | AA32: =SUM(W32:Z32) -> 337433.97 | AB32: 9150.2979 | AC32: =AC27+AC29+AC30 -> -352353.3 | AD32: =AD27+AD29+AD30 -> -18876.646 | AE32: =AE27+AE29+AE30 -> -129700 | AF32: =SUM(AB32:AE32) -> -491779.65 | AG32: 51502 | AH32: =AH27+AH29+AH30 -> 214786.52 | AI32: =AI27+AI29+AI30 -> 177015.7 | AJ32: =AJ27+AJ29+AJ30 -> 93916 | AK32: =SUM(AG32:AJ32) -> 537220.21 | AL32: =AL27+AL29+AL30 -> 160206.02 | AM32: =AM27+AM29+AM30 -> 190485.23 | AN32: =AN27+AN29+AN30 -> 69387.722 | AO32: =AO27+AO29+AO30 -> -141146.49 | AP32: =SUM(AL32:AO32) -> 278932.48 | AQ32: =AQ27+AQ29+AQ30 -> -16340.903 | AR32: =AR27+AR29+AR30 -> 59360.073 | AS32: =AS27+AS29+AS30 -> -4784.9222 | AT32: =AT27+AT29+AT30 -> -7501.7261 | AU32: =SUM(AQ32:AT32) -> 30732.522 | AV32: =AV27+AV29+AV30 -> 50256.757 | AW32: 36925 | AX32: =AX27+AX29+AX30 -> 109172 | AY32: =AY27+AY29+AY30 -> 68366 | AZ32: =SUM(AV32:AY32) -> 264719.76 | BA32: =BA27+BA29+BA30 -> 10892 | BB32: =BB27+BB29+BB30 -> 86823 | BC32: =BC27+BC29+BC30 -> 35067 | BD32: =BD27+BD29+BD30 -> -34398 | BE32: =BE27+BE29+BE30 -> 98384 | BF32: =BF27+BF29+BF30 -> 3920 | BG32: =BG27+BG29+BG30 -> 86869
C33: =C32/C5 -> -0.0042935579 | D33: =D32/D5 -> 0.042185436 | E33: =E32/E5 -> 0.0013593666 | F33: =F32/F5 -> -0.0090598056 | G33: =G32/G5 -> 0.007210409 | H33: =H32/H5 -> 0.0039173249 | I33: =I32/I5 -> -0.004086231 | J33: =J32/J5 -> 0.0030664417 | ... AA33: =AA32/AA5 -> 0.033688165 | AB33: 0.0041133069 | AC33: =AC32/AC5 -> -0.30068277 | AD33: =AD32/AD5 -> -0.0075063529 | AE33: =AE32/AE5 -> -0.045518227 | AF33: =AF32/AF5 -> -0.056135589 | AG33: 0.016438054 | AH33: =AH32/AH5 -> 0.067460568 | AI33: =AI32/AI5 -> 0.049390844 | AJ33: =AJ32/AJ5 -> 0.024796893 | AK33: =AK32/AK5 -> 0.039246481 | AL33: =AL32/AL5 -> 0.037455896 | AM33: =AM32/AM5 -> 0.045436017 | AN33: =AN32/AN5 -> 0.016068151 | AO33: =AO32/AO5 -> -0.033929812 | ... AV33: =AV32/AV5 -> 0.013976648 | AW33: 0.0096044601 | AX33: =AX32/AX5 -> 0.027413806 | AY33: =AY32/AY5 -> 0.017488909 | AZ33: =AZ32/AZ5 -> 0.017266044 | BA33: =BA32/BA5 -> 0.0027658359 | BB33: =BB32/BB5 -> 0.021140413 | BC33: =BC32/BC5 -> 0.0092223357 | BD33: =BD32/BD5 -> -0.0097746027 | BE33: =BE32/BE5 -> 0.0064024835 | ... BG33: =BG32/BG5 -> 0.021649757
A34: EBITDA | B34: EBITDA | C34: 139833.52 | D34: 242501.9 | E34: 204669.95 | F34: 164061.6 | G34: =SUM(C34:F34) -> 751066.97 | H34: 236295.42 | I34: 179570.95 | J34: 191109.14 | K34: 189249.51 | L34: =SUM(H34:K34) -> 796225.02 | M34: 185393.84 | N34: 194139.02 | O34: 220254.57 | P34: 198765.91 | Q34: =SUM(M34:P34) -> 798553.34 | R34: 227112.85 | S34: 275408.5 | T34: 311999.73 | U34: 242554.66 | V34: =SUM(R34:U34) -> 1057075.7 | W34: 242587.39 | X34: 304247.27 | Y34: 333779.69 | Z34: 215195.55 | AA34: =SUM(W34:Z34) -> 1095809.9 | AB34: 204967.46 | AC34: -199515.39 | AD34: 207676.01 | AE34: 159011.44 | AF34: =SUM(AB34:AE34) -> 372139.51 | AG34: 367938.26 | AH34: 592729.23 | AI34: 489861.86 | AJ34: 390803.28 | AK34: =SUM(AG34:AJ34) -> 1841332.6 | AL34: 548151.67 | AM34: 534572.73 | AN34: 362701.61 | AO34: 291488.72 | AP34: =SUM(AL34:AO34) -> 1736914.7 | AQ34: 286760.45 | AR34: 363406.6 | AS34: 313322.08 | AT34: 289375.03 | AU34: =SUM(AQ34:AT34) -> 1252864.2 | AV34: 316641.76 | AW34: 388931 | AX34: 440235 | AY34: 378263 | AZ34: =SUM(AV34:AY34) -> 1524070.8 | BA34: 354362.01 | BB34: 450478.87 | BC34: ='Indicadores | KPI'!BD6 -> 360435 | BD34: ='Indicadores | KPI'!BE6 -> 328178 | BE34: =SUM(BA34:BD34) -> 1493453.9 | BF34: ='Indicadores | KPI'!BG6 -> 357046 | BG34: ='Indicadores | KPI'!BH6 -> 417527
C35: =C34/C5 -> 0.089899878 | D35: =D34/D5 -> 0.14564198 | E35: =E34/E5 -> 0.1143208 | F35: =F34/F5 -> 0.089375081 | G35: =G34/G5 -> 0.10970157 | H35: =H34/H5 -> 0.13257468 | I35: =I34/I5 -> 0.10202156 | J35: =J34/J5 -> 0.1197793 | ... AA35: =AA34/AA5 -> 0.10940163 | AB35: 0.092138425 | AC35: =AC34/AC5 -> -0.17025764 | AD35: =AD34/AD5 -> 0.082582965 | AE35: =AE34/AE5 -> 0.055805079 | AF35: =AF34/AF5 -> 0.042478925 | AG35: 0.117436 | AH35: =AH34/AH5 -> 0.18616555 | AI35: =AI34/AI5 -> 0.13668105 | AJ35: =AJ34/AJ5 -> 0.10318484 | AK35: =AK34/AK5 -> 0.13451807 | AL35: =AL34/AL5 -> 0.12815693 | AM35: =AM34/AM5 -> 0.12751044 | AN35: =AN34/AN5 -> 0.083991 | AO35: =AO34/AO5 -> 0.070070162 | ... AV35: =AV34/AV5 -> 0.088059612 | AW35: 0.10116377 | AX35: =AX34/AX5 -> 0.1105459 | AY35: =AY34/AY5 -> 0.09676458 | AZ35: =AZ34/AZ5 -> 0.099405775 | BA35: =BA34/BA5 -> 0.089984132 | BB35: =BB34/BB5 -> 0.10968648 | BC35: =BC34/BC5 -> 0.094791472 | BD35: =BD34/BD5 -> 0.0932557 | BE35: =BE34/BE5 -> 0.097188708 | ... BG35: =BG34/BG5 -> 0.10405735

Sheet Receita - Revenue
A1: Consolidado | B1: Consolidated
C2: 1Q15 | D2: 2Q15 | E2: 3Q15 | F2: 4Q15 | G2: 2015 | H2: 1Q16 | I2: 2Q16 | J2: 3Q16 | K2: 4Q16 | L2: 2016 | M2: 1Q17 | N2: 2Q17 | O2: 3Q17 | P2: 4Q17 | Q2: 2017 | R2: 1Q18 | S2: 2Q18 | T2: 3Q18 | U2: 4Q18 | V2: 2018 | W2: 1Q19 | X2: 2Q19 | Y2: 3Q19 | Z2: 4Q19 | AA2: 2019 | AB2: 1Q20 | AC2: 2Q20 | AD2: 3Q20 | AE2: 4Q20 | AF2: 2020 | AG2: 1Q21 | AH2: 2Q21 | AI2: 3Q21 | AJ2: 4Q21 | AK2: 2021 | AL2: 1Q22 | AM2: 2Q22 | AN2: 3Q22 | AO2: 4Q22 | AP2: 2022 | AQ2: 1Q23 | AR2: 2Q23 | AS2: 3Q23 | AT2: 4Q23 | AU2: 2023 | AV2: 1Q24 | AW2: 2Q24 | AX2: 3Q24 | AY2: 4Q24 | AZ2: 2024 | BA2: 1Q25 | BB2: 2Q25 | BC2: 3Q25 | BD2: 4Q25 | BE2: 2025 | BF2: 1Q26 | BG2: 2Q26
A3: Receita Operacional Líquida - R$ mil | B3: Net Operating Revenue- R$ thousand | C3: 1T15 | D3: 2T15 | E3: 3T15 | F3: 4T15 | G3: 2015 | H3: 1T16 | I3: 2T16 | J3: 3T16 | K3: 4T16 | L3: 2016 | M3: 1T17 | N3: 2T17 | O3: 3T17 | P3: 4T17 | Q3: 2017 | R3: 1T18 | S3: 2T18 | T3: 3T18 | U3: 4T18 | V3: 2018 | W3: 1T19 | X3: 2T19 | Y3: 3T19 | Z3: 4T19 | AA3: 2019 | AB3: 1T20 | AC3: 2T20 | AD3: 3T20 | AE3: 4T20 | AF3: 2020 | AG3: 1T21 | AH3: 2T21 | AI3: 3T21 | AJ3: 4T21 | AK3: 2021 | AL3: 1T22 | AM3: 2T22 | AN3: 3T22 | AO3: 4T22 | AP3: 2022 | AQ3: 1T23 | AR3: 2T23 | AS3: 3T23 | AT3: 4T23 | AU3: 2023 | AV3: 1T24 | AW3: 2T24 | AX3: 3T24 | AY3: 4T24 | AZ3: 2024 | BA3: 1T25 | BB3: 2T25 | BC3: 3T25 | BD3: 4T25 | BE3: 2025 | BF3: 1T26 | BG3: 2T26
A4: Rodas Alumínio (Veículos Leves) | B4: Aluminum Wheels (Light vehicles) | C4: 55826.718 | D4: 51406.334 | E4: 45925.259 | F4: 45857.582 | G4: 199015.89 | H4: 64556.254 | I4: 77321.594 | J4: 86827.66 | K4: 83670.502 | L4: 312376.01 | M4: 95863.583 | N4: 96598.923 | O4: 103304.59 | P4: 99676.893 | Q4: 395443.99 | R4: 124153.39 | S4: 131893.76 | T4: 128774.13 | U4: 115297.1 | V4: 500118.37 | W4: 128353.3 | X4: 128200.67 | Y4: 132201.9 | Z4: 98378.282 | AA4: 487134.15 | AB4: 83410.737 | AC4: 16630.592 | AD4: 85530.498 | AE4: 108157.48 | AF4: 293729.31 | AG4: 113754.44 | AH4: 127555.91 | AI4: 146455.94 | AJ4: 126539.64 | AK4: =SUM(AG4:AJ4) -> 514305.92 | AL4: 127475.65 | AM4: 142561.86 | AN4: 185289.02 | AO4: 145037.5 | AP4: =SUM(AL4:AO4) -> 600364.03 | AQ4: 163406.36 | AR4: 168729.99 | AS4: 175382.85 | AT4: 160190.46 | AU4: =SUM(AQ4:AT4) -> 667709.66 | AV4: 163394.69 | AW4: 182932.1 | AX4: 222634.44 | AY4: 214167.85 | AZ4: =SUM(AV4:AY4) -> 783129.08 | BA4: 226790.48 | BB4: 262871 | BC4: 263219 | BD4: 221455 | BE4: =SUM(BA4:BD4) -> 974335.48 | BF4: 241468 | BG4: 295494
A5: Rodas Aço (Veículos Leves) | B5: Steel Wheels (Light vehicles) | C5: 86091.388 | D5: 77419.531 | E5: 75153.514 | F5: 65774.839 | G5: 304439.27 | H5: 59818.323 | I5: 62127.665 | J5: 69106.489 | K5: 77518.81 | L5: 268571.29 | M5: 80416.907 | N5: 93925.839 | O5: 99338.179 | P5: 102702.66 | Q5: 376383.59 | R5: 99069.386 | S5: 105517.08 | T5: 110520.82 | U5: 97538.081 | V5: 412645.36 | W5: 106924.05 | X5: 127513.61 | Y5: 129235.29 | Z5: 99418.607 | AA5: 463091.56 | AB5: 92178.857 | AC5: 19156.332 | AD5: 93941.46 | AE5: 93076.701 | AF5: 298353.35 | AG5: 94939.348 | AH5: 112655.05 | AI5: 104828.07 | AJ5: 114536.84 | AK5: =SUM(AG5:AJ5) -> 426959.31 | AL5: 127454.01 | AM5: 150685.7 | AN5: 176694.32 | AO5: 135961.37 | AP5: =SUM(AL5:AO5) -> 590795.39 | AQ5: 136872.3 | AR5: 150553.86 | AS5: 161730.19 | AT5: 131773.19 | AU5: =SUM(AQ5:AT5) -> 580929.55 | AV5: 132047.02 | AW5: 136812.83 | AX5: 164831.33 | AY5: 146000.07 | AZ5: =SUM(AV5:AY5) -> 579691.25 | BA5: 132684.03 | BB5: 145772 | BC5: 181207 | BD5: 147606 | BE5: =SUM(BA5:BD5) -> 607269.03 | BF5: 149936 | BG5: 166699
A6: Rodas Aço (Veículos Comerciais) | B6: Steel Wheels (Commercial vehicles) | C6: 95298.834 | D6: 79696.223 | E6: 78127.409 | F6: 46507.35 | G6: 299629.82 | H6: 61136.574 | I6: 72734.943 | J6: 84326.806 | K6: 76884.65 | L6: 295082.97 | M6: 82579.905 | N6: 107693.61 | O6: 119111.54 | P6: 93763.767 | Q6: 403148.83 | R6: 127748.15 | S6: 134414.59 | T6: 158953.39 | U6: 145584.45 | V6: 566700.57 | W6: 153568 | X6: 174301.93 | Y6: 181888.91 | Z6: 140410.61 | AA6: 650169.45 | AB6: 126965.31 | AC6: 75193.895 | AD6: 168498.38 | AE6: 183865.6 | AF6: 554523.18 | AG6: 242798.07 | AH6: 275929.33 | AI6: 370919.39 | AJ6: 361028.53 | AK6: =SUM(AG6:AJ6) -> 1250675.3 | AL6: 394994.83 | AM6: 399312.15 | AN6: 420374.53 | AO6: 355379.32 | AP6: =SUM(AL6:AO6) -> 1570060.8 | AQ6: 288711.05 | AR6: 263324.2 | AS6: 255887.05 | AT6: 217163.73 | AU6: =SUM(AQ6:AT6) -> 1025086 | AV6: 242314.76 | AW6: 267040.95 | AX6: 280967.81 | AY6: 236546.2 | AZ6: =SUM(AV6:AY6) -> 1026869.7 | BA6: 235906.04 | BB6: 253852 | BC6: 248267 | BD6: 144060 | BE6: =SUM(BA6:BD6) -> 882085.04 | BF6: 198324 | BG6: 207281
A7: Comp. Estruturais (Veículos Leves) | B7: Structural Components (Light vehicles) | C7: 40363.381 | D7: 34789.908 | E7: 37781.839 | F7: 39295.597 | G7: 152230.72 | H7: 36783.019 | I7: 33576.174 | J7: 31535.434 | K7: 40634.134 | L7: 142528.76 | M7: 38943.069 | N7: 40239.606 | O7: 42229.592 | P7: 44369.981 | Q7: 165782.25 | R7: 45447.796 | S7: 47932.099 | T7: 38424.19 | U7: 34089.412 | V7: 165893.5 | W7: 37994.363 | X7: 55877.182 | Y7: 47728.539 | Z7: 51413.113 | AA7: 193013.2 | AB7: 39538.184 | AC7: 14437.726 | AD7: 54943.615 | AE7: 58059.968 | AF7: 166979.49 | AG7: 64791.642 | AH7: 90402.496 | AI7: 111407.28 | AJ7: 75705.886 | AK7: =SUM(AG7:AJ7) -> 342307.3 | AL7: 101866.82 | AM7: 112573.03 | AN7: 127900.73 | AO7: 118183.36 | AP7: =SUM(AL7:AO7) -> 460523.95 | AQ7: 114473.51 | AR7: 115560.93 | AS7: 123975.95 | AT7: 113081.21 | AU7: =SUM(AQ7:AT7) -> 467091.59 | AV7: 102806.91 | AW7: 114782.3 | AX7: 124815.21 | AY7: 125568.69 | AZ7: =SUM(AV7:AY7) -> 467973.11 | BA7: 114125.01 | BB7: 127840 | BC7: 134215 | BD7: 130597 | BE7: =SUM(BA7:BD7) -> 506777.01 | BF7: 119229 | BG7: 121304
A8: Comp. Estruturais (Veículos Comerciais) | B8: Structural Components (Commercial vehicles) | C8: 127634.44 | D8: 110636.92 | E8: 86980.481 | F8: 70049.061 | G8: 395300.9 | H8: 87087.919 | I8: 100373.89 | J8: 96446.381 | K8: 97788.664 | L8: 381696.86 | M8: 97232.561 | N8: 118669.37 | O8: 136190.94 | P8: 138473.89 | Q8: 490566.75 | R8: 161369.2 | S8: 159558.9 | T8: 190171.09 | U8: 212994.05 | V8: 724093.23 | W8: 177666.73 | X8: 254171.68 | Y8: 231663.79 | Z8: 224006 | AA8: 887508.2 | AB8: 172629.47 | AC8: 52179.132 | AD8: 178119.39 | AE8: 218552.48 | AF8: 621480.47 | AG8: 268303 | AH8: 328999.85 | AI8: 431475.43 | AJ8: 419685.76 | AK8: =SUM(AG8:AJ8) -> 1448464 | AL8: 443102.8 | AM8: 467558.07 | AN8: 527852.76 | AO8: 506447.07 | AP8: =SUM(AL8:AO8) -> 1944960.7 | AQ8: 322144.64 | AR8: 308928.59 | AS8: 296337.21 | AT8: 279039.06 | AU8: =SUM(AQ8:AT8) -> 1206449.5 | AV8: 335321.59 | AW8: 367842.02 | AX8: 407291.27 | AY8: 392927.61 | AZ8: =SUM(AV8:AY8) -> 1503382.5 | BA8: 331454.69 | BB8: 405024 | BC8: 404903 | BD8: 287366 | BE8: =SUM(BA8:BD8) -> 1428747.7 | BF8: 329078 | BG8: 349236
A9: América do Sul | B9: South America | C9: =SUM(C4:C8) -> 405214.76 | D9: =SUM(D4:D8) -> 353948.91 | E9: =SUM(E4:E8) -> 323968.5 | F9: =SUM(F4:F8) -> 267484.43 | G9: =SUM(G4:G8) -> 1350616.6 | H9: =SUM(H4:H8) -> 309382.09 | I9: =SUM(I4:I8) -> 346134.27 | J9: =SUM(J4:J8) -> 368242.77 | ... AU9: =SUM(AU4:AU8) -> 3947266.3 | AV9: =SUM(AV4:AV8)+1 -> 975885.97 | AW9: =SUM(AW4:AW8) -> 1069410.2 | AX9: =SUM(AX4:AX8)-1 -> 1200539.1 | AY9: =SUM(AY4:AY8) -> 1115210.4 | AZ9: =SUM(AV9:AY9) -> 4361045.6 | BA9: =SUM(BA4:BA8) -> 1040960.2 | BB9: =SUM(BB4:BB8) -> 1195359 | BC9: =SUM(BC4:BC8) -> 1231811 | BD9: =SUM(BD4:BD8) -> 931084 | BE9: =SUM(BE4:BE8) -> 4399214.2 | BF9: =SUM(BF4:BF8) -> 1038035 | BG9: =SUM(BG4:BG8) -> 1140014
C10: =C9/C$27 -> 0.26051519 | D10: =D9/D$27 -> 0.21257492 | E10: =E9/E$27 -> 0.18095642 | F10: =F9/F$27 -> 0.14571628 | G10: =G9/G$27 -> 0.19727238 | H10: =H9/H$27 -> 0.17358029 | I10: =I9/I$27 -> 0.19665298 | J10: =J9/J$27 -> 0.2307994 | ... BG10: =BG9/BG$27 -> 0.28411776
A11: Rodas Alumínio (Veículos Leves) | B11: Aluminum Wheels (Light vehicles) | C11: 53275.1 | D11: 63877.322 | E11: 82085.679 | F11: 83012.251 | G11: 282250.35 | H11: 86654.425 | I11: 72616.156 | J11: 67056.831 | K11: 65454.116 | L11: 291781.53 | M11: 68516.393 | N11: 72898.644 | O11: 57623.205 | P11: 61361.504 | Q11: 260399.75 | R11: 62973.433 | S11: 81461.696 | T11: 114428.03 | U11: 103342.65 | V11: 362205.81 | W11: 111241.08 | X11: 119366.2 | Y11: 109273.06 | Z11: 96133.624 | AA11: 436013.97 | AB11: 101482.63 | AC11: 41140.64 | AD11: 117717 | AE11: 120970.98 | AF11: 381311.24 | AG11: 129983.69 | AH11: 103211.49 | AI11: 128707.25 | AJ11: 156471.69 | AK11: =SUM(AG11:AJ11) -> 518374.13 | AL11: 148343.43 | AM11: 143272.89 | AN11: 143074.17 | AO11: 117387.86 | AP11: =SUM(AL11:AO11) -> 552078.35 | AQ11: 161443.34 | AR11: 158063.15 | AS11: 159105.48 | AT11: 155776.73 | AU11: =SUM(AQ11:AT11) -> 634388.7 | AV11: 155580.92 | AW11: 162880.51 | AX11: 179724.61 | AY11: 166325.52 | AZ11: =SUM(AV11:AX11) -> 498186.03 | BA11: 155636.23 | BB11: 147141 | BC11: 145961 | BD11: 129678 | BE11: =SUM(BA11:BD11) -> 578416.23 | BF11: 201616 | BG11: 193933
A12: Rodas Aço (Veículos Leves) | B12: Steel Wheels (Light vehicles) | C12: 244123 | D12: 260693.21 | E12: 294548.31 | F12: 299216.05 | G12: 1098580.6 | H12: 291770.43 | I12: 272197.77 | J12: 252003.82 | K12: 262169.23 | L12: 1078141.2 | M12: 248823.73 | N12: 262123.37 | O12: 245239.5 | P12: 238714.54 | Q12: 994901.14 | R12: 246005.45 | S12: 280931.49 | T12: 323004.35 | U12: 313664.76 | V12: 1163606.1 | W12: 276063.8 | X12: 277832.01 | Y12: 289028.31 | Z12: 250178.21 | AA12: 1093102.3 | AB12: 254896.64 | AC12: 100027.78 | AD12: 340541.09 | AE12: 346120.77 | AF12: 1041586.3 | AG12: 369418.66 | AH12: 305202.28 | AI12: 407144.36 | AJ12: 461827.7 | AK12: =SUM(AG12:AJ12) -> 1543593 | AL12: 503922.51 | AM12: 472172.43 | AN12: 411485.75 | AO12: 371550.91 | AP12: =SUM(AL12:AO12) -> 1759131.6 | AQ12: 351310.91 | AR12: 361344.85 | AS12: 414048.25 | AT12: 332993.36 | AU12: =SUM(AQ12:AT12) -> 1459697.4 | AV12: 348859.57 | AW12: 445102.02 | AX12: 420112.73 | AY12: 377114.95 | AZ12: =SUM(AV12:AX12) -> 1214074.3 | BA12: 386922.32 | BB12: 455338 | BC12: 444008 | BD12: 383787 | BE12: =SUM(BA12:BD12) -> 1670055.3 | BF12: 362125 | BG12: 397656
A13: Rodas Aço (Veículos Comerciais) | B13: Steel Wheels (Commercial vehicles) | C13: 54757.897 | D13: 70142.725 | E13: 78374.825 | F13: 63410.083 | G13: 266685.53 | H13: 69068.161 | I13: 62434.891 | J13: 52766.802 | K13: 57591.806 | L13: 241861.66 | M13: 53180.707 | N13: 60510.454 | O13: 55112.663 | P13: 52423.354 | Q13: 221227.18 | R13: 64059.766 | S13: 81495.956 | T13: 99096.902 | U13: 92088.438 | V13: 336741.06 | W13: 96754.317 | X13: 105344.67 | Y13: 104080.19 | Z13: 78235.225 | AA13: 384414.4 | AB13: 78320.672 | AC13: 64523.784 | AD13: 86864.93 | AE13: 79960.791 | AF13: 309670.18 | AG13: 91487.891 | AH13: 98214.066 | AI13: 99802.771 | AJ13: 106363.45 | AK13: =SUM(AG13:AJ13) -> 395868.18 | AL13: 117452.6 | AM13: 120117.39 | AN13: 125619.58 | AO13: 90704.863 | AP13: =SUM(AL13:AO13) -> 453894.43 | AQ13: 95520.24 | AR13: 90849.811 | AS13: 91533.286 | AT13: 78466.728 | AU13: =SUM(AQ13:AT13) -> 356370.06 | AV13: 88311.189 | AW13: 98481.629 | AX13: 95178.626 | AY13: 72332.593 | AZ13: =SUM(AV13:AX13) -> 281971.44 | BA13: 104175.74 | BB13: 104795 | BC13: 101486 | BD13: 73068 | BE13: =SUM(BA13:BD13) -> 383524.74 | BF13: 79240 | BG13: 101080
A14: Comp. Estruturais (Veículos Comerciais) | B14: Structural Components (Commercial vehicles) | C14: 147943.92 | D14: 174442.39 | E14: 183499.4 | F14: 192858.05 | G14: 698743.75 | H14: 164011.53 | I14: 135064.12 | J14: 113935.66 | K14: 119573.6 | L14: 532584.9 | M14: 138093.56 | N14: 171087.77 | O14: 180757.8 | P14: 160617.13 | Q14: 650556.27 | R14: 188842.89 | S14: 229640.73 | T14: 309280.17 | U14: 221734.46 | V14: 949498.25 | W14: 293325.19 | X14: 322880.5 | Y14: 299885.63 | Z14: 213185.03 | AA14: 1129276.3 | AB14: 233162 | AC14: 138438.39 | AD14: 252292.99 | AE14: 245558.89 | AF14: 869452.27 | AG14: 278553 | AH14: 337755.91 | AI14: 429152.38 | AJ14: 418602.53 | AK14: =SUM(AG14:AJ14) -> 1464063.8 | AL14: 561996.04 | AM14: 537796.04 | AN14: 561455.28 | AO14: 572083.59 | AP14: =SUM(AL14:AO14) -> 2233330.9 | AQ14: 538166.77 | AR14: 446993.65 | AS14: 446152.62 | AT14: 436593.96 | AU14: =SUM(AQ14:AT14) -> 1867907 | AV14: 469229.18 | AW14: 494976.05 | AX14: 544900.72 | AY14: 464603.89 | AZ14: =SUM(AV14:AX14) -> 1509105.9 | BA14: 423778.31 | BB14: 336349 | BC14: 238695 | BD14: 245874 | BE14: =SUM(BA14:BD14) -> 1244696.3 | BF14: 307665 | BG14: 345139
A15: América do Norte | B15: North America | C15: =SUM(C11:C14) -> 500099.91 | D15: =SUM(D11:D14) -> 569155.64 | E15: =SUM(E11:E14) -> 638508.22 | F15: =SUM(F11:F14) -> 638496.44 | G15: =SUM(G11:G14) -> 2346260.2 | H15: =SUM(H11:H14) -> 611504.54 | I15: =SUM(I11:I14) -> 542312.94 | J15: =SUM(J11:J14) -> 485763.11 | ... AU15: =SUM(AU11:AU14) -> 4318363.1 | AV15: =SUM(AV11:AV14)-1 -> 1061979.8 | AW15: =SUM(AW11:AW14) -> 1201440.2 | AX15: =SUM(AX11:AX14)+1 -> 1239917.7 | AY15: =SUM(AY11:AY14) -> 1080376.9 | AZ15: =SUM(AV15:AX15) -> 3503337.7 | BA15: =SUM(BA11:BA14) -> 1070512.6 | BB15: =SUM(BB11:BB14) -> 1043623 | BC15: =SUM(BC11:BC14) -> 930150 | BD15: =SUM(BD11:BD14) -> 832407 | BE15: =SUM(BE11:BE14) -> 3876692.6 | BF15: =SUM(BF11:BF14) -> 950646 | BG15: =SUM(BG11:BG14) -> 1037808
C16: =C15/C$27 -> 0.32151747 | D16: =D15/D$27 -> 0.34182394 | E16: =E15/E$27 -> 0.35664628 | F16: =F15/F$27 -> 0.34783081 | G16: =G15/G$27 -> 0.34269705 | H16: =H15/H$27 -> 0.34308753 | I16: =I15/I$27 -> 0.30811008 | J16: =J15/J$27 -> 0.3044563 | ... BG16: =BG15/BG$27 -> 0.25864567
A17: Rodas Alumínio (Veículos Leves) | B17: Aluminum Wheels (Light vehicles) | C17: 248710.2 | D17: 290526.22 | E17: 325938.01 | F17: 351251.34 | G17: 1216425.8 | H17: 338233.24 | I17: 343067.95 | J17: 291502.2 | K17: 345182.32 | L17: 1317985.7 | M17: 330407.16 | N17: 352205.15 | O17: 355061.05 | P17: 396406.67 | Q17: 1434080 | R17: 421216.15 | S17: 460483.01 | T17: 457984.14 | U17: 443699.03 | V17: 1783382.3 | W17: 445823.69 | X17: 441063.97 | Y17: 416771.87 | Z17: 462199.42 | AA17: 1765858.9 | AB17: 434454.6 | AC17: 249798.48 | AD17: 460201.06 | AE17: 534808.51 | AF17: 1679262.7 | AG17: 533486.93 | AH17: 516146.04 | AI17: 420969.3 | AJ17: 510036.95 | AK17: =SUM(AG17:AJ17) -> 1980639.2 | AL17: 562153.44 | AM17: 593709.48 | AN17: 597017.63 | AO17: 683953.29 | AP17: =SUM(AL17:AO17) -> 2436833.8 | AQ17: 682080.45 | AR17: 675394.72 | AS17: 562619.25 | AT17: 539782.76 | AU17: =SUM(AQ17:AT17) -> 2459877.2 | AV17: 581580.62 | AW17: 594550.64 | AX17: 591961.89 | AY17: 688796.04 | AZ17: =SUM(AV17:AX17) -> 1768093.1 | BA17: 734965.85 | BB17: 765300 | BC17: 673711 | BD17: 706370 | BE17: =SUM(BA17:BD17) -> 2880346.8 | BF17: 744105 | BG17: 752470
A18: Rodas Aço (Veículos Leves) | B18: Steel Wheels (Light vehicles) | C18: 156523.93 | D18: 177654.29 | E18: 208356.77 | F18: 266499.9 | G18: 809034.9 | H18: 213272.37 | I18: 214409.02 | J18: 186290.9 | K18: 200232.69 | L18: 814204.98 | M18: 179351.05 | N18: 199811.88 | O18: 210343.91 | P18: 221962.7 | Q18: 811469.53 | R18: 218079.24 | S18: 255283.16 | T18: 239059.93 | U18: 245998.97 | V18: 958421.31 | W18: 220617.17 | X18: 243228.14 | Y18: 225416.17 | Z18: 236500.6 | AA18: 925762.08 | AB18: 229434.01 | AC18: 186327.57 | AD18: 256661.76 | AE18: 313960.33 | AF18: 986383.67 | AG18: 288002.18 | AH18: 263464.52 | AI18: 287498.37 | AJ18: 310681.5 | AK18: =SUM(AG18:AJ18) -> 1149646.6 | AL18: 329746.47 | AM18: 334589.57 | AN18: 299896.2 | AO18: 308267.24 | AP18: =SUM(AL18:AO18) -> 1272499.5 | AQ18: 330487.6 | AR18: 321817.06 | AS18: 305693.5 | AT18: 356817.26 | AU18: =SUM(AQ18:AT18) -> 1314815.4 | AV18: 355103.84 | AW18: 351441.66 | AX18: 307973.07 | AY18: 361149.36 | AZ18: =SUM(AV18:AX18) -> 1014518.6 | BA18: 387433.3 | BB18: 377226 | BC18: 348437 | BD18: 361147 | BE18: =SUM(BA18:BD18) -> 1474243.3 | BF18: 360281 | BG18: 339662
A19: Rodas Aço (Veículos Comerciais) | B19: Steel Wheels (Commercial vehicles) | C19: 128288.9 | D19: 142702.31 | E19: 138592.67 | F19: 152734.1 | G19: 562317.98 | H19: 158293.16 | I19: 164439.94 | J19: 135292.31 | K19: 127192.87 | L19: 585218.28 | M19: 142321.32 | N19: 163508.17 | O19: 156031.2 | P19: 164837.69 | Q19: 626698.39 | R19: 186621.81 | S19: 198325.24 | T19: 196772.28 | U19: 189416.35 | V19: 771135.69 | W19: 192901.04 | X19: 178354.04 | Y19: 160685.93 | Z19: 162147.83 | AA19: 694088.86 | AB19: 187764.02 | AC19: 139872.02 | AD19: 204193.6 | AE19: 243966.33 | AF19: 775795.97 | AG19: 300299.19 | AH19: 291912.77 | AI19: 307154.69 | AJ19: 356182.81 | AK19: =SUM(AG19:AJ19) -> 1255549.5 | AL19: 425137.2 | AM19: 387719.13 | AN19: 344397 | AO19: 390316.19 | AP19: =SUM(AL19:AO19) -> 1547569.5 | AQ19: 439094.61 | AR19: 395115.24 | AS19: 326142.81 | AT19: 328430.12 | AU19: =SUM(AQ19:AT19) -> 1488782.8 | AV19: 307448.1 | AW19: 305185.13 | AX19: 281356.61 | AY19: 309170.27 | AZ19: =SUM(AV19:AX19) -> 893989.83 | BA19: 353134.4 | BB19: 382310 | BC19: 344277 | BD19: 365405 | BE19: =SUM(BA19:BD19) -> 1445126.4 | BF19: 393187 | BG19: 389787
A20: Europa | B20: Europe | C20: =SUM(C17:C19) -> 533523.02 | D20: =SUM(D17:D19) -> 610882.82 | E20: =SUM(E17:E19) -> 672887.45 | F20: =SUM(F17:F19) -> 770485.34 | G20: =SUM(G17:G19) -> 2587778.6 | H20: =SUM(H17:H19) -> 709798.77 | I20: =SUM(I17:I19) -> 721916.91 | J20: =SUM(J17:J19) -> 613085.42 | ... AU20: =SUM(AU17:AU19) -> 5263475.4 | AV20: =SUM(AV17:AV19)-1 -> 1244131.6 | AW20: =SUM(AW17:AW19) -> 1251177.4 | AX20: =SUM(AX17:AX19) -> 1181291.6 | AY20: =SUM(AY17:AY19) -> 1359115.7 | AZ20: =SUM(AV20:AX20) -> 3676600.5 | BA20: =SUM(BA17:BA19) -> 1475533.5 | BB20: =SUM(BB17:BB19) -> 1524836 | BC20: =SUM(BC17:BC19) -> 1366425 | BD20: =SUM(BD17:BD19) -> 1432922 | BE20: =SUM(BE17:BE19) -> 5799716.5 | BF20: =SUM(BF17:BF19) -> 1497573 | BG20: =SUM(BG17:BG19) -> 1481919
C21: =C20/C$27 -> 0.3430054 | D21: =D20/D$27 -> 0.36688449 | E21: =E20/E$27 -> 0.3758492 | F21: =F20/F$27 -> 0.4197338 | G21: =G20/G$27 -> 0.37797347 | H21: =H20/H$27 -> 0.39823598 | I21: =I20/I$27 -> 0.41015041 | J21: =J20/J$27 -> 0.38425668 | ... BG21: =BG20/BG$27 -> 0.36932837
A22: Rodas Alumínio (Veículos Leves) | B22: Aluminum Wheels (Light vehicles) | C22: 61365.781 | D22: 71970.106 | E22: 97043.098 | F22: 93637.614 | G22: 324016.6 | H22: 82233.343 | I22: 84507.346 | J22: 68905.93 | K22: 70561.629 | L22: 306208.25 | M22: 79705.34 | N22: 96505.992 | O22: 98910.276 | P22: 105078.03 | Q22: 374046.55 | R22: 127300.83 | S22: 139070.77 | T22: 160616.54 | U22: 156982.63 | V22: 583970.76 | W22: 149644.17 | X22: 150830.44 | Y22: 153705.34 | Z22: 146433.2 | AA22: 600613.14 | AB22: 132801.89 | AC22: 44414.639 | AD22: 139344.66 | AE22: 192925.8 | AF22: 509486.99 | AG22: 206260.8 | AH22: 211790.2 | AI22: 202231.51 | AJ22: 214630.38 | AK22: =SUM(AG22:AJ22) -> 834912.88 | AL22: 254874.22 | AM22: 184676.36 | AN22: 241020.28 | AO22: 224228.47 | AP22: =SUM(AL22:AO22) -> 904799.33 | AQ22: 226468.96 | AR22: 195792.84 | AS22: 210712.14 | AT22: 195849.44 | AU22: =SUM(AQ22:AT22) -> 828823.39 | AV22: 162311.16 | AW22: 167304.92 | AX22: 202252.67 | AY22: 180884.93 | AZ22: =SUM(AV22:AX22) -> 531868.75 | BA22: 194703.6 | BB22: 201712 | BC22: 134564 | BD22: 166576 | BE22: =SUM(BA22:BD22) -> 697555.6 | BF22: 173996 | BG22: 206937
A23: Rodas Aço (Veículos Leves) | B23: Steel Wheels (Light vehicles) | C23: 16170.097 | D23: 18109.868 | E23: 16273.421 | F23: 17096.691 | G23: 67650.077 | H23: 20310.378 | I23: 18021.825 | J23: 18331.908 | K23: 18753.75 | L23: 75417.861 | M23: 17429.212 | N23: 20302.062 | O23: 20680.288 | P23: 18001.022 | Q23: 82565.678 | R23: 16205.245 | S23: 22667.508 | T23: 22562.088 | U23: 17787.822 | V23: 79222.663 | W23: 21425.467 | X23: 23447.797 | Y23: 17595.339 | Z23: 22601.516 | AA23: 85070.119 | AB23: 21293.926 | AC23: 4894.6562 | AD23: 29992.536 | AE23: 43560.687 | AF23: 99741.804 | AG23: 50822.948 | AH23: 36682.442 | AI23: 41095.751 | AJ23: 45814.323 | AK23: =SUM(AG23:AJ23) -> 174415.46 | AL23: 58657.53 | AM23: 51834.178 | AN23: 57762.819 | AO23: 49841.251 | AP23: =SUM(AL23:AO23) -> 218095.78 | AQ23: 54701.685 | AR23: 44864.503 | AS23: 50250.07 | AT23: 44009.443 | AU23: =SUM(AQ23:AT23) -> 193825.7 | AV23: 57652.577 | AW23: 54545.461 | AX23: 56454.367 | AY23: 49531.33 | AZ23: =SUM(AV23:AX23) -> 168652.41 | BA23: 54381.661 | BB23: 53610 | BC23: 49048 | BD23: 49306 | BE23: =SUM(BA23:BD23) -> 206345.66 | BF23: 50987 | BG23: 47699
A24: Rodas Aço (Veículos Comerciais) | B24: Steel Wheels (Commercial vehicles) | C24: 39062.631 | D24: 40987.575 | E24: 41631.624 | F24: 48451.837 | G24: 170133.67 | H24: 49128.091 | I24: 47233.964 | J24: 41180.98 | K24: 35250.889 | L24: 172793.92 | M24: 46171.505 | N24: 45728.061 | O24: 52515.881 | P24: 56254.332 | Q24: 200669.78 | R24: 54659.138 | S24: 70809.337 | T24: 67662.134 | U24: 65533.124 | V24: 258663.73 | W24: 55817.094 | X24: 64917.264 | Y24: 43151.479 | Z24: 57392.232 | AA24: 221278.07 | AB24: 36226.639 | AC24: 24808.825 | AD24: 45913.067 | AE24: 65862.253 | AF24: 172810.78 | AG24: 100194 | AH24: 83960.093 | AI24: 95136.239 | AJ24: 109301.74 | AK24: =SUM(AG24:AJ24) -> 388592.08 | AL24: 120013.04 | AM24: 93805.843 | AN24: 98498.617 | AO24: 90613.316 | AP24: =SUM(AL24:AO24) -> 402930.81 | AQ24: 93270.356 | AR24: 103869.59 | AS24: 92792.851 | AT24: 113533.51 | AU24: =SUM(AQ24:AT24) -> 403466.31 | AV24: 93803.503 | AW24: 100690.29 | AX24: 101917.29 | AY24: 123987.41 | AZ24: =SUM(AV24:AX24) -> 296411.09 | BA24: 101958.76 | BB24: 87828 | BC24: 90403 | BD24: 106825 | BE24: =SUM(BA24:BD24) -> 387014.76 | BF24: 96096 | BG24: 98093
A25: Ásia + Outros | B25: Asia + Others | C25: =SUM(C22:C24) -> 116598.51 | D25: =SUM(D22:D24) -> 131067.55 | E25: =SUM(E22:E24) -> 154948.14 | F25: =SUM(F22:F24) -> 159186.14 | G25: =SUM(G22:G24) -> 561800.34 | H25: =SUM(H22:H24) -> 151671.81 | I25: =SUM(I22:I24) -> 149763.13 | J25: =SUM(J22:J24) -> 128418.82 | ... AU25: =SUM(AU22:AU24) -> 1426115.4 | AV25: =SUM(AV22:AV24)+1 -> 313768.24 | AW25: =SUM(AW22:AW24)-1 -> 322539.68 | AX25: =SUM(AX22:AX24) -> 360624.33 | AY25: =SUM(AY22:AY24) -> 354403.67 | AZ25: =SUM(AV25:AX25) -> 996932.25 | BA25: =SUM(BA22:BA24) -> 351044.03 | BB25: =SUM(BB22:BB24) -> 343150 | BC25: =SUM(BC22:BC24) -> 274015 | BD25: =SUM(BD22:BD24) -> 322707 | BE25: =SUM(BE22:BE24) -> 1290916 | BF25: =SUM(BF22:BF24) -> 321079 | BG25: =SUM(BG22:BG24) -> 352729
C26: =C25/C$27 -> 0.074961936 | D26: =D25/D$27 -> 0.078716652 | E26: =E25/E$27 -> 0.086548108 | F26: =F25/F$27 -> 0.086719112 | G26: =G25/G$27 -> 0.082057105 | H26: =H25/H$27 -> 0.085096193 | I26: =I25/I$27 -> 0.085086538 | J26: =J25/J$27 -> 0.080487624 | ... BG26: =BG25/BG$27 -> 0.087908196
A27: Iochpe-Maxion | B27: Iochpe-Maxion | C27: =C9+C15+C20+C25 -> 1555436.2 | D27: =D9+D15+D20+D25 -> 1665054.9 | E27: =E9+E15+E20+E25 -> 1790312.3 | F27: =F9+F15+F20+F25 -> 1835652.3 | G27: =G25+G20+G15+G9 -> 6846455.8 | H27: =H25+H20+H15+H9 -> 1782357.2 | I27: =I25+I20+I15+I9 -> 1760127.2 | J27: =J25+J20+J15+J9 -> 1595510.1 | K27: =K25+K20+K15+K9 -> 1678459.7 | L27: =L25+L20+L15+L9 -> 6816454.2 | M27: =M25+M20+M15+M9 -> 1699036 | N27: =N25+N20+N15+N9 -> 1901808.9 | ... AS27: =AS25+AS20+AS15+AS9 -> 3672363.5 | AT27: =AT9+AT15+AT20+AT25 -> 3483501 | AU27: =AU25+AU20+AU15+AU9 -> 14955220 | AV27: =AV9+AV15+AV20+AV25 -> 3595765.6 | AW27: =AW9+AW15+AW20+AW25 -> 3844567.5 | AX27: =AX9+AX15+AX20+AX25 -> 3982372.6 | AY27: =AY9+AY15+AY20+AY25 -> 3909106.7 | AZ27: =AZ25+AZ20+AZ15+AZ9 -> 12537916 | BA27: =BA9+BA15+BA20+BA25 -> 3938050.4 | BB27: =BB9+BB15+BB20+BB25 -> 4106968 | BC27: =BC9+BC15+BC20+BC25 -> 3802401 | BD27: =BD9+BD15+BD20+BD25 -> 3519120 | BE27: =BE9+BE15+BE20+BE25 -> 15366539 | BF27: =BF9+BF15+BF20+BF25 -> 3807333 | BG27: =BG9+BG15+BG20+BG25 -> 4012470
A29: Rodas de alumínio | B29: Aluminum Wheels | C29: =C4+C11+C17+C22 -> 419177.79 | D29: =D4+D11+D17+D22 -> 477779.98 | E29: =E4+E11+E17+E22 -> 550992.04 | F29: =F4+F11+F17+F22 -> 573758.78 | G29: =G4+G11+G17+G22 -> 2021708.6 | H29: =H4+H11+H17+H22 -> 571677.27 | I29: =I4+I11+I17+I22 -> 577513.05 | J29: =J4+J11+J17+J22 -> 514292.62 | ... BD29: =BD4+BD11+BD17+BD22 -> 1224079 | BE29: =SUM(BE4,BE11,BE17,BE22) -> 5130654.2 | BF29: =BF4+BF11+BF17+BF22 -> 1361185 | BG29: =BG4+BG11+BG17+BG22 -> 1448834
C30: =C29/C$27 -> 0.26949212 | D30: =D29/D$27 -> 0.28694548 | E30: =E29/E$27 -> 0.30776309 | F30: =F29/F$27 -> 0.31256397 | G30: =G29/G$27 -> 0.29529273 | H30: =H29/H$27 -> 0.32074225 | I30: =I29/I$27 -> 0.32810869 | J30: =J29/J$27 -> 0.32233742 | ... BG30: =BG29/BG$27 -> 0.36108282
A31: Rodas de aço (veículos leves) | B31: Steel Wheels (Light Vehicles) | C31: =C5+C12+C18+C23 -> 502908.41 | D31: =D5+D12+D18+D23 -> 533876.9 | E31: =E5+E12+E18+E23 -> 594332.02 | F31: =F5+F12+F18+F23 -> 648587.48 | G31: =G5+G12+G18+G23 -> 2279704.8 | H31: =H5+H12+H18+H23 -> 585171.5 | I31: =I5+I12+I18+I23 -> 566756.28 | J31: =J5+J12+J18+J23 -> 525733.12 | ... BD31: =BD5+BD12+BD18+BD23 -> 941846 | BE31: =SUM(BE5,BE12,BE18,BE23) -> 3957913.3 | BF31: =BF5+BF12+BF18+BF23 -> 923329 | BG31: =BG5+BG12+BG18+BG23 -> 951716
C32: =C31/C$27 -> 0.32332307 | D32: =D31/D$27 -> 0.32063621 | E32: =E31/E$27 -> 0.33197114 | F32: =F31/F$27 -> 0.35332806 | G32: =G31/G$27 -> 0.33297591 | H32: =H31/H$27 -> 0.32831325 | I32: =I31/I$27 -> 0.32199733 | J32: =J31/J$27 -> 0.32950786 | ... BG32: =BG31/BG$27 -> 0.23718956
A33: Rodas de aço (veículos comerciais) | B33: Steel Wheels (Commercial Vehicles) | C33: =C6+C13+C19+C24 -> 317408.26 | D33: =D6+D13+D19+D24 -> 333528.83 | E33: =E6+E13+E19+E24 -> 336726.53 | F33: =F6+F13+F19+F24 -> 311103.37 | G33: =G6+G13+G19+G24 -> 1298767 | H33: =H6+H13+H19+H24 -> 337625.98 | I33: =I6+I13+I19+I24 -> 346843.74 | J33: =J6+J13+J19+J24 -> 313566.9 | ... BD33: =BD6+BD13+BD19+BD24 -> 689358 | BE33: =SUM(BE6,BE13,BE19,BE24) -> 3097750.9 | BF33: =BF6+BF13+BF19+BF24 -> 766847 | BG33: =BG6+BG13+BG19+BG24 -> 796241
C34: =C33/C$27 -> 0.20406382 | D34: =D33/D$27 -> 0.20031101 | E34: =E33/E$27 -> 0.18808256 | F34: =F33/F$27 -> 0.16947837 | G34: =G33/G$27 -> 0.18969917 | H34: =H33/H$27 -> 0.18942666 | I34: =I33/I$27 -> 0.19705606 | J34: =J33/J$27 -> 0.19653081 | ... BG34: =BG33/BG$27 -> 0.19844161
A35: Comp. Estruturais (veículos leves) | B35: Structural Comp. (Light Vehicles) | C35: =C7 -> 40363.381 | D35: =D7 -> 34789.908 | E35: =E7 -> 37781.839 | F35: =F7 -> 39295.597 | G35: =G7 -> 152230.72 | H35: =H7 -> 36783.019 | I35: =I7 -> 33576.174 | J35: =J7 -> 31535.434 | ... BG35: =BG7 -> 121304
C36: =C35/C$27 -> 0.025949879 | D36: =D35/D$27 -> 0.02089415 | E36: =E35/E$27 -> 0.02110349 | F36: =F35/F$27 -> 0.021406884 | G36: =G35/G$27 -> 0.022234968 | H36: =H35/H$27 -> 0.020637288 | I36: =I35/I$27 -> 0.019075992 | J36: =J35/J$27 -> 0.019765111 | ... BG36: =BG35/BG$27 -> 0.030231753
A37: Comp. Estruturais (veículos comerciais) | B37: Structural Comp. (Commercial Vehicles) | C37: =C8+C14 -> 275578.35 | D37: =D8+D14 -> 285079.3 | E37: =E8+E14 -> 270479.88 | F37: =F8+F14 -> 262907.11 | G37: =G8+G14 -> 1094044.6 | H37: =H8+H14 -> 251099.45 | I37: =I8+I14 -> 235438.01 | J37: =J8+J14 -> 210382.04 | ... BD37: =BD8+BD14 -> 533240 | BE37: =SUM(BE8,BE14) -> 2673444 | BF37: =BF8+BF14 -> 636743 | BG37: =BG8+BG14 -> 694375
C38: =C37/C$27 -> 0.17717111 | D38: =D37/D$27 -> 0.17121315 | E38: =E37/E$27 -> 0.15107972 | F38: =F37/F$27 -> 0.14322271 | G38: =G37/G$27 -> 0.15979723 | H38: =H37/H$27 -> 0.14088054 | I38: =I37/I$27 -> 0.13376193 | J38: =J37/J$27 -> 0.13185879 | ... BG38: =BG37/BG$27 -> 0.17305425
A40: Veículos leves | B40: Light Vehicles | C40: =C29+C31+C35 -> 962449.59 | D40: =D29+D31+D35 -> 1046446.8 | E40: =E29+E31+E35 -> 1183105.9 | F40: =F29+F31+F35 -> 1261641.9 | G40: =G29+G31+G35 -> 4453644.1 | H40: =H29+H31+H35 -> 1193631.8 | I40: =I29+I31+I35 -> 1177845.5 | J40: =J29+J31+J35 -> 1071561.2 | ... BD40: =BD29+BD31+BD35 -> 2296522 | BE40: =SUM(BE29,BE31,BE35) -> 9595344.5 | BF40: =BF29+BF31+BF35 -> 2403743 | BG40: =BG29+BG31+BG35 -> 2521854
C41: =C40/C$27 -> 0.61876507 | D41: =D40/D$27 -> 0.62847584 | E41: =E40/E$27 -> 0.66083772 | F41: =F40/F$27 -> 0.68729891 | G41: =G40/G$27 -> 0.6505036 | H41: =H40/H$27 -> 0.66969279 | I41: =I40/I$27 -> 0.66918201 | J41: =J40/J$27 -> 0.67161039 | ... BG41: =BG40/BG$27 -> 0.62850414
A42: Veículos comerciais | B42: Commercial Vehicles | C42: =C33+C37 -> 592986.61 | D42: =D33+D37 -> 618608.13 | E42: =E33+E37 -> 607206.41 | F42: =F33+F37 -> 574010.48 | G42: =G33+G37 -> 2392811.6 | H42: =H33+H37 -> 588725.43 | I42: =I33+I37 -> 582281.75 | J42: =J33+J37 -> 523948.94 | ... BD42: =BD33+BD37 -> 1222598 | BE42: =SUM(BE33,BE37) -> 5771194.9 | BF42: =BF33+BF37 -> 1403590 | BG42: =BG33+BG37 -> 1490616
C43: =C42/C$27 -> 0.38123493 | D43: =D42/D$27 -> 0.37152416 | E43: =E42/E$27 -> 0.33916228 | F43: =F42/F$27 -> 0.31270109 | G43: =G42/G$27 -> 0.3494964 | H43: =H42/H$27 -> 0.33030721 | I43: =I42/I$27 -> 0.33081799 | J43: =J42/J$27 -> 0.32838961 | ... BG43: =BG42/BG$27 -> 0.37149586
W46: =W40/R40-1 -> 0.10116953
C47: 3453212.2
C48: 2458465.1 | W48: =W42/R42-1 -> 0.23839041

Sheet EBITDA
A1: Consolidado | B1: Consolidated | C1: 1Q15 | D1: 2Q15 | E1: 3Q15 | F1: 4Q15 | G1: 2015 | H1: 1Q16 | I1: 2Q16 | J1: 3Q16 | K1: 4Q16 | L1: 2016 | M1: 1Q17 | N1: 2Q17 | O1: 3Q17 | P1: 4Q17 | Q1: 2017 | R1: 1Q18 | S1: 2Q18 | T1: 3Q18 | U1: 4Q18 | V1: 2018 | W1: 1Q19 | X1: 2Q19 | Y1: 3Q19 | Z1: 4Q19 | AA1: 2019 | AB1: 1Q20 | AC1: 2Q20 | AD1: 3Q20 | AE1: 4Q20 | AF1: 2020 | AG1: 1Q21 | AH1: 2Q21 | AI1: 3Q21 | AJ1: 4Q21 | AK1: 2021 | AL1: 1Q22 | AM1: 2Q22 | AN1: 3Q22 | AO1: 4Q22 | AP1: 2022 | AQ1: 1Q23 | AR1: 2Q23 | AS1: 3Q23 | AT1: 4Q23 | AU1: 2023 | AV1: 1Q24 | AW1: 2Q24 | AX1: 3Q24 | AY1: 4Q24 | AZ1: 2024 | BA1: 1Q25 | BB1: 2Q25 | BC1: 3Q25 | BD1: 4Q25 | BE1: 2025 | BF1: 1Q26 | BG1: 2Q26
A2: Conciliação do EBITDA - R$ mil | B2: EBITDA Reconciliation - R$ Thousand | C2: 1T15 | D2: 2T15 | E2: 3T15 | F2: 4T15 | G2: 2015 | H2: 1T16 | I2: 2T16 | J2: 3T16 | K2: 4T16 | L2: 2016 | M2: 1T17 | N2: 2T17 | O2: 3T17 | P2: 4T17 | Q2: 2017 | R2: 1T18 | S2: 2T18 | T2: 3T18 | U2: 4T18 | V2: 2018 | W2: 1T19 | X2: 2T19 | Y2: 3T19 | Z2: 4T19 | AA2: 2019 | AB2: 1T20 | AC2: 2T20 | AD2: 3T20 | AE2: 4T20 | AF2: 2020 | AG2: 1T21 | AH2: 2T21 | AI2: 3T21 | AJ2: 4T21 | AK2: 2021 | AL2: 1T22 | AM2: 2T22 | AN2: 3T22 | AO2: 4T22 | AP2: 2022 | AQ2: 1T23 | AR2: 2T23 | AS2: 3T23 | AT2: 4T23 | AU2: 2023 | AV2: 1T24 | AW2: 2T24 | AX2: 3T24 | AY2: 4T24 | AZ2: 2024 | BA2: 1T25 | BB2: 2T25 | BC2: 3T25 | BD2: 4T25 | BE2: 2025 | BF2: 1T26 | BG2: 2T26
A3: Lucro líquido (Prejuízo) | B3: Net Income (Loss) | C3: -6678.4145 | D3: 70241.425 | E3: 2433.6646 | F3: -16631.049 | G3: 49366 | H3: 6982.0714 | I3: -7191.5244 | J3: 4893 | K3: 16848 | L3: 21530.635 | M3: -1250.7129 | N3: 24569.457 | O3: 34157.305 | P3: 11805.205 | Q3: 6403.1137 | R3: -12966.111 | S3: 44135 | T3: 93479.1 | U3: 76677 | V3: 201325 | W3: 63098 | X3: 110390 | Y3: 124838 | Z3: 39109.203 | AA3: 337435 | AB3: 9150.2979 | AC3: -352353.3 | AD3: -18876.646 | AE3: -129700 | AF3: -491779.81 | AG3: 51502 | AH3: 214786.52 | AI3: 177016 | AJ3: 93916 | AK3: 537221 | AL3: 160206.02 | AM3: 190485.23 | AN3: 69387.722 | AO3: -141146.49 | AP3: 278932.9 | AQ3: -16340.903 | AR3: 59360.073 | AS3: -4783.9222 | AT3: -7501.7261 | AU3: =SUM(AQ3:AT3) -> 30733.522 | AV3: 50256.757 | AW3: 36925 | AX3: 109172 | AY3: 68366 | AZ3: 196353.76 | BA3: 10892 | BB3: 86822 | BC3: 35067 | BD3: -34398 | BE3: =SUM(BA3:BD3) -> 98383 | BF3: 3920 | BG3: 86869
A4: Não Controladores | B4: Minority Shareholders | C4: 16380.681 | D4: 13403.283 | E4: 10131.915 | F4: 30567.121 | G4: 70483 | H4: 15761 | I4: 21394.133 | J4: 13397.867 | K4: 17047 | L4: 67599 | M4: 14170.89 | N4: 14724.602 | O4: 19336.508 | P4: 25574 | Q4: 73806 | R4: 20547 | S4: 20981 | T4: 18815 | U4: 44474 | V4: 104817 | W4: 17956 | X4: 19672 | Y4: 21970 | Z4: 24382 | AA4: 83980 | AB4: 21176 | AC4: 667 | AD4: 13184 | AE4: 36839 | AF4: 71866 | AG4: 26500 | AH4: 20235 | AI4: 27027 | AJ4: 15955 | AK4: 89717 | AL4: 28506 | AM4: 28706 | AN4: 20201 | AO4: 47826 | AP4: 125239 | AQ4: 16743 | AR4: 22745 | AS4: 11218 | AT4: 24452 | AU4: =SUM(AQ4:AT4) -> 75158 | AV4: 31567 | AW4: 34571 | AX4: 20408 | AY4: 28818 | AZ4: 86546 | BA4: 24640 | BB4: 23510 | BC4: 38429 | BD4: 32172 | BE4: =SUM(BA4:BD4) -> 118751 | BF4: 33185 | BG4: 36403
A5: Imp. de Renda / Contrib. Social | B5: Income Taxes and Social Contribution | C5: 12099.447 | D5: -1746.2678 | E5: 14932.497 | F5: -12292.3 | G5: 12993 | H5: 32944 | I5: 5983.1559 | J5: 9933.8441 | K5: -3159 | L5: 45702 | M5: 34646.521 | N5: 32522.366 | O5: 36840.114 | P5: -2478 | Q5: 69139 | R5: 74940 | S5: 60029 | T5: 58279 | U5: -18716 | V5: 174532 | W5: -15089 | X5: 21886 | Y5: 55824 | Z5: 22315 | AA5: 84936 | AB5: 5590 | AC5: -64469 | AD5: 34932 | AE5: 26154 | AF5: 2207 | AG5: 86037 | AH5: 150726 | AI5: 71865 | AJ5: 21302 | AK5: 329930 | AL5: 108937 | AM5: 82338 | AN5: 18131 | AO5: 14442 | AP5: 223848 | AQ5: 33469 | AR5: 41112 | AS5: 72542 | AT5: 11686 | AU5: =SUM(AQ5:AT5) -> 158809 | AV5: 23910 | AW5: 78459 | AX5: 77798 | AY5: 25212 | AZ5: 180167 | BA5: 41506 | BB5: 45152 | BC5: 3850 | BD5: 55996 | BE5: =SUM(BA5:BD5) -> 146504 | BF5: 35437 | BG5: 43399
A6: Resultado Financeiro | B6: Financial Results | C6: 51106.204 | D6: 89646.446 | E6: 97391.157 | F6: 78616.466 | G6: 316760 | H6: 97388 | I6: 80937.755 | J6: 85952 | K6: 80212.3 | L6: 344490.3 | M6: 68479 | N6: 49042 | O6: 53652.214 | P6: 80764 | Q6: 347208 | R6: 64607 | S6: 64847 | T6: 49149 | U6: 42216 | V6: 220819 | W6: 77802 | X6: 49704 | Y6: 24105 | Z6: 18293 | AA6: 169904 | AB6: 49580 | AC6: 84121 | AD6: 42240 | AE6: 57045 | AF6: 232986 | AG6: 59042 | AH6: 68543 | AI6: 78756 | AJ6: 118276 | AK6: 324617 | AL6: 122252 | AM6: 112366 | AN6: 137777 | AO6: 245269 | AP6: 617664 | AQ6: 131889 | AR6: 122408 | AS6: 118930 | AT6: 144649 | AU6: =SUM(AQ6:AT6) -> 517876 | AV6: 95156 | AW6: 116478 | AX6: 99186 | AY6: 124753 | AZ6: 310820 | BA6: 139991 | BB6: 151372 | BC6: 144566 | BD6: 142347 | BE6: =SUM(BA6:BD6) -> 578276 | BF6: 146281 | BG6: 117042
A7: Depreciação / Amortização | B7: Depreciation / Amortization | C7: 66925.606 | D7: 70957.016 | E7: 79780.714 | F7: 83801.359 | G7: 301465 | H7: 83220.345 | I7: 78447.434 | J7: 76932.431 | K7: 78301.207 | L7: 316903 | M7: 69348.028 | N7: 73279.34 | O7: 76268.59 | P7: 83100.786 | Q7: 301997 | R7: 79984.561 | S7: 85416.097 | T7: 92277.227 | U7: 97903.262 | V7: 355575 | W7: 98821.56 | X7: 102594.82 | Y7: 107042.01 | Z7: 111095.95 | AA7: 419554 | AB7: 119471.16 | AC7: 132518.61 | AD7: 136197.01 | AE7: 168673.44 | AF7: 556860 | AG7: 144857.26 | AH7: 138438.72 | AI7: 135197.86 | AJ7: 141354.28 | AK7: 559848 | AL7: 128250.65 | AM7: 120677.5 | AN7: 117204.89 | AO7: 125098.21 | AP7: 491231 | AQ7: 121000.36 | AR7: 117781.52 | AS7: 115416 | AT7: 116089.75 | AU7: =SUM(AQ7:AT7) -> 470287.63 | AV7: 115752 | AW7: 122498 | AX7: 133671 | AY7: 131114 | AZ7: 371921 | BA7: 137333 | BB7: 143622 | BC7: 138523 | BD7: 132061 | BE7: =SUM(BA7:BD7) -> 551539 | BF7: 138223 | BG7: 133814
A8: EBITDA | B8: EBITDA | C8: =SUM(C3:C7) -> 139833.52 | D8: =SUM(D3:D7) -> 242501.9 | E8: =SUM(E3:E7) -> 204669.95 | F8: =SUM(F3:F7) -> 164061.6 | G8: =SUM(G3:G7) -> 751067 | H8: =SUM(H3:H7) -> 236295.42 | I8: =SUM(I3:I7) -> 179570.95 | J8: =SUM(J3:J7) -> 191109.14 | ... AP8: =SUM(AP3:AP7) -> 1736914.9 | AQ8: 286760.45 | AR8: 363406.6 | AS8: 313322.08 | AT8: 289375 | AU8: =SUM(AQ8:AT8) -> 1252864.1 | AV8: 316642 | AW8: 388931 | AX8: 440235 | AY8: =SUM(AY3:AY7) -> 378263 | AZ8: =SUM(AV8:AY8) -> 1524071 | BA8: 354362 | BB8: 450478 | BC8: 360435 | BD8: 328178 | BE8: =SUM(BA8:BD8) -> 1493453 | BF8: =SUM(BF3:BF7) -> 357046 | BG8: =SUM(BG3:BG7) -> 417527

Sheet Balanço - Balance Sheet
A1: R$ mil | B1: R$ thousand | C1: 1Q15 | D1: 2Q15 | E1: 3Q15 | F1: 4Q15 | G1: 2015 | H1: 1Q16 | I1: 2Q16 | J1: 3Q16 | K1: 4Q16 | L1: 2016 | M1: 1Q17 | N1: 2Q17 | O1: 3Q17 | P1: 4Q17 | Q1: 2017 | R1: 1Q18 | S1: 2Q18 | T1: 3Q18 | U1: 4Q18 | V1: 2018 | W1: 1Q19 | X1: 2Q19 | Y1: 3Q19 | Z1: 4Q19 | AA1: 2019 | AB1: 1Q20 | AC1: 2Q20 | AD1: 3Q20 | AE1: 4Q20 | AF1: 2020 | AG1: 1Q21 | AH1: 2Q21 | AI1: 3Q21 | AJ1: 4Q21 | AK1: 2021 | AL1: 1Q22 | AM1: 2Q22 | AN1: 3Q22 | AO1: 4Q22 | AP1: 2022 | AQ1: 1Q23 | AR1: 2Q23 | AS1: 3Q23 | AT1: 4Q23 | AU1: 2023 | AV1: 1Q24 | AW1: 2Q24 | AX1: 3Q24 | AY1: 4Q24 | AZ1: 2024 | BA1: 1Q25 | BB1: 2Q25 | BC1: 3Q25 | BD1: 4Q25 | BE1: 2025 | BF1: 1Q26 | BG1: 2Q26
A2: ATIVO | B2: ASSETS | C2: 1T15 | D2: 2T15 | E2: 3T15 | F2: 4T15 | G2: 2015 | H2: 1T16 | I2: 2T16 | J2: 3T16 | K2: 4T16 | L2: 2016 | M2: 1T17 | N2: 2T17 | O2: 3T17 | P2: 4T17 | Q2: 2017 | R2: 1T18 | S2: 2T18 | T2: 3T18 | U2: 4T18 | V2: 2018 | W2: 1T19 | X2: 2T19 | Y2: 3T19 | Z2: 4T19 | AA2: 2019 | AB2: 1T20 | AC2: 2T20 | AD2: 3T20 | AE2: 4T20 | AF2: 2020 | AG2: 1T21 | AH2: 2T21 | AI2: 3T21 | AJ2: 4T21 | AK2: 2021 | AL2: 1T22 | AM2: 2T22 | AN2: 3T22 | AO2: 4T22 | AP2: 2022 | AQ2: 1T23 | AR2: 2T23 | AS2: 3T23 | AT2: 4T23 | AU2: 2023 | AV2: 1T24 | AW2: 2T24 | AX2: 3T24 | AY2: 4T24 | AZ2: 2024 | BA2: 1T25 | BB2: 2T25 | BC2: 3T25 | BD2: 4T25 | BE2: 2025 | BF2: 1T26 | BG2: 2T26
A3: CIRCULANTE | B3: CURRENT
A4: Caixa e Equivalentes de Caixa | B4: Cash and Cash Equivalents | C4: 643969 | D4: 675073 | E4: 691991 | F4: 739255 | G4: 739255 | H4: 560069 | I4: 509196 | J4: 341134 | K4: 431599 | L4: 431599 | M4: 690274 | N4: 695515 | O4: 502741 | P4: 543331 | Q4: 543331 | R4: 820925 | S4: 312904 | T4: 285356 | U4: 486903 | V4: 486903 | W4: 435074 | X4: 353039 | Y4: 671381 | Z4: 646137 | AA4: 646137 | AB4: 1133921 | AC4: 1392574 | AD4: 1641643 | AE4: 1605439 | AF4: 1605439 | AG4: 1508930 | AH4: 1355258 | AI4: 1006988 | AJ4: 1088114 | AK4: 1088114 | AL4: 1385993 | AM4: 1392893 | AN4: 1604256 | AO4: 2287054 | AP4: 2287054 | AQ4: 2604739 | AR4: 2458590 | AS4: 3054672 | AT4: 2962366 | AU4: 2962366 | AV4: 2295227 | AW4: 2255949 | AX4: 2338050 | AY4: ='BS - Consolidado'!J5 -> 2463475 | AZ4: =AY4 -> 2463475 | BA4: ='BS - Consolidado'!I5 -> 1932732 | BB4: ='BS - Consolidado'!H5 -> 1678690 | BC4: ='BS - Consolidado'!G5 -> 1624952 | BD4: ='BS - Consolidado'!F5 -> 1599733 | BE4: =BD4 -> 1599733 | BF4: ='BS - Consolidado'!E5 -> 1866118 | BG4: ='BS - Consolidado'!D5 -> 1868049
A5: Contas a Receber de Clientes | B5: Trade Receivables | C5: 957009 | D5: 896538 | E5: 1095504 | F5: 865496 | G5: 865496 | H5: 923874 | I5: 884992 | J5: 909652 | K5: 835158 | L5: 835158 | M5: 978340 | N5: 1118783 | O5: 1141765 | P5: 1064916 | Q5: 1064916 | R5: 1306513 | S5: 1470644 | T5: 1555906 | U5: 1253826 | V5: 1253826 | W5: 1502342 | X5: 1479216 | Y5: 1440886 | Z5: 1029650 | AA5: 1029650 | AB5: 1323161 | AC5: 966336 | AD5: 1528126 | AE5: 1405954 | AF5: 1405954 | AG5: 1824896 | AH5: 1749006 | AI5: 2040574 | AJ5: 1731914 | AK5: 1731914 | AL5: 2027779 | AM5: 2466700 | AN5: 2406460 | AO5: 2053692 | AP5: 2053692 | AQ5: 2267301 | AR5: 1589570 | AS5: 1526405 | AT5: 1261050 | AU5: 1261050 | AV5: 1609129 | AW5: 1780765 | AX5: 1714233 | AY5: ='BS - Consolidado'!J12 -> 1449118 | AZ5: =AY5 -> 1449118 | BA5: ='BS - Consolidado'!I12 -> 1777578 | BB5: ='BS - Consolidado'!H12 -> 1699403 | BC5: ='BS - Consolidado'!G12 -> 1544030 | BD5: ='BS - Consolidado'!F12 -> 1333705 | BE5: =BD5 -> 1333705 | BF5: ='BS - Consolidado'!E12 -> 1737718 | BG5: ='BS - Consolidado'!D12 -> 1850701
A6: Estoques | B6: Inventory | C6: 786847 | D6: 753593 | E6: 936330 | F6: 854665 | G6: 854665 | H6: 856847 | I6: 825903 | J6: 861165 | K6: 865029 | L6: 865029 | M6: 933278 | N6: 1056564 | O6: 1110176 | P6: 1191445 | Q6: 1191445 | R6: 1260011 | S6: 1441329 | T6: 1519877 | U6: 1448021 | V6: 1448021 | W6: 1517728 | X6: 1399921 | Y6: 1417784 | Z6: 1328470 | AA6: 1328470 | AB6: 1698388 | AC6: 1659113 | AD6: 1717282 | AE6: 1748497 | AF6: 1748497 | AG6: 2200098 | AH6: 2474865 | AI6: 3081815 | AJ6: 3196694 | AK6: 3196694 | AL6: 2807064 | AM6: 3055324 | AN6: 2965662 | AO6: 2702075 | AP6: 2702075 | AQ6: 2563366 | AR6: 2444233 | AS6: 2456263 | AT6: 2320305 | AU6: 2320305 | AV6: 2343032 | AW6: 2461251 | AX6: 2444430 | AY6: ='BS - Consolidado'!J15 -> 2458784 | AZ6: =AY6 -> 2458784 | BA6: ='BS - Consolidado'!I15 -> 2542395 | BB6: ='BS - Consolidado'!H15 -> 2647642 | BC6: ='BS - Consolidado'!G15 -> 2568157 | BD6: ='BS - Consolidado'!F15 -> 2465712 | BE6: =BD6 -> 2465712 | BF6: ='BS - Consolidado'!E15 -> 2355533 | BG6: ='BS - Consolidado'!D15 -> 2546919
A7: Impostos a Recuperar | B7: Recoverable Taxes | C7: 126516 | D7: 100338 | E7: 146911 | F7: 135447 | G7: 135447 | H7: 120694 | I7: 107601 | J7: 105145 | K7: 125249 | L7: 125249 | M7: 131950 | N7: 144112 | O7: 150232 | P7: 159482 | Q7: 159482 | R7: 145162 | S7: 207658 | T7: 260784 | U7: 237675 | V7: 237675 | W7: 228744 | X7: 252380 | Y7: 308369 | Z7: 223589 | AA7: 223589 | AB7: 213089 | AC7: 200080 | AD7: 216022 | AE7: 239884 | AF7: 239884 | AG7: 314949 | AH7: 392709 | AI7: 577775 | AJ7: 500695 | AK7: 500695 | AL7: 481564 | AM7: 582900 | AN7: 693491 | AO7: 600748 | AP7: 600748 | AQ7: 645572 | AR7: 669896 | AS7: 707121 | AT7: 717498 | AU7: 717498 | AV7: 706830 | AW7: 669423 | AX7: 659911 | AY7: ='BS - Consolidado'!J17 -> 687164 | AZ7: =AY7 -> 687164 | BA7: ='BS - Consolidado'!I17 -> 607687 | BB7: ='BS - Consolidado'!H17 -> 577961 | BC7: ='BS - Consolidado'!G17 -> 521001 | BD7: ='BS - Consolidado'!F17 -> 498665 | BE7: =BD7 -> 498665 | BF7: ='BS - Consolidado'!E17 -> 449973 | BG7: ='BS - Consolidado'!D17 -> 499212
A8: Despesas Antecipadas | B8: Prepaid Expenses | C8: 27460 | D8: 24819 | E8: 25228 | F8: 30592 | G8: 30592 | H8: 31614 | I8: 24335 | J8: 23381 | K8: 23054 | L8: 23054 | M8: 26989 | N8: 30864 | O8: 28265 | P8: 19657 | Q8: 19657 | R8: 27384 | S8: 25332 | T8: 26108 | U8: 19641 | V8: 19641 | W8: 27177 | X8: 25991 | Y8: 23565 | Z8: 20210 | AA8: 20210 | AB8: 46607 | AC8: 48608 | AD8: 50855 | AE8: 49145 | AF8: 49145 | AG8: 55688 | AH8: 55849 | AI8: 49293 | AJ8: 49093 | AK8: 49093 | AL8: 46157 | AM8: 55869 | AN8: 55625 | AO8: 57725 | AP8: 57725 | AQ8: 81893 | AR8: 77817 | AS8: 69736 | AT8: 80481 | AU8: 80481 | AV8: 92785 | AW8: 113515 | AX8: 88658 | AY8: ='BS - Consolidado'!J19 -> 122362 | AZ8: =AY8 -> 122362 | BA8: ='BS - Consolidado'!I19 -> 127604 | BB8: ='BS - Consolidado'!H19 -> 114572 | BC8: ='BS - Consolidado'!G19 -> 94192 | BD8: ='BS - Consolidado'!F19 -> 92499 | BE8: =BD8 -> 92499 | BF8: ='BS - Consolidado'!E19 -> 100397 | BG8: ='BS - Consolidado'!D19 -> 106577
A9: Instrumento Financeiro Derivativo | B9: Derivative Financial Instruments | C9: - | D9: - | E9: - | F9: - | G9: - | H9: - | I9: - | J9: - | K9: - | L9: - | M9: - | N9: - | O9: - | P9: - | Q9: - | R9: - | S9: - | T9: - | U9: - | V9: - | W9: - | X9: - | Y9: - | Z9: - | AA9: - | AB9: - | AC9: - | AD9: - | AE9: - | AF9: - | AG9: - | AH9: 25430 | AI9: 167959 | AJ9: 249055 | AK9: 249055 | AL9: 185048 | AM9: 210749 | AN9: 257298 | AO9: 32079 | AP9: 32079 | AQ9: 43820 | AR9: 36999 | AS9: 45409 | AT9: 28277 | AU9: 28277 | AV9: 34044 | AW9: 35149 | AX9: 31595 | AY9: ='BS - Consolidado'!J26 -> 43488 | AZ9: =AY9 -> 43488 | BA9: ='BS - Consolidado'!I26 -> 36174 | BB9: ='BS - Consolidado'!H26 -> 27564 | BC9: ='BS - Consolidado'!G26 -> 27714 | BD9: ='BS - Consolidado'!F26 -> 28669 | BE9: =BD9 -> 28669 | BF9: ='BS - Consolidado'!E26 -> 34111 | BG9: ='BS - Consolidado'!D26 -> 32634
A10: Outros Créditos | B10: Other | C10: 17033 | D10: 21617 | E10: 31903 | F10: 102400 | G10: 102400 | H10: 84564 | I10: 81865 | J10: 109642 | K10: 84622 | L10: 84622 | M10: 68232 | N10: 73379 | O10: 81660 | P10: 69932 | Q10: 69932 | R10: 80354 | S10: 104420 | T10: 94910 | U10: 77736 | V10: 77736 | W10: 88246 | X10: 105689 | Y10: 114226 | Z10: 109565 | AA10: 109565 | AB10: 111081 | AC10: 105581 | AD10: 124480 | AE10: 113007 | AF10: 113007 | AG10: 149793 | AH10: 155257 | AI10: 29566 | AJ10: 31949 | AK10: 31949 | AL10: 27830 | AM10: 33219 | AN10: 38514 | AO10: 152952 | AP10: 152952 | AQ10: 142880 | AR10: 171178 | AS10: 189175 | AT10: 144175 | AU10: 144175 | AV10: 151250 | AW10: 182952 | AX10: 203096 | AY10: ='BS - Consolidado'!J25 -> 166556 | AZ10: =AY10 -> 166556 | BA10: ='BS - Consolidado'!I25 -> 151051 | BB10: ='BS - Consolidado'!H25 -> 180331 | BC10: ='BS - Consolidado'!G25 -> 212627 | BD10: ='BS - Consolidado'!F25 -> 198934 | BE10: =BD10 -> 198934 | BF10: ='BS - Consolidado'!E25 -> 186206 | BG10: ='BS - Consolidado'!D25 -> 228782
C11: =SUM(C4:C10) -> 2558834 | D11: =SUM(D4:D10) -> 2471978 | E11: =SUM(E4:E10) -> 2927867 | F11: =SUM(F4:F10) -> 2727855 | G11: =SUM(G4:G10) -> 2727855 | H11: =SUM(H4:H10) -> 2577662 | I11: =SUM(I4:I10) -> 2433892 | J11: =SUM(J4:J10) -> 2350119 | ... U11: =SUM(U4:U10) -> 3523802 | V11: 3523802 | W11: =SUM(W4:W10) -> 3799311 | X11: =SUM(X4:X10) -> 3616236 | Y11: =SUM(Y4:Y10) -> 3976211 | Z11: =SUM(Z4:Z10) -> 3357621 | AA11: 3357621 | AB11: =SUM(AB4:AB10) -> 4526247 | AC11: =SUM(AC4:AC10) -> 4372292 | AD11: =SUM(AD4:AD10) -> 5278408 | AE11: =SUM(AE4:AE10) -> 5161926 | AF11: 5161926 | AG11: =SUM(AG4:AG10) -> 6054354 | AH11: =SUM(AH4:AH10) -> 6208374 | AI11: =SUM(AI4:AI10) -> 6953970 | AJ11: =SUM(AJ4:AJ10) -> 6847514 | AK11: =SUM(AK4:AK10) -> 6847514 | AL11: =SUM(AL4:AL10) -> 6961435 | AM11: =SUM(AM4:AM10) -> 7797654 | AN11: =SUM(AN4:AN10) -> 8021306 | AO11: =SUM(AO4:AO10) -> 7886325 | AP11: 7886325 | AQ11: =SUM(AQ4:AQ10) -> 8349571 | AR11: =SUM(AR4:AR10) -> 7448283 | AS11: =SUM(AS4:AS10) -> 8048781 | AT11: =SUM(AT4:AT10) -> 7514152 | AU11: =SUM(AU4:AU10) -> 7514152 | AV11: =SUM(AV4:AV10) -> 7232297 | AW11: =SUM(AW4:AW10) -> 7499004 | AX11: =SUM(AX4:AX10) -> 7479973 | ... BG11: =SUM(BG4:BG10) -> 7132874
A13: NÃO CIRCULANTE | B13: LONG TERM
A14: Partes Relacionadas | B14: Related Parties | N14: 32138 | O14: 32987 | P14: 31961 | Q14: 31961 | R14: 32625 | S14: 33304 | T14: 32612 | U14: 32612 | V14: 32612 | W14: 32571 | X14: 32571 | Y14: 32571 | Z14: 4897 | AA14: 4897 | AB14: 5288
A15: Contas a receber de clientes | B15: Accounts receivable from customers | R15: 2285 | W15: 0
A16: Impostos a Recuperar | B16: Recoverable taxes | C16: 30996 | D16: 18391 | E16: 16935 | F16: 22273 | G16: 22273 | H16: 23985 | I16: 51594 | J16: 44057 | K16: 34002 | L16: 34002 | M16: 23236 | N16: 20427 | O16: 20953 | P16: 19435 | Q16: 19435 | R16: 15997 | S16: 18384 | T16: 21346 | U16: 29189 | V16: 29189 | W16: 35699 | X16: 34388 | Y16: 124320 | Z16: 166759 | AA16: 166759 | AB16: 147838 | AC16: 150092 | AD16: 155498 | AE16: 151962 | AF16: 151962 | AG16: 152278 | AH16: 343024 | AI16: 368922 | AJ16: 370063 | AK16: 370063 | AL16: 269596 | AM16: 285275 | AN16: 278300 | AO16: 338745 | AP16: 338745 | AQ16: 283507 | AR16: 277106 | AS16: 262981 | AT16: 234431 | AU16: 234431 | AV16: 239921 | AW16: 243968 | AX16: 218371 | AY16: ='BS - Consolidado'!J48 -> 133072 | AZ16: =AY16 -> 133072 | BA16: ='BS - Consolidado'!I48 -> 131897 | BB16: ='BS - Consolidado'!H48 -> 133577 | BC16: ='BS - Consolidado'!G48 -> 135868 | BD16: ='BS - Consolidado'!F48 -> 132726 | BE16: =BD16 -> 132726 | BF16: ='BS - Consolidado'!E48 -> 134130 | BG16: ='BS - Consolidado'!D48 -> 105970
A17: Imposto de Renda e Contribuição Social diferidos | B17: Deferred income tax and social contribution | C17: 77853 | D17: 75698 | E17: 91047 | F17: 88129 | G17: 88129 | H17: 113980 | I17: 137360 | J17: 153040 | K17: 188481 | L17: 188481 | M17: 199984 | N17: 209404 | O17: 238282 | P17: 257236 | Q17: 257236 | R17: 232465 | S17: 236634 | T17: 246395 | U17: 257517 | V17: 257517 | W17: 312586 | X17: 328681 | Y17: 324220 | Z17: 306628 | AA17: 306628 | AB17: 360681 | AC17: 444780 | AD17: 465290 | AE17: 419156 | AF17: 419156 | AG17: 410705 | AH17: 355525 | AI17: 365634 | AJ17: 323117 | AK17: 323117 | AL17: 256697 | AM17: 243601 | AN17: 247107 | AO17: 269034 | AP17: 269034 | AQ17: 255658 | AR17: 252275 | AS17: 256235 | AT17: 255413 | AU17: 255413 | AV17: 278269 | AW17: 292059 | AX17: 277657 | AY17: ='BS - Consolidado'!J39 -> 334035 | AZ17: =AY17 -> 334035 | BA17: ='BS - Consolidado'!I39 -> 309625 | BB17: ='BS - Consolidado'!H39 -> 293892 | BC17: ='BS - Consolidado'!G39 -> 290500 | BD17: ='BS - Consolidado'!F39 -> 284018 | BE17: =BD17 -> 284018 | BF17: ='BS - Consolidado'!E39 -> 282901 | BG17: ='BS - Consolidado'!D39 -> 302988
A18: Depósitos Judiciais | B18: Escrow deposits | C18: 21430 | D18: 25554 | E18: 28415 | F18: 24324 | G18: 24324 | H18: 30212 | I18: 26793 | J18: 30116 | K18: 55066 | L18: 55066 | M18: 54593 | N18: 58015 | O18: 59010 | P18: 61548 | Q18: 61548 | R18: 63661 | S18: 63910 | T18: 65117 | U18: 59468 | V18: 59468 | W18: 54421 | X18: 55398 | Y18: 56554 | Z18: 58495 | AA18: 58495 | AB18: 60673 | AC18: 59979 | AD18: 54254 | AE18: 56466 | AF18: 56466 | AG18: 56339 | AH18: 55601 | AI18: 55352 | AJ18: 56649 | AK18: 56649 | AL18: 58212 | AM18: 59472 | AN18: 61325 | AO18: 62618 | AP18: 62618 | AQ18: 65235 | AR18: 67355 | AS18: 68735 | AT18: 69889 | AU18: 69889 | AV18: 72589 | AW18: 77578 | AX18: 77377 | AY18: ='BS - Consolidado'!J49 -> 76742 | AZ18: =AY18 -> 76742 | BA18: ='BS - Consolidado'!I49 -> 77644 | BB18: ='BS - Consolidado'!H49 -> 78764 | BC18: ='BS - Consolidado'!G49 -> 76270 | BD18: ='BS - Consolidado'!F49 -> 56891 | BE18: =BD18 -> 56891 | BF18: ='BS - Consolidado'!E49 -> 60070 | BG18: ='BS - Consolidado'!D49 -> 80500
A19: Instrumento Financeiro Derivativo | B19: Derivative Financial Instruments | C19: - | D19: - | E19: - | F19: - | G19: - | H19: - | I19: - | J19: - | K19: - | L19: - | M19: - | N19: - | O19: - | P19: - | Q19: - | R19: - | S19: - | T19: - | U19: - | V19: - | W19: - | X19: - | Y19: - | Z19: - | AA19: - | AB19: - | AC19: - | AD19: - | AE19: - | AF19: - | AH19: 10718 | AI19: 65137 | AJ19: 112730 | AK19: 112730 | AL19: 131418 | AM19: 279288 | AN19: 398905 | AO19: 258780 | AP19: 258780 | AQ19: 223748 | AR19: 170679 | AS19: 202434 | AT19: 119229 | AU19: 119229 | AV19: 153191 | AW19: 182659 | AX19: 141559 | AY19: ='BS - Consolidado'!J51 -> 244805 | AZ19: =AY19 -> 244805 | BA19: ='BS - Consolidado'!I51 -> 194373 | BB19: ='BS - Consolidado'!H51 -> 32502 | BC19: ='BS - Consolidado'!G51 -> 49376 | BD19: ='BS - Consolidado'!F51 -> 45656 | BE19: =BD19 -> 45656 | BF19: ='BS - Consolidado'!E51 -> 87778 | BG19: ='BS - Consolidado'!D51 -> 77466
A20: Outros Créditos | B20: Other receivables | C20: 4711 | D20: 10258 | E20: 17866 | F20: 9484 | G20: 9484 | H20: 18320 | I20: 4517 | J20: 6502 | K20: 11504 | L20: 11504 | M20: 11574 | N20: 11418 | O20: 6022 | P20: 12451 | Q20: 12451 | R20: 5202 | S20: 5138 | T20: 4819 | U20: 4394 | V20: 4394 | W20: 4881 | X20: 3736 | Y20: 3621 | Z20: 1520 | AA20: 1520 | AB20: 1374 | AC20: 1217 | AD20: 1217 | AE20: 2046 | AF20: 2046 | AG20: 2107 | AH20: 972 | AI20: 662 | AJ20: 16056 | AK20: 16056 | AL20: 13102 | AM20: 81452 | AN20: 84233 | AO20: 74127 | AP20: 74127 | AQ20: 73893 | AR20: 104684 | AS20: 111706 | AT20: 93672 | AU20: 93672 | AV20: 104285 | AW20: 115914 | AX20: 113659 | AY20: ='BS - Consolidado'!J50 -> 130095 | AZ20: =AY20 -> 130095 | BA20: ='BS - Consolidado'!I50 -> 131332 | BB20: ='BS - Consolidado'!H50 -> 129776 | BC20: ='BS - Consolidado'!G50 -> 133919 | BD20: ='BS - Consolidado'!F50 -> 150209 | BE20: =BD20 -> 150209 | BF20: ='BS - Consolidado'!E50 -> 139546 | BG20: ='BS - Consolidado'!D50 -> 159992
A21: Investimentos | B21: Investments | C21: 13390 | D21: 78816 | E21: 82081 | F21: 73020 | G21: 73020 | H21: 99599 | I21: 98945 | J21: 85548 | K21: 81425 | L21: 81425 | M21: 86604 | N21: 62593 | O21: 59652 | P21: 47339 | Q21: 47339 | R21: 50052 | S21: 43090 | T21: 40726 | U21: 46803 | V21: 46803 | W21: 39655 | X21: 37768 | Y21: 67979 | Z21: 74612 | AA21: 74612 | AB21: 91571 | AC21: 93706 | AD21: 97383 | AE21: 95283 | AF21: 95283 | AG21: 102535 | AH21: 101125 | AI21: 114411 | AJ21: 138834 | AK21: 138834 | AL21: 128601 | AM21: 132510 | AN21: 133444 | AO21: 129203 | AP21: 129203 | AQ21: 127862 | AR21: 148090 | AS21: 141801 | AT21: 159767 | AU21: 159767 | AV21: 155270 | AW21: 170435 | AX21: 187943 | AY21: ='BS - Consolidado'!J52 -> 230043 | AZ21: =AY21 -> 230043 | BA21: ='BS - Consolidado'!I52 -> 222190 | BB21: ='BS - Consolidado'!H52 -> 222967 | BC21: ='BS - Consolidado'!G52 -> 213400 | BD21: ='BS - Consolidado'!F52 -> 295306 | BE21: =BD21 -> 295306 | BF21: ='BS - Consolidado'!E52 -> 295222 | BG21: ='BS - Consolidado'!D52 -> 189146
A22: Imobilizado | B22: Property, plant and equipment | C22: 2965850 | D22: 2933474 | E22: 3419877 | F22: 3358914 | G22: 3358914 | H22: 3157459 | I22: 2910615 | J22: 2949578 | K22: 2919881 | L22: 2919881 | M22: 2858422 | N22: 2960084 | O22: 2878626 | P22: 3023091 | Q22: 3023091 | R22: 3039531 | S22: 3289869 | T22: 3369818 | U22: 3398325 | V22: 3398325 | W22: 3411159 | X22: 3404563 | Y22: 3568801 | Z22: 3590747 | AA22: 3590747 | AB22: 4234363 | AC22: 4372430 | AD22: 4505066 | AE22: 4237764 | AF22: 4237764 | AG22: 4389253 | AH22: 3939697 | AI22: 4139906 | AJ22: 4253134 | AK22: 4253134 | AL22: 3723126 | AM22: 3919901 | AN22: 3898889 | AO22: 4043815 | AP22: 4043815 | AQ22: 3968305 | AR22: 3849102 | AS22: 3942344 | AT22: 4043995 | AU22: 4043995 | AV22: 4094019 | AW22: 4442430 | AX22: 4527119 | AY22: ='BS - Consolidado'!J59+'BS - Consolidado'!J61 -> 4968505 | AZ22: =AY22 -> 4968505 | BA22: ='BS - Consolidado'!I59+'BS - Consolidado'!I61 -> 4750824 | BB22: ='BS - Consolidado'!H59+'BS - Consolidado'!H61 -> 4752826 | BC22: ='BS - Consolidado'!G59+'BS - Consolidado'!G61 -> 4676676 | BD22: ='BS - Consolidado'!F59+'BS - Consolidado'!F61 -> 4841597 | BE22: =BD22 -> 4841597 | BF22: ='BS - Consolidado'!E59+'BS - Consolidado'!E61 -> 4609028 | BG22: ='BS - Consolidado'!D59+'BS - Consolidado'!D61 -> 4591055
A23: Intangível | B23: Intangible assets | C23: 1384304 | D23: 1338076 | E23: 1704383 | F23: 1686380 | G23: 1686380 | H23: 1537028 | I23: 1386501 | J23: 1399440 | K23: 1402045 | L23: 1402045 | M23: 1361066 | N23: 1419257 | O23: 1361454 | P23: 1420424 | Q23: 1420424 | R23: 1428183 | S23: 1652870 | T23: 1716135 | U23: 1667080 | V23: 1667080 | W23: 1678263 | X23: 1651821 | Y23: 1788900 | Z23: 1740135 | AA23: 1740135 | AB23: 2223453 | AC23: 2334121 | AD23: 2397686 | AE23: 2219880 | AF23: 2219880 | AG23: 2420960 | AH23: 2137136 | AI23: 2309567 | AJ23: 2348415 | AK23: 2348415 | AL23: 1971695 | AM23: 2078537 | AN23: 2039454 | AO23: 2085571 | AP23: 2085571 | AQ23: 2053043 | AR23: 1951142 | AS23: 1979396 | AT23: 1969307 | AU23: 1969307 | AV23: 1992052 | AW23: 2185849 | AX23: 2200702 | AY23: ='BS - Consolidado'!J62 -> 2360020 | AZ23: =AY23 -> 2360020 | BA23: ='BS - Consolidado'!I62 -> 2244031 | BB23: ='BS - Consolidado'!H62 -> 2261408 | BC23: ='BS - Consolidado'!G62 -> 2194315 | BD23: ='BS - Consolidado'!F62 -> 2263699 | BE23: =BD23 -> 2263699 | BF23: ='BS - Consolidado'!E62 -> 2114215 | BG23: ='BS - Consolidado'!D62 -> 2188299
A24: Direito de uso | B24: Right of use | C24: - | D24: - | E24: - | W24: 71597 | X24: 71588 | Y24: 79348 | Z24: 73997 | AA24: 73997 | AB24: 65689 | AC24: 63970 | AD24: 55598 | AE24: 67320 | AF24: 67320 | AG24: 63701 | AH24: 51106 | AI24: 57912 | AJ24: 53018 | AK24: 53018 | AL24: 38967 | AM24: 36645 | AN24: 34733 | AO24: 47237 | AP24: 47237 | AQ24: 66831 | AR24: 61509 | AS24: 65829 | AT24: 74261 | AU24: 74261 | AV24: 81410 | AW24: 83773 | AX24: 84147 | AY24: ='BS - Consolidado'!J60 -> 93107 | AZ24: =AY24 -> 93107 | BA24: ='BS - Consolidado'!I60 -> 92002 | BB24: ='BS - Consolidado'!H60 -> 88176 | BC24: ='BS - Consolidado'!G60 -> 89676 | BD24: ='BS - Consolidado'!F60 -> 104465 | BE24: =BD24 -> 104465 | BF24: ='BS - Consolidado'!E60 -> 102587 | BG24: ='BS - Consolidado'!D60 -> 99337
C25: =SUM(C16:C24) -> 4498534 | D25: =SUM(D16:D24) -> 4480267 | E25: =SUM(E16:E24) -> 5360604 | F25: =SUM(F16:F24) -> 5262524 | G25: =SUM(G16:G24) -> 5262524 | H25: =SUM(H16:H24) -> 4980583 | I25: =SUM(I16:I24) -> 4616325 | J25: =SUM(J16:J24) -> 4668281 | ... M25: =SUM(M16:M24) -> 4595479 | N25: =SUM(N14:N24) -> 4773336 | O25: =SUM(O14:O24) -> 4656986 | P25: =SUM(P14:P24) -> 4873485 | Q25: =SUM(Q14:Q24) -> 4873485 | R25: =SUM(R14:R24) -> 4870001 | S25: =SUM(S14:S24) -> 5343199 | T25: =SUM(T14:T24) -> 5496968 | U25: =SUM(U14:U24) -> 5495388 | V25: 5495388 | W25: =SUM(W14:W24) -> 5640832 | X25: =SUM(X14:X24) -> 5620514 | Y25: =SUM(Y14:Y24) -> 6046314 | Z25: =SUM(Z14:Z24) -> 6017790 | AA25: 6017790 | AB25: =SUM(AB14:AB24) -> 7190930 | AC25: =SUM(AC16:AC24) -> 7520295 | AD25: =SUM(AD14:AD24) -> 7731992 | AE25: =SUM(AE16:AE24) -> 7249877 | AF25: 7249877 | AG25: =SUM(AG16:AG24) -> 7597878 | AH25: =SUM(AH16:AH24) -> 6994904 | AI25: =SUM(AI16:AI24) -> 7477503 | AJ25: =SUM(AJ16:AJ24) -> 7672016 | AK25: =SUM(AK16:AK24) -> 7672016 | AL25: =SUM(AL16:AL24) -> 6591414 | AM25: =SUM(AM16:AM24) -> 7116681 | AN25: =SUM(AN16:AN24) -> 7176390 | AO25: =SUM(AO16:AO24) -> 7309130 | AP25: 7309130 | AQ25: =SUM(AQ16:AQ24) -> 7118082 | AR25: =SUM(AR16:AR24) -> 6881942 | AS25: =SUM(AS16:AS24) -> 7031461 | AT25: =SUM(AT16:AT24) -> 7019964 | AU25: =SUM(AU16:AU24) -> 7019964 | AV25: =SUM(AV16:AV24) -> 7171006 | AW25: =SUM(AW16:AW24) -> 7794665 | AX25: =SUM(AX16:AX24) -> 7828534 | ... BG25: =SUM(BG16:BG24) -> 7794753
A27: TOTAL DO ATIVO | B27: TOTAL ASSETS | C27: =C25+C11 -> 7057368 | D27: =D25+D11 -> 6952245 | E27: =E25+E11 -> 8288471 | F27: =F25+F11 -> 7990379 | G27: =G25+G11 -> 7990379 | H27: =H25+H11 -> 7558245 | I27: =I25+I11 -> 7050217 | J27: =J25+J11 -> 7018400 | ... U27: =U25+U11 -> 9019190 | V27: 9019190 | W27: =W25+W11 -> 9440143 | X27: =X25+X11 -> 9236750 | Y27: =Y25+Y11 -> 10022525 | Z27: =Z25+Z11 -> 9375411 | AA27: 9375411 | AB27: =AB25+AB11 -> 11717177 | AC27: =AC25+AC11 -> 11892587 | AD27: =AD25+AD11 -> 13010400 | AE27: =AE25+AE11 -> 12411803 | AF27: 12411803 | AG27: =AG25+AG11 -> 13652232 | AH27: =AH25+AH11 -> 13203278 | AI27: =AI25+AI11 -> 14431473 | AJ27: =AJ25+AJ11 -> 14519530 | AK27: =AK25+AK11 -> 14519530 | AL27: =AL25+AL11 -> 13552849 | AM27: =AM25+AM11 -> 14914335 | AN27: =AN25+AN11 -> 15197696 | AO27: =AO25+AO11 -> 15195455 | AP27: 15195455 | AQ27: =AQ25+AQ11 -> 15467653 | AR27: =AR25+AR11 -> 14330225 | AS27: =AS25+AS11 -> 15080242 | AT27: =AT25+AT11 -> 14534116 | AU27: =AU25+AU11 -> 14534116 | AV27: =AV25+AV11 -> 14403303 | AW27: =AW25+AW11 -> 15293669 | AX27: =AX25+AX11 -> 15308507 | ... BG27: =BG25+BG11 -> 14927627
A29: PASSIVO E PATRIMÔNIO LÍQUIDO | B29: LIABILITIES
A31: CIRCULANTE | B31: CURRENT
A32: Empréstimos, financiamentos e debêntures | B32: Borrowings, Financing and Debentures | C32: 1399861 | D32: 1477652 | E32: 1637787 | F32: 1684702 | G32: 1684702 | H32: 1725679 | I32: 1170066 | J32: 1144541 | K32: 1182808 | L32: 1182808 | M32: 787887 | N32: 1235474 | O32: 1149628 | P32: 1352544 | Q32: 1352544 | R32: =1175351-2038 -> 1173313 | S32: 1001361 | T32: =915824+151507 -> 1067331 | U32: =912955+163194 -> 1076149 | V32: 1076149 | W32: =707690+160258 -> 867948 | X32: =726463+17474 -> 743937 | Y32: =724591+864 -> 725455 | Z32: =629300+19397 -> 648697 | AA32: 648697 | AB32: =1462768-195 -> 1462573 | AC32: =1827512+765 -> 1828277 | AD32: =2341754-5335 -> 2336419 | AE32: 1907564 | AF32: 1907564 | AG32: 3303156 | AH32: 1798780 | AI32: =1645033+213790 -> 1858823 | AJ32: =1240639+241142 -> 1481781 | AK32: =1240639+241142 -> 1481781 | AL32: =1634537+388379 -> 2022916 | AM32: =838668+438766 -> 1277434 | AN32: =654954+615402 -> 1270356 | AO32: 1043611 | AP32: 1043611 | AQ32: 2017722 | AR32: 1813563 | AS32: 1775347 | AT32: 1631599 | AU32: 1631599 | AV32: 1387002 | AW32: 1113245 | AX32: 1069562 | AY32: ='BS - Consolidado'!J86 -> 614709 | AZ32: =AY32 -> 614709 | BA32: ='BS - Consolidado'!I86 -> 509221 | BB32: ='BS - Consolidado'!H86 -> 354676 | BC32: ='BS - Consolidado'!G86 -> 390576 | BD32: ='BS - Consolidado'!F86 -> 356196 | BE32: =BD32 -> 356196 | BF32: ='BS - Consolidado'!E86 -> 279439 | BG32: ='BS - Consolidado'!D86 -> 265029
A33: Fornecedores | B33: Trade Payables | C33: 874574 | D33: 914167 | E33: 1080719 | F33: 936491 | G33: 936491 | H33: 813219 | I33: 806110 | J33: 730800 | K33: 856084 | L33: 856084 | M33: 853623 | N33: 978150 | O33: 955804 | P33: 1056299 | Q33: 1056299 | R33: 1146239 | S33: 1365829 | T33: 1372013 | U33: 1316903 | V33: 1316903 | W33: 1367348 | X33: 1246438 | Y33: 1228512 | Z33: 1126821 | AA33: 1126821 | AB33: 1436452 | AC33: 919013 | AD33: 1349412 | AE33: 1463594 | AF33: 1463594 | AG33: 1729247 | AH33: 1700511 | AI33: 1974037 | AJ33: 2269458 | AK33: 2269458 | AL33: 2009326 | AM33: 2493077 | AN33: 2388009 | AO33: 2294570 | AP33: 2294570 | AQ33: 2273866 | AR33: 2085250 | AS33: 2080949 | AT33: 1906468 | AU33: 1906468 | AV33: 2082011 | AW33: 2292708 | AX33: 2208094 | AY33: ='BS - Consolidado'!J76 -> 2263044 | AZ33: =AY33 -> 2263044 | BA33: ='BS - Consolidado'!I76 -> 2467337 | BB33: ='BS - Consolidado'!H76 -> 2441738 | BC33: ='BS - Consolidado'!G76 -> 2100209 | BD33: ='BS - Consolidado'!F76 -> 1950556 | BE33: =BD33 -> 1950556 | BF33: ='BS - Consolidado'!E76 -> 2295142 | BG33: ='BS - Consolidado'!D76 -> 2522216
A34: Obrigações Fiscais | B34: Tax obligations | C34: 74195 | D34: 58652 | E34: 70292 | F34: 55897 | G34: 55897 | H34: 68181 | I34: 60106 | J34: 76595 | K34: 77103 | L34: 77103 | M34: 109234 | N34: 135423 | O34: 151118 | P34: 133550 | Q34: 133550 | R34: 134495 | S34: 159266 | T34: 198779 | U34: 121901 | V34: 121901 | W34: 138571 | X34: 172239 | Y34: 216024 | Z34: 121060 | AA34: 121060 | AB34: 93075 | AC34: 73495 | AD34: 123405 | AE34: 90868 | AF34: 90868 | AG34: 117971 | AH34: 220606 | AI34: 284710 | AJ34: 220549 | AK34: 220549 | AL34: 175807 | AM34: 211394 | AN34: 253510 | AO34: 317483 | AP34: 317483 | AQ34: 149626 | AR34: 164540 | AS34: 171878 | AT34: 126797 | AU34: 126797 | AV34: 172569 | AW34: 193817 | AX34: 229013 | AY34: ='BS - Consolidado'!J81 -> 210899 | AZ34: =AY34 -> 210899 | BA34: ='BS - Consolidado'!I81 -> 162633 | BB34: ='BS - Consolidado'!H81 -> 153543 | BC34: ='BS - Consolidado'!G81 -> 153051 | BD34: ='BS - Consolidado'!F81 -> 196478 | BE34: =BD34 -> 196478 | BF34: ='BS - Consolidado'!E81 -> 157826 | BG34: ='BS - Consolidado'!D81 -> 193620
A35: Obrigações Sociais e Trabalhistas | B35: Social and Labor Obligations | C35: =152061+46943 -> 199004 | D35: =104222+51017 -> 155239 | E35: 194825 | F35: 161260 | G35: 161260 | H35: 182197 | I35: =120566+69852 -> 190418 | J35: =130424+83124 -> 213548 | K35: =149649+54180 -> 203829 | L35: =149649+54180 -> 203829 | M35: =163018+71449 -> 234467 | N35: 232666 | O35: 257416 | P35: =181448+70488 -> 251936 | Q35: =181448+70488 -> 251936 | R35: =158828+92111 -> 250939 | S35: 297134 | T35: =212423+127888 -> 340311 | U35: =235284+92987 -> 328271 | V35: 328271 | W35: =193602+112474 -> 306076 | X35: =194728+132162 -> 326890 | Y35: =216525+145449 -> 361974 | Z35: =239012+83076 -> 322088 | AA35: 322088 | AB35: =221479+105276 -> 326755 | AC35: =254245+97427 -> 351672 | AD35: =252905+123828 -> 376733 | AE35: 318632 | AF35: 318632 | AG35: 399131 | AH35: 441451 | AI35: =361011+175984 -> 536995 | AJ35: =395998+111950 -> 507948 | AK35: =395998+111950 -> 507948 | AL35: =286356+146134 -> 432490 | AM35: =299019+174056 -> 473075 | AN35: =339989+196165 -> 536154 | AO35: 502106 | AP35: 502106 | AQ35: 559435 | AR35: 452827 | AS35: 507656 | AT35: 451023 | AU35: 451023 | AV35: 512995 | AW35: 506597 | AX35: 550070 | AY35: ='BS - Consolidado'!J73 -> 526158 | AZ35: =AY35 -> 526158 | BA35: ='BS - Consolidado'!I73 -> 591797 | BB35: ='BS - Consolidado'!H73 -> 552854 | BC35: ='BS - Consolidado'!G73 -> 579471 | BD35: ='BS - Consolidado'!F73 -> 496288 | BE35: =BD35 -> 496288 | BF35: ='BS - Consolidado'!E73 -> 560309 | BG35: ='BS - Consolidado'!D73 -> 559457
A36: Adiantamentos de Clientes | B36: Advances from Customers | C36: 16578 | D36: 17601 | E36: 56573 | F36: 89559 | G36: 89559 | H36: 28172 | I36: 31254 | J36: 33085 | K36: 55942 | L36: 55942 | M36: 66589 | N36: 89275 | O36: 101088 | P36: 99795 | Q36: 99795 | R36: 120363 | S36: 129266 | T36: 129408 | U36: 109025 | V36: 109025 | W36: 111520 | X36: 76239 | Y36: 69118 | Z36: 27244 | AA36: 27244 | AB36: 48317 | AC36: 47215 | AD36: 53239 | AE36: 58849 | AF36: 58849 | AG36: 78299 | AH36: 102615 | AI36: 68904 | AJ36: 83113 | AK36: 83113 | AL36: 81757 | AM36: 83481 | AN36: 110416 | AO36: 66561 | AP36: 66561 | AQ36: 63351 | AR36: 59910 | AS36: 51739 | AT36: 47539 | AU36: 47539 | AV36: 55435 | AW36: 42311 | AX36: 109966 | AY36: ='BS - Consolidado'!J101 -> 50633 | AZ36: =AY36 -> 50633 | BA36: ='BS - Consolidado'!I101 -> 38672 | BB36: ='BS - Consolidado'!H101 -> 37294 | BC36: ='BS - Consolidado'!G101 -> 36286 | BD36: ='BS - Consolidado'!F101 -> 27993 | BE36: =BD36 -> 27993 | BF36: ='BS - Consolidado'!E101 -> 20769 | BG36: ='BS - Consolidado'!D101 -> 24426
A37: Instrumento Financeiro Derivativo | B37: Derivative Financial Instruments | C37: - | D37: - | E37: - | F37: - | G37: - | H37: - | I37: - | J37: - | K37: - | L37: - | M37: - | O37: - | P37: - | Q37: - | R37: - | S37: - | T37: - | U37: - | V37: - | W37: - | X37: - | Y37: - | Z37: - | AA37: - | AB37: - | AC37: - | AD37: - | AE37: - | AF37: - | AG37: - | AH37: - | AI37: - | AJ37: - | AK37: - | AL37: 14327 | AM37: 14315 | AN37: 10260 | AO37: 16250 | AP37: 16250 | AQ37: 14940 | AR37: 15783 | AS37: 7067 | AT37: 18662 | AU37: 18662 | AV37: 2247 | AW37: 722 | AX37: 8504 | AY37: ='BS - Consolidado'!J103 -> 235 | AZ37: =AY37 -> 235 | BA37: ='BS - Consolidado'!I103 -> 219 | BB37: ='BS - Consolidado'!H103 -> 10698 | BC37: ='BS - Consolidado'!G103 -> 2543 | BD37: ='BS - Consolidado'!F103 -> 1023 | BE37: =BD37 -> 1023 | BF37: ='BS - Consolidado'!E103 -> 0 | BG37: ='BS - Consolidado'!D103 -> 0
A38: Dividendos e Juros Sobre Capital Próprio a Pagar | B38: Dividends and Interests on Capital | C38: - | D38: - | E38: - | F38: 21166 | G38: 21166 | H38: 86440 | I38: 78216 | J38: 305 | K38: 10751 | L38: 10751 | M38: 73718 | N38: 70498 | O38: 25881 | P38: 5436 | Q38: 5436 | R38: 93564 | S38: 53138 | T38: 79606 | U38: 99199 | V38: 99199 | W38: 56352 | X38: 56117 | Y38: 65930 | Z38: 127147 | AA38: 127147 | AB38: 81676 | AC38: 86596 | AD38: 93026 | AE38: 89731 | AF38: 89731 | AG38: 74790 | AH38: 55756 | AI38: 34025 | AJ38: 201326 | AK38: 201326 | AL38: 37290 | AM38: 61023 | AN38: 78816 | AO38: 125623 | AP38: 125623 | AQ38: 101712 | AR38: 42432 | AS38: 21531 | AT38: 13465 | AU38: 13465 | AV38: 85797 | AW38: 97359 | AX38: 112474 | AY38: ='BS - Consolidado'!J98 -> 99673 | AZ38: =AY38 -> 99673 | BA38: ='BS - Consolidado'!I98 -> 135133 | BB38: ='BS - Consolidado'!H98 -> 101219 | BC38: ='BS - Consolidado'!G98 -> 120177 | BD38: ='BS - Consolidado'!F98 -> 42437 | BE38: =BD38 -> 42437 | BF38: ='BS - Consolidado'!E98 -> 95340 | BG38: ='BS - Consolidado'!D98 -> 52247
A39: Outras Obrigações | B39: Other | C39: 171358 | D39: 180724 | E39: 172383 | F39: 139675 | G39: 139675 | H39: 146850 | I39: 207282 | J39: 202473 | K39: 135202 | L39: 135202 | M39: 138895 | N39: 147535 | O39: 173176 | P39: 161294 | Q39: 161294 | R39: 190927 | S39: 199587 | T39: 185617 | U39: 210381 | V39: 210381 | W39: 251630 | X39: 231278 | Y39: 248312 | Z39: 210561 | AA39: 210561 | AB39: 245445 | AC39: 296446 | AD39: 360805 | AE39: 423213 | AF39: 423213 | AG39: 436883 | AH39: 462058 | AI39: =465146+28544 -> 493690 | AJ39: =375209+27344 -> 402553 | AK39: =375209+27344 -> 402553 | AL39: =405432+22420 -> 427852 | AM39: =359139+20709 -> 379848 | AN39: =412800+15719 -> 428519 | AO39: 402259 | AP39: 402259 | AQ39: 475057 | AR39: 499814 | AS39: 489167 | AT39: 421833 | AU39: 421833 | AV39: 387875 | AW39: 461573 | AX39: 512506 | AY39: ='BS - Consolidado'!J102 -> 540808 | AZ39: =AY39 -> 540808 | BA39: ='BS - Consolidado'!I102 -> 556061 | BB39: ='BS - Consolidado'!H102 -> 476205 | BC39: ='BS - Consolidado'!G102 -> 406249 | BD39: ='BS - Consolidado'!F102 -> 427993 | BE39: =BD39 -> 427993 | BF39: ='BS - Consolidado'!E102 -> 427191 | BG39: ='BS - Consolidado'!D102 -> 503534
C40: =SUM(C32:C39) -> 2735570 | D40: =SUM(D32:D39) -> 2804035 | E40: =SUM(E32:E39) -> 3212579 | F40: =SUM(F32:F39) -> 3088750 | G40: =SUM(G32:G39) -> 3088750 | H40: =SUM(H32:H39) -> 3050738 | I40: =SUM(I32:I39) -> 2543452 | J40: =SUM(J32:J39) -> 2401347 | ... U40: =SUM(U32:U39) -> 3261829 | V40: 3261829 | W40: =SUM(W32:W39) -> 3099445 | X40: =SUM(X32:X39) -> 2853138 | Y40: =SUM(Y32:Y39) -> 2915325 | Z40: =SUM(Z32:Z39) -> 2583618 | AA40: 2583618 | AB40: =SUM(AB32:AB39) -> 3694293 | AC40: =SUM(AC32:AC39) -> 3602714 | AD40: =SUM(AD32:AD39) -> 4693039 | AE40: =SUM(AE32:AE39) -> 4352451 | AF40: 4352451 | AG40: =SUM(AG32:AG39) -> 6139477 | AH40: =SUM(AH32:AH39) -> 4781777 | AI40: =SUM(AI32:AI39) -> 5251184 | AJ40: =SUM(AJ32:AJ39) -> 5166728 | AK40: =SUM(AK32:AK39) -> 5166728 | AL40: =SUM(AL32:AL39) -> 5201765 | AM40: =SUM(AM32:AM39) -> 4993647 | AN40: =SUM(AN32:AN39) -> 5076040 | AO40: =SUM(AO32:AO39) -> 4768463 | AP40: 4768463 | AQ40: =SUM(AQ32:AQ39) -> 5655709 | AR40: =SUM(AR32:AR39) -> 5134119 | AS40: =SUM(AS32:AS39) -> 5105334 | AT40: =SUM(AT32:AT39) -> 4617386 | AU40: =SUM(AU32:AU39) -> 4617386 | AV40: =SUM(AV32:AV39) -> 4685931 | AW40: =SUM(AW32:AW39) -> 4708332 | AX40: =SUM(AX32:AX39) -> 4800189 | ... BG40: =SUM(BG32:BG39) -> 4120529
C41: - | D41: - | E41: -
A42: NÃO CIRCULANTE | B42: LONG TERM | C42: - | D42: - | E42: -
A43: Empréstimos, financiamentos e debêntures | B43: Borrowings, Financing and Debentures | C43: 1790353 | D43: 1622068 | E43: 1783196 | F43: 1730153 | G43: 1730153 | H43: 1628772 | I43: 1917312 | J43: 1964462 | K43: 1877277 | L43: 1877277 | M43: 2030521 | N43: 1707481 | O43: 1635279 | P43: 1490732 | Q43: 1490732 | R43: =1276149+602131 -> 1878280 | S43: 1841657 | T43: =1375449+445453 -> 1820902 | U43: =1291758+445798 -> 1737556 | V43: 1737556 | W43: =1404227+890080 -> 2294307 | X43: =1358854+890776 -> 2249630 | Y43: =1394744+1239285 -> 2634029 | Z43: =1173173+1239713 -> 2412886 | AA43: 2412886 | AB43: =1597034+1240433 -> 2837467 | AC43: =1959363+1241100 -> 3200463 | AD43: 3043845 | AE43: 3212825 | AF43: 3212825 | AG43: 2263046 | AH43: 3574364 | AI43: =2761160+1004462 -> 3765622 | AJ43: =3041331+1009098 -> 4050429 | AK43: =3041331+1009098 -> 4050429 | AL43: =3047073+618636 -> 3665709 | AM43: =3373338+1365491 -> 4738829 | AN43: =3737169+1193190 -> 4930359 | AO43: 5433377 | AP43: 5433377 | AQ43: 4924655 | AR43: 4382987 | AS43: 5092090 | AT43: 5133934 | AU43: 5133934 | AV43: 4875884 | AW43: 5244652 | AX43: 5144600 | AY43: ='BS - Consolidado'!J118 -> 5774050 | AZ43: =AY43 -> 5774050 | BA43: ='BS - Consolidado'!I118 -> 5314654 | BB43: ='BS - Consolidado'!H118 -> 5240740 | BC43: ='BS - Consolidado'!G118 -> 5240584 | BD43: ='BS - Consolidado'!F118 -> 5275350 | BE43: =BD43 -> 5275350 | BF43: ='BS - Consolidado'!E118 -> 5428057 | BG43: ='BS - Consolidado'!D118 -> 5398534
A44: Provisão para riscos tributários, cíveis e trabalhistas | B44: Provision for tax, civil and labor risks | C44: 26005 | D44: 25223 | E44: 40963 | F44: 48679 | G44: 48679 | H44: 48334 | I44: 37631 | J44: 41605 | K44: 70650 | L44: 70650 | M44: 74973 | N44: 80842 | O44: 89573 | P44: 100663 | Q44: 100663 | R44: 106686 | S44: 104829 | T44: 111900 | U44: 105150 | V44: 105150 | W44: 101410 | X44: 84568 | Y44: 86542 | Z44: 83753 | AA44: 83753 | AB44: 82744 | AC44: 84136 | AD44: 104246 | AE44: 79423 | AF44: 79423 | AG44: 90726 | AH44: 86108 | AI44: 100176 | AJ44: 90893 | AK44: 90893 | AL44: 92759 | AM44: 77558 | AN44: 79580 | AO44: 78574 | AP44: 78574 | AQ44: 77939 | AR44: 79259 | AS44: 78045 | AT44: 78965 | AU44: 78965 | AV44: 83760 | AW44: 85485 | AX44: 65433 | AY44: ='BS - Consolidado'!J138 -> 62577 | AZ44: =AY44 -> 62577 | BA44: ='BS - Consolidado'!I138 -> 61878 | BB44: ='BS - Consolidado'!H138 -> 62266 | BC44: ='BS - Consolidado'!G138 -> 61031 | BD44: ='BS - Consolidado'!F138 -> 42040 | BE44: =BD44 -> 42040 | BF44: ='BS - Consolidado'!E138 -> 45656 | BG44: ='BS - Consolidado'!D138 -> 65991
A45: Imposto de Renda e Contribuição Social Diferidos | B45: Deferred Income Tax and Social Contribution | C45: 179030 | D45: 153767 | E45: 185458 | F45: 164662 | G45: 164662 | H45: 162240 | I45: 146056 | J45: 146301 | K45: 162883 | L45: 162883 | M45: 164849 | N45: 181786 | O45: 176300 | P45: 169030 | Q45: 169030 | R45: 163462 | S45: 201689 | T45: 221847 | U45: 199862 | V45: 199862 | W45: 178767 | X45: 165427 | Y45: 182911 | Z45: 174548 | AA45: 174548 | AB45: 198721 | AC45: 203951 | AD45: 221660 | AE45: 175180 | AF45: 175180 | AG45: 192230 | AH45: 160053 | AI45: 166283 | AJ45: 120725 | AK45: 120725 | AL45: 88254 | AM45: 109058 | AN45: 82710 | AO45: 42904 | AP45: 42904 | AQ45: 19869 | AR45: 52507 | AS45: 52221 | AT45: 47568 | AU45: 47568 | AV45: 37286 | AW45: 69025 | AX45: 57485 | AY45: ='BS - Consolidado'!J135 -> 75899 | AZ45: =AY45 -> 75899 | BA45: ='BS - Consolidado'!I135 -> 69199 | BB45: ='BS - Consolidado'!H135 -> 77302 | BC45: ='BS - Consolidado'!G135 -> 60833 | BD45: ='BS - Consolidado'!F135 -> 40968 | BE45: =BD45 -> 40968 | BF45: ='BS - Consolidado'!E135 -> 35498 | BG45: ='BS - Consolidado'!D135 -> 34595
A46: Instrumento Financeiro Derivativo | B46: Derivative Financial Instruments | C46: - | D46: - | E46: - | F46: - | G46: - | H46: - | I46: - | J46: - | K46: - | L46: - | M46: - | N46: - | O46: - | P46: - | Q46: - | R46: - | S46: - | T46: - | U46: - | V46: - | W46: - | X46: - | Y46: - | Z46: - | AA46: - | AB46: - | AC46: - | AD46: - | AE46: - | AF46: - | AG46: - | AH46: - | AI46: - | AJ46: - | AK46: - | AL46: 1378 | AM46: 5464 | AN46: - | AO46: 1591 | AP46: 1591 | AR46: 0 | AS46: 0 | AT46: 489 | AU46: 489 | AV46: 450 | AW46: 206 | AX46: 103 | AY46: ='BS - Consolidado'!J134 -> 0 | AZ46: =AY46 -> 0 | BA46: ='BS - Consolidado'!I134 -> 0 | BB46: ='BS - Consolidado'!H134 -> 0 | BC46: ='BS - Consolidado'!G134 -> 0 | BD46: ='BS - Consolidado'!F134 -> 0 | BE46: =BD46 -> 0 | BF46: ='BS - Consolidado'!E134 -> 0 | BG46: ='BS - Consolidado'!D134 -> 0
A47: Passivo a descoberto de controladas | B47: Unsecured Liabilities in Subsidiaries | C47: 9349 | D47: - | E47: - | F47: - | G47: - | H47: - | I47: - | J47: - | K47: - | L47: - | M47: - | N47: - | O47: - | P47: - | Q47: - | R47: - | S47: - | T47: - | U47: - | V47: - | W47: - | X47: - | Y47: - | Z47: - | AA47: - | AB47: - | AC47: - | AD47: - | AE47: - | AF47: - | AG47: - | AH47: - | AI47: - | AJ47: - | AK47: - | AL47: - | AM47: - | AN47: - | AO47: - | AP47: - | AQ47: - | AR47: - | AS47: - | AT47: - | AU47: - | AV47: - | AY47: - | AZ47: =AY47 -> - | BA47: - | BB47: - | BC47: - | BD47: - | BE47: =BD47 -> - | BF47: - | BG47: -
A48: Passivo Atuarial de Plano de Pensão | B48: Pension Plan Liabilities | C48: 389153 | D48: 387201 | E48: 489991 | F48: 462299 | G48: 462299 | H48: 436969 | I48: 379533 | J48: 387215 | K48: 383157 | L48: 383157 | M48: 374882 | N48: 412973 | O48: 404578 | P48: 421237 | Q48: 421237 | R48: 429673 | S48: 466872 | T48: 474051 | U48: 471053 | V48: 471053 | W48: 463959 | X48: 459380 | Y48: 478073 | Z48: 515932 | AA48: 515932 | AB48: 641121 | AC48: 678251 | AD48: 715811 | AE48: 701929 | AF48: 701929 | AG48: 730273 | AH48: 643352 | AI48: 677397 | AJ48: 616795 | AK48: 616795 | AL48: 512224 | AM48: 535043 | AN48: =515240 -> 515240 | AO48: 462259 | AP48: 462259 | AQ48: 436477 | AR48: 418091 | AS48: 420829 | AT48: 424222 | AU48: 424222 | AV48: 444097 | AW48: 459977 | AX48: 460629 | AY48: ='BS - Consolidado'!J147 -> 477376 | AZ48: =AY48 -> 477376 | BA48: ='BS - Consolidado'!I147 -> 450596 | BB48: ='BS - Consolidado'!H147 -> 479171 | BC48: ='BS - Consolidado'!G147 -> 463888 | BD48: ='BS - Consolidado'!F147 -> 439751 | BE48: =BD48 -> 439751 | BF48: ='BS - Consolidado'!E147 -> 431370 | BG48: ='BS - Consolidado'!D147 -> 424604
A49: Outras Obrigações | B49: Other | C49: 42210 | D49: 52857 | E49: 48460 | F49: 39346 | G49: 39346 | H49: 34679 | I49: 24751 | J49: 23797 | K49: 24352 | L49: 24352 | M49: 24579 | N49: 28358 | O49: 36168 | P49: 49227 | Q49: 49227 | R49: 46136 | S49: 46583 | T49: 47899 | U49: 45213 | V49: 45213 | W49: 88021 | X49: 94543 | Y49: 99275 | Z49: 107698 | AA49: 107698 | AB49: 78463 | AC49: 78398 | AD49: 76049 | AE49: 87234 | AF49: 87234 | AG49: 86951 | AH49: 64431 | AI49: =29955+26233 -> 56188 | AJ49: =51937+23904 -> 75841 | AK49: =51937+23904 -> 75841 | AL49: =91119+16333 -> 107452 | AM49: =88251+16793 -> 105044 | AN49: =86362+16342 -> 102704 | AO49: 115480 | AP49: 115480 | AQ49: 136452 | AR49: 117794 | AS49: 126059 | AT49: 146523 | AU49: 146523 | AV49: 134841 | AW49: 181828 | AX49: 184417 | AY49: ='BS - Consolidado'!J129 -> 194328 | AZ49: =AY49 -> 194328 | BA49: ='BS - Consolidado'!I129 -> 193529 | BB49: ='BS - Consolidado'!H129 -> 170753 | BC49: ='BS - Consolidado'!G129 -> 169008 | BD49: ='BS - Consolidado'!F129 -> 243662 | BE49: =BD49 -> 243662 | BF49: ='BS - Consolidado'!E129 -> 208688 | BG49: ='BS - Consolidado'!D129 -> 198369
C50: =SUM(C43:C49) -> 2436100 | D50: =SUM(D43:D49) -> 2241116 | E50: =SUM(E43:E49) -> 2548068 | F50: =SUM(F43:F49) -> 2445139 | G50: =SUM(G43:G49) -> 2445139 | H50: =SUM(H43:H49) -> 2310994 | I50: =SUM(I43:I49) -> 2505283 | J50: =SUM(J43:J49) -> 2563380 | ... U50: =SUM(U43:U49) -> 2558834 | V50: 2558834 | W50: =SUM(W43:W49) -> 3126464 | X50: =SUM(X43:X49) -> 3053548 | Y50: =SUM(Y43:Y49) -> 3480830 | Z50: =SUM(Z43:Z49) -> 3294817 | AA50: 3294817 | AB50: =SUM(AB43:AB49) -> 3838516 | AC50: =SUM(AC43:AC49) -> 4245199 | AD50: =SUM(AD43:AD49) -> 4161611 | AE50: =SUM(AE43:AE49) -> 4256591 | AF50: 4256591 | AG50: =SUM(AG43:AG49) -> 3363226 | AH50: =SUM(AH43:AH49) -> 4528308 | AI50: =SUM(AI43:AI49) -> 4765666 | AJ50: =SUM(AJ43:AJ49) -> 4954683 | AK50: =SUM(AK43:AK49) -> 4954683 | AL50: =SUM(AL43:AL49) -> 4467776 | AM50: =SUM(AM43:AM49) -> 5570996 | AN50: =SUM(AN43:AN49) -> 5710593 | AO50: =SUM(AO43:AO49) -> 6134185 | AP50: 6134185 | AQ50: =SUM(AQ43:AQ49) -> 5595392 | AR50: =SUM(AR43:AR49) -> 5050638 | AS50: =SUM(AS43:AS49) -> 5769244 | AT50: =SUM(AT43:AT49) -> 5831701 | AU50: =SUM(AU43:AU49) -> 5831701 | AV50: =SUM(AV43:AV49) -> 5576318 | AW50: =SUM(AW43:AW49) -> 6041173 | AX50: =SUM(AX43:AX49) -> 5912667 | ... BG50: =SUM(BG43:BG49) -> 6122093
A51: PATRIMONIO LÍQUIDO | B51: EQUITY
A52: Capital social | B52: Issued Capital | C52: 700000 | D52: 700000 | E52: 700000 | F52: 700000 | G52: 700000 | H52: 700000 | I52: 700000 | J52: 700000 | K52: 700000 | L52: 700000 | M52: 1254323 | N52: 1254422 | O52: 1262653 | P52: 1277398 | Q52: 1277398 | R52: 1407536 | S52: 1407536 | T52: 1407536 | U52: 1407536 | V52: 1407536 | W52: 1407536 | X52: 1447474 | Y52: 1447474 | Z52: 1576954 | AA52: 1576954 | AB52: 1576954 | AC52: 1576954 | AD52: 1576954 | AE52: 1576954 | AF52: 1576954 | AG52: 1576954 | AH52: 1576954 | AI52: 1576954 | AJ52: 1576954 | AK52: 1576954 | AL52: 1576954 | AM52: 1576954 | AN52: 1576954 | AO52: 1576954 | AP52: 1576954 | AQ52: 1576954 | AR52: 1576954 | AS52: 1576954 | AT52: 1576954 | AU52: 1576954 | AV52: 1576954 | AW52: 1576954 | AX52: 1576954 | AY52: ='BS - Consolidado'!J156 -> 1576954 | AZ52: =AY52 -> 1576954 | BA52: ='BS - Consolidado'!I156 -> 1576954 | BB52: ='BS - Consolidado'!H156 -> 1576954 | BC52: ='BS - Consolidado'!G156 -> 1576954 | BD52: ='BS - Consolidado'!F156 -> 1576954 | BE52: ='BS - Consolidado'!G156 -> 1576954 | BF52: ='BS - Consolidado'!E156 -> 1576954 | BG52: ='BS - Consolidado'!D156 -> 1576954
A53: Opções outorgadas reconhecidas | B53: Stock Options | C53: 3083 | D53: 2783 | E53: 2783 | F53: 2783 | G53: 2783 | H53: 2783 | I53: 2783 | J53: 2783 | K53: 2783 | L53: 2783 | M53: 2783 | N53: 3019 | O53: 3061 | P53: 3080 | Q53: 3080 | R53: 3094 | S53: 3025 | T53: 3049 | U53: 3084 | V53: 3084 | W53: 3084 | X53: 3100 | Y53: 3071 | Z53: 3071 | AA53: 3071 | AB53: 3061 | AC53: 3061 | AD53: 3061 | AE53: 3061 | AF53: 3061 | AG53: 3061 | AH53: 3061 | AI53: 3061 | AJ53: 3061 | AK53: 3061 | AL53: 3061 | AM53: 3061 | AN53: 3061 | AO53: 3061 | AP53: 3061 | AQ53: 3061 | AR53: 3061 | AS53: 0 | AT53: 0 | AU53: 0 | AV53: 0 | AW53: 0 | AZ53: =AY53 -> 0
A54: Reservas de lucros | B54: Earning reserves | C54: 256546 | D54: 256846 | E54: 256846 | F54: 292407 | G54: 292407 | H54: 292407 | I54: 292407 | J54: 292407 | K54: 310193 | L54: 310193 | M54: 310193 | N54: 310193 | O54: 310193 | P54: 317286 | Q54: 317286 | R54: 404280 | S54: 252380 | T54: 217899 | U54: 393156 | V54: 393156 | W54: 393156 | X54: 393156 | Y54: 364959 | Z54: 606530 | AA54: 606530 | AB54: 606530 | AC54: 606530 | AD54: 606530 | AE54: 120921 | AF54: 120921 | AG54: 120921 | AH54: 120921 | AI54: 120921 | AJ54: 450209 | AK54: 450209 | AL54: 450209 | AM54: 414628 | AN54: 384583 | AO54: 623446 | AP54: 623446 | AQ54: 623446 | AR54: 623446 | AS54: 623446 | AT54: 645807.85 | AU54: 645807.85 | AV54: 645808 | AW54: 626617 | AX54: 568358 | AY54: ='BS - Consolidado'!J166 -> 807705 | AZ54: =AY54 -> 807705 | BA54: ='BS - Consolidado'!I166 -> 807705 | BB54: ='BS - Consolidado'!H166 -> 807705 | BC54: ='BS - Consolidado'!G166 -> 761705 | BD54: ='BS - Consolidado'!F166 -> 862297 | BE54: =BD54 -> 862297 | BF54: ='BS - Consolidado'!E166 -> 862297 | BG54: ='BS - Consolidado'!D166 -> 862297
A55: Reserva de capital | B55: Capital reserves | S55: 116298 | T55: 116298 | U55: 127006 | V55: 127006 | W55: 127006 | X55: 133113 | Y55: 139616 | Z55: 6000 | AA55: 6000 | AB55: 6000 | AC55: 6000 | AD55: 6000 | AE55: 12467 | AF55: 12467 | AG55: 12467 | AH55: 12467 | AI55: 12467 | AJ55: 21301 | AK55: 21301 | AL55: 21301 | AM55: 21301 | AN55: 34484 | AO55: 34484 | AP55: 34484 | AQ55: 34484 | AR55: 45214 | AS55: 48275 | AT55: 48275 | AU55: 48275 | AV55: 3061 | AW55: 3061 | AX55: 3061 | AY55: ='BS - Consolidado'!J164 -> 3061 | AZ55: =AY55 -> 3061 | BA55: ='BS - Consolidado'!I164 -> 3061 | BB55: ='BS - Consolidado'!H164 -> 3061 | BC55: ='BS - Consolidado'!G164 -> 3061 | BD55: ='BS - Consolidado'!F164 -> 3061 | BE55: =BD55 -> 3061 | BF55: ='BS - Consolidado'!E164 -> 3061 | BG55: ='BS - Consolidado'!D164 -> 3061
A56: Ações em tesouraria | B56: Treasury Shares | C56: -6097 | D56: -6079 | E56: -6060 | F56: -6042 | G56: -6042 | H56: -6023 | I56: -6005 | J56: -8142 | K56: -8091 | L56: -8091 | M56: -8060 | N56: -12939 | O56: -12939 | P56: -12880 | Q56: -12880 | R56: -26213 | S56: -26046 | T56: -26046 | U56: -26022 | V56: -26022 | W56: -29009 | X56: -28988 | Y56: -28920 | Z56: -28920 | AA56: -28920 | AB56: -28894 | AC56: -28894 | AD56: -28894 | AE56: -28894 | AF56: -28894 | AG56: -28894 | AH56: -28894 | AI56: -28894 | AJ56: -28894 | AK56: -28894 | AL56: -41448 | AM56: -41448 | AN56: -41448 | AO56: -41448 | AP56: -41448 | AQ56: -48032 | AR56: -55539 | AS56: -55539 | AT56: -55539 | AU56: -55539 | AV56: -62353 | AW56: -62353 | AX56: -62353 | AY56: ='BS - Consolidado'!J162 -> -62353 | AZ56: =AY56 -> -62353 | BA56: ='BS - Consolidado'!I162 -> -62353 | BB56: ='BS - Consolidado'!H162 -> -62353 | BC56: ='BS - Consolidado'!G162 -> -62353 | BD56: ='BS - Consolidado'!F162 -> -62353 | BE56: =BD56 -> -62353 | BF56: ='BS - Consolidado'!E162 -> -62353 | BG56: ='BS - Consolidado'!D162 -> -62353
A57: Ajuste de avaliação patrimonial | B57: Equity valuation adjustment | C57: 738175 | D57: 673793 | E57: 1219955 | F57: 1164299 | G57: 1164299 | H57: 981896 | I57: 800284 | J57: 828716 | K57: 779100 | L57: 779100 | M57: 748845 | N57: 793487 | O57: 744741 | P57: 838674 | Q57: 838674 | R57: 825242 | S57: 1028423 | T57: 1141632 | U57: 1059662 | V57: 1059662 | W57: 1050437 | X57: 1034227 | Y57: 1194021 | Z57: 1099760 | AA57: 1099760 | AB57: 1747513 | AC57: 1938867 | AD57: =2032791+4639 -> 2037430 | AE57: 1777776 | AF57: 1777776 | AG57: 2101020 | AH57: 1645421 | AI57: =1883549+58365 -> 1941914 | AJ57: =1912937+56867 -> 1969804 | AK57: =1912937+56867 -> 1969804 | AL57: =1321308+55419 -> 1376727 | AM57: =1607579+53957 -> 1661536 | AN57: =1606224+52503 -> 1658727 | AO57: 1723310 | AP57: 1723310 | AQ57: 1690301 | AR57: 1547434 | AS57: 1599199 | AT57: 1478128 | AU57: 1478128 | AV57: 1572594 | AW57: 1883169 | AX57: 1856271 | AY57: ='BS - Consolidado'!J178+'BS - Consolidado'!J181+'BS - Consolidado'!J183 -> 2232538 | AZ57: =AY57 -> 2232538 | BA57: ='BS - Consolidado'!I178+'BS - Consolidado'!I181+'BS - Consolidado'!I183 -> 1969861 | BB57: ='BS - Consolidado'!H178+'BS - Consolidado'!H181+'BS - Consolidado'!H183 -> 1893395 | BC57: ='BS - Consolidado'!G178+'BS - Consolidado'!G181+'BS - Consolidado'!G183 -> 1784690 | BD57: ='BS - Consolidado'!F178+'BS - Consolidado'!F181+'BS - Consolidado'!F183 -> 1941764 | BE57: =BD57 -> 1941764 | BF57: ='BS - Consolidado'!E178+'BS - Consolidado'!E181+'BS - Consolidado'!E183 -> 1713983 | BG57: ='BS - Consolidado'!D178+'BS - Consolidado'!D181+'BS - Consolidado'!D183 -> 1624446
A58: Outros resultados abrangentes Plano de Pensão | G58: - | L58: - | P58: -35705 | Q58: -35705 | R58: -7680 | T58: -46662 | U58: -42472 | V58: -42472 | W58: - | X58: -42472 | Y58: -42472 | Z58: -34917 | AA58: -34917 | AF58: - | AG58: - | AH58: - | AJ58: 49309 | AK58: 49309 | AL58: 49309 | AM58: 49309 | AN58: 49309 | AZ58: =AY58 -> 0
A59: Resultado do Período | B59: Period result | C59: -4318 | D59: 68438 | E59: 73069 | F59: - | G59: - | H59: 8706 | I59: 3373 | J59: 9545 | K59: - | L59: - | M59: 527 | N59: 27166 | O59: 177 | P59: - | Q59: - | R59: -6696 | S59: 39255 | T59: =124648+9846 -> 134494 | U59: - | V59: - | W59: 65004 | X59: 175221 | Y59: 301864 | Z59: - | AA59: - | AB59: =9150+1536 -> 10686 | AC59: =-343203+3088 -> -340115 | AD59: -362080 | AF59: - | AG59: 53010 | AH59: 269323 | AI59: =443305+4440 -> 447745 | AL59: =160206+1355 -> 161561 | AM59: =350691+2724 -> 353415 | AN59: =420079+4085 -> 424164 | AQ59: -15039 | AR59: 45580 | AS59: 41943 | AT59: 0 | AU59: 0 | AV59: 51139 | AW59: 88954 | AX59: 199153 | AY59: ='BS - Consolidado'!J177 -> 0 | AZ59: =AY59 -> 0 | BA59: ='BS - Consolidado'!I177 -> 11575 | BB59: ='BS - Consolidado'!H177 -> 99004 | BC59: ='BS - Consolidado'!G177 -> 134591 | BD59: ='BS - Consolidado'!F177 -> 0 | BE59: =BD59 -> 0 | BF59: ='BS - Consolidado'!E177 -> 4226 | BG59: ='BS - Consolidado'!D177 -> 91331
A61: Patrimônio Líquido Atribuído aos Acionistas Controladores | B61: Shareholders' Equity Attributed to Controlling Shareholders | C61: =SUM(C52:C59) -> 1687389 | D61: =SUM(D52:D59) -> 1695781 | E61: =SUM(E52:E59) -> 2246593 | F61: =SUM(F52:F59) -> 2153447 | G61: =SUM(G52:G59) -> 2153447 | H61: =SUM(H52:H59) -> 1979769 | I61: =SUM(I52:I59) -> 1792842 | J61: =SUM(J52:J59) -> 1825309 | ... U61: =SUM(U52:U59) -> 2921950 | V61: 2921950 | W61: =SUM(W52:W59) -> 3017214 | X61: =SUM(X52:X59) -> 3114831 | Y61: =SUM(Y52:Y59) -> 3379613 | Z61: =SUM(Z52:Z59) -> 3228478 | AA61: 3228478 | AB61: =SUM(AB52:AB59) -> 3921850 | AC61: =SUM(AC52:AC59) -> 3762403 | AD61: =SUM(AD52:AD59) -> 3839001 | AE61: =SUM(AE52:AE59) -> 3462285 | AF61: 3462285 | AG61: =SUM(AG52:AG59) -> 3838539 | AH61: =SUM(AH52:AH59) -> 3599253 | AI61: =SUM(AI52:AI59) -> 4074168 | AJ61: =SUM(AJ52:AJ59) -> 4041744 | AK61: =SUM(AK52:AK59) -> 4041744 | AL61: =SUM(AL52:AL59) -> 3597674 | AM61: =SUM(AM52:AM59) -> 4038756 | AN61: =SUM(AN52:AN59) -> 4089834 | AO61: =SUM(AO52:AO59) -> 3919807 | AP61: 3919807 | AQ61: =SUM(AQ52:AQ59) -> 3865175 | AR61: =SUM(AR52:AR59) -> 3786150 | AS61: =SUM(AS52:AS59) -> 3834278 | AT61: =SUM(AT52:AT59) -> 3693625.9 | AU61: =SUM(AU52:AU59) -> 3693625.9 | AV61: =SUM(AV52:AV59) -> 3787203 | AW61: =SUM(AW52:AW59) -> 4116402 | AX61: =SUM(AX52:AX59) -> 4141444 | ... BG61: =SUM(BG52:BG59) -> 4095736
A63: Participação dos Acionistas não Controladores | B63: Noncontrolling Interests in Subsidiaries' Equity | C63: 198309 | D63: 211313 | E63: 281231 | F63: 303043 | G63: 303043 | H63: 216744 | I63: 208640 | J63: 228364 | K63: 233092 | L63: 233092 | M63: 181714 | N63: 216744 | O63: 207930 | P63: 242652 | Q63: 242652 | R63: 176710 | S63: 217404 | T63: 242045 | U63: 276577 | V63: 276577 | W63: 197020 | X63: 215233 | Y63: 246757 | Z63: 268498 | AA63: 268498 | AB63: 262518 | AC63: 282271 | AD63: 316749 | AE63: 340476 | AF63: 340476 | AG63: 310990 | AH63: 293940 | AI63: 340455 | AJ63: 356375 | AK63: 356375 | AL63: 285634 | AM63: 310936 | AN63: 321229 | AO63: 373000 | AP63: 373000 | AQ63: 351377 | AR63: 359318 | AS63: 371386 | AT63: 391403 | AU63: 391403 | AV63: 353851 | AW63: 427762 | AX63: 454207 | AY63: ='BS - Consolidado'!J186 -> 513077 | AZ63: =AY63 -> 513077 | BA63: ='BS - Consolidado'!I186 -> 471407 | BB63: ='BS - Consolidado'!H186 -> 443826 | BC63: ='BS - Consolidado'!G186 -> 470119 | BD63: ='BS - Consolidado'!F186 -> 530026 | BE63: =BD63 -> 530026 | BF63: ='BS - Consolidado'!E186 -> 472080 | BG63: ='BS - Consolidado'!D186 -> 589269
C64: =SUM(C61:C63) -> 1885698 | D64: =SUM(D61:D63) -> 1907094 | E64: =SUM(E61:E63) -> 2527824 | F64: =SUM(F61:F63) -> 2456490 | G64: =SUM(G61:G63) -> 2456490 | H64: =SUM(H61:H63) -> 2196513 | I64: =SUM(I61:I63) -> 2001482 | J64: =SUM(J61:J63) -> 2053673 | ... U64: =SUM(U61:U63) -> 3198527 | V64: 3198527 | W64: =SUM(W61:W63) -> 3214234 | X64: =SUM(X61:X63) -> 3330064 | Y64: =SUM(Y61:Y63) -> 3626370 | Z64: =SUM(Z61:Z63) -> 3496976 | AA64: 3496976 | AB64: =SUM(AB61:AB63) -> 4184368 | AC64: =SUM(AC61:AC63) -> 4044674 | AD64: =SUM(AD61:AD63) -> 4155750 | AE64: =SUM(AE61:AE63) -> 3802761 | AF64: 3802761 | AG64: =SUM(AG61:AG63) -> 4149529 | AH64: =SUM(AH61:AH63) -> 3893193 | AI64: =SUM(AI61:AI63) -> 4414623 | AJ64: =SUM(AJ61:AJ63) -> 4398119 | AK64: =SUM(AK61:AK63) -> 4398119 | AL64: =SUM(AL61:AL63) -> 3883308 | AM64: =SUM(AM61:AM63) -> 4349692 | AN64: =SUM(AN61:AN63) -> 4411063 | AO64: =SUM(AO61:AO63) -> 4292807 | AP64: 4292807 | AQ64: =SUM(AQ61:AQ63) -> 4216552 | AR64: =SUM(AR61:AR63) -> 4145468 | AS64: =SUM(AS61:AS63) -> 4205664 | AT64: =SUM(AT61:AT63) -> 4085028.9 | AU64: =SUM(AU61:AU63) -> 4085028.9 | AV64: =SUM(AV61:AV63) -> 4141054 | AW64: =SUM(AW61:AW63) -> 4544164 | AX64: =SUM(AX61:AX63) -> 4595651 | ... BG64: =SUM(BG61:BG63) -> 4685005
A65: TOTAL DO PASSIVO E PATRIMÔNIO LÍQUIDO | B65: TOTAL LIABILITIES | C65: =C64+C50+C40 -> 7057368 | D65: =D64+D50+D40 -> 6952245 | E65: =E64+E50+E40 -> 8288471 | F65: =F64+F50+F40 -> 7990379 | G65: =G64+G50+G40 -> 7990379 | H65: =H64+H50+H40 -> 7558245 | I65: =I64+I50+I40 -> 7050217 | J65: =J64+J50+J40 -> 7018400 | ... U65: =U64+U50+U40 -> 9019190 | V65: 9019190 | W65: =W64+W50+W40 -> 9440143 | X65: =X64+X50+X40 -> 9236750 | Y65: =Y64+Y50+Y40 -> 10022525 | Z65: =Z64+Z50+Z40 -> 9375411 | AA65: 9375411 | AB65: =AB64+AB50+AB40 -> 11717177 | AC65: =AC64+AC50+AC40 -> 11892587 | AD65: =AD64+AD50+AD40 -> 13010400 | AE65: =AE64+AE50+AE40 -> 12411803 | AF65: =AF64+AF50+AF40 -> 12411803 | AG65: =AG64+AG50+AG40 -> 13652232 | AH65: =AH64+AH50+AH40 -> 13203278 | AI65: =AI64+AI50+AI40 -> 14431473 | ... AO65: =AO64+AO50+AO40 -> 15195455 | AP65: 15195455 | AQ65: =AQ64+AQ50+AQ40 -> 15467653 | AR65: =AR64+AR50+AR40 -> 14330225 | AS65: =AS64+AS50+AS40 -> 15080242 | AT65: =AT64+AT50+AT40 -> 14534116 | AU65: =AU64+AU50+AU40 -> 14534116 | AV65: =AV64+AV50+AV40 -> 14403303 | AW65: =AW64+AW50+AW40 -> 15293669 | AX65: =AX64+AX50+AX40 -> 15308507 | ... BG65: =BG64+BG50+BG40 -> 14927627

Sheet BS - Consolidado
D1: 2T26 | E1: 1T26 | F1: 4T25 | G1: 3T25 | H1: 2T25 | I1: 1T25 | J1: 4T24 | K1: 3T24 | L1: 2T24 | M1: 1T24 | N1: 4T23 | O1: 3T23 | P1: 2T23 | Q1: 1T23 | R1: 4T22 | S1: 3T22 | T1: 2T22 | U1: 1T22 | V1: 4T21 | W1: 3T21 | X1: 2T21 | Y1: 1T21 | Z1: 4T20 | AA1: 3T20 | AB1: 2T20 | AC1: 1T20 | AD1: 4T19 | AE1: 3T19 | AF1: 2T19 | AG1: 1T19 | AH1: 4T18 | AI1: 3T18 | AJ1: 2T18 | AK1: 1T18 | AL1: 4T17 | AM1: 3T17 | AN1: 2T17 | AO1: 1T17 | AP1: 4T16
A2: Codigo Conta | B2: Descricao Conta | D2: 46203 | E2: 46112 | F2: 46022 | G2: 45930 | H2: 45838 | I2: 45747 | J2: 45657 | K2: 45565 | L2: 45473 | M2: 45382 | N2: 45291 | O2: 45199 | P2: 45107 | Q2: 45016 | R2: 44926 | S2: 44834 | T2: 44742 | U2: 44651 | V2: 44561 | W2: 44469 | X2: 44377 | Y2: 44286 | Z2: 44196 | AA2: 44104 | AB2: 44012 | AC2: 43921 | AD2: 43830 | AE2: 43738 | AF2: 43646 | AG2: 43555 | AH2: 43465 | AI2: 43373 | AJ2: 43281 | AK2: 43190 | AL2: 43100 | AM2: 43008 | AN2: 42916 | AO2: 42825 | AP2: 42735
A3: 1 | B3: Ativo Total | C3: =CONCATENATE(A3,B3) -> 1Ativo Total | D3: 14927627 | E3: 14555533 | F3: 14392484 | G3: 14452673 | H3: 14920051 | I3: 15329139 | J3: 15961371 | K3: 15308507 | L3: 15293669 | M3: 14403303 | N3: 14534116 | O3: 15080242 | P3: 14330225 | Q3: 15467653 | R3: 15195455 | S3: 15197696 | T3: 14914335 | U3: 13552849 | V3: 14519530 | W3: 14431473 | X3: 13203278 | Y3: 13652232 | Z3: 12411803 | AA3: 13010400 | AB3: 11892587 | AC3: 11717177 | AD3: 9375411 | AE3: 10022525 | AF3: 9236750 | AG3: 9440143 | AH3: 9019190 | AI3: 9239909 | AJ3: 8905486 | AK3: 8510350 | AL3: 7922248 | AM3: 7671825 | AN3: 7892553 | AO3: 7424542 | AP3: 7057115
A4: 1.01 | B4: Ativo Circulante | C4: =CONCATENATE(A4,B4) -> 1.01Ativo Circulante | D4: 7132874 | E4: 6730056 | F4: 6217917 | G4: 6592673 | H4: 6926163 | I4: 7175221 | J4: 7390947 | K4: 7479973 | L4: 7499004 | M4: 7232297 | N4: 7514152 | O4: 8048781 | P4: 7448283 | Q4: 8349571 | R4: 7886325 | S4: 8021306 | T4: 7797654 | U4: 6961435 | V4: 6847514 | W4: 6953970 | X4: 6208374 | Y4: 6054354 | Z4: 5161926 | AA4: 5278408 | AB4: 4372292 | AC4: 4526247 | AD4: 3357621 | AE4: 3976211 | AF4: 3616236 | AG4: 3799311 | AH4: 3523802 | AI4: 3742941 | AJ4: 3562287 | AK4: 3640349 | AL4: 3048763 | AM4: 3014839 | AN4: 3119217 | AO4: 2829063 | AP4: 2364711
A5: 1.01.01 | B5: Caixa e Equivalentes de Caixa | C5: =CONCATENATE(A5,B5) -> 1.01.01Caixa e Equivalentes de Caixa | D5: 1868049 | E5: 1866118 | F5: 1599733 | G5: 1624952 | H5: 1678690 | I5: 1932732 | J5: 2463475 | K5: 2338050 | L5: 2255949 | M5: 2295227 | N5: 2962366 | O5: 3054672 | P5: 2458590 | Q5: 2604739 | R5: 2287054 | S5: 1604256 | T5: 1392893 | U5: 1385993 | V5: 1088114 | W5: 1006988 | X5: 1355258 | Y5: 1508930 | Z5: 1605439 | AA5: 1641643 | AB5: 1392574 | AC5: 1133921 | AD5: 646137 | AE5: 671381 | AF5: 353039 | AG5: 435074 | AH5: 486903 | AI5: 285356 | AJ5: 312904 | AK5: 820925 | AL5: 543331 | AM5: 502741 | AN5: 695515 | AO5: 690274 | AP5: 431599
A6: 1.01.02 | B6: Aplicações Financeiras | C6: =CONCATENATE(A6,B6) -> 1.01.02Aplicações Financeiras | D6: 0 | E6: 0 | F6: 0 | G6: 0 | H6: 0 | I6: 0 | J6: 0 | K6: 0 | L6: 0 | M6: 0 | N6: 0 | O6: 0 | P6: 0 | Q6: 0 | R6: 0 | S6: 0 | T6: 0 | U6: 0 | V6: 0 | W6: 0 | X6: 0 | Y6: 0 | Z6: 0 | AA6: 0 | AB6: 0 | AC6: 0 | AD6: 0 | AE6: 0 | AF6: 0 | AG6: 0 | AH6: 0 | AI6: 0 | AJ6: 0 | AK6: 0 | AL6: 0 | AM6: 0 | AN6: 0 | AO6: 0 | AP6: 0
A7: 1.01.02.01 | B7: Aplicações Financeiras Avaliadas a Valor Justo através do Resultado | C7: =CONCATENATE(A7,B7) -> 1.01.02.01Aplicações Financeiras Avaliadas a Valor Justo através do Resultado | D7: 0 | E7: 0 | F7: 0 | G7: 0 | H7: 0 | I7: 0 | J7: 0 | K7: 0 | L7: 0 | M7: 0 | N7: 0 | O7: 0 | P7: 0 | Q7: 0 | R7: 0 | S7: 0 | T7: 0 | U7: 0 | V7: 0 | W7: 0 | X7: 0 | Y7: 0 | Z7: 0 | AA7: 0 | AB7: 0 | AC7: 0 | AD7: 0 | AE7: 0 | AF7: 0 | AG7: 0 | AH7: 0 | AI7: 0 | AJ7: 0 | AK7: 0 | AL7: 0 | AM7: 0 | AN7: 0 | AO7: 0 | AP7: 0
A8: 1.01.02.01.01 | B8: Títulos para Negociação | C8: =CONCATENATE(A8,B8) -> 1.01.02.01.01Títulos para Negociação | D8: 0 | E8: 0 | F8: 0 | G8: 0 | H8: 0 | I8: 0 | J8: 0 | K8: 0 | L8: 0 | M8: 0 | N8: 0 | O8: 0 | P8: 0 | Q8: 0 | R8: 0 | S8: 0 | T8: 0 | U8: 0 | V8: 0 | W8: 0 | X8: 0 | Y8: 0 | Z8: 0 | AA8: 0 | AB8: 0 | AC8: 0 | AD8: 0 | AE8: 0 | AF8: 0 | AG8: 0 | AH8: 0 | AI8: 0 | AJ8: 0 | AK8: 0 | AL8: 0 | AM8: 0 | AN8: 0 | AO8: 0 | AP8: 0
A9: 1.01.02.01.02 | B9: Títulos Designados a Valor Justo | C9: =CONCATENATE(A9,B9) -> 1.01.02.01.02Títulos Designados a Valor Justo | D9: 0 | E9: 0 | F9: 0 | G9: 0 | H9: 0 | I9: 0 | J9: 0 | K9: 0 | L9: 0 | M9: 0 | N9: 0 | O9: 0 | P9: 0 | Q9: 0 | R9: 0 | S9: 0 | T9: 0 | U9: 0 | V9: 0 | W9: 0 | X9: 0 | Y9: 0 | Z9: 0 | AA9: 0 | AB9: 0 | AC9: 0 | AD9: 0 | AE9: 0 | AF9: 0 | AG9: 0 | AH9: 0 | AI9: 0 | AJ9: 0 | AK9: 0 | AL9: 0 | AM9: 0 | AN9: 0 | AO9: 0 | AP9: 0
A10: 1.01.02.02 | B10: Aplicações Financeiras Avaliadas a Valor Justo através de Outros Resultados Abrangentes | C10: =CONCATENATE(A10,B10) -> 1.01.02.02Aplicações Financeiras Avaliadas a Valor Justo através de Outros Resultados Abrangentes | D10: 0 | E10: 0 | F10: 0 | G10: 0 | H10: 0 | I10: 0 | J10: 0 | K10: 0 | L10: 0 | M10: 0 | N10: 0 | O10: 0 | P10: 0 | Q10: 0 | R10: 0 | S10: 0 | T10: 0 | U10: 0 | V10: 0 | W10: 0 | X10: 0 | Y10: 0 | Z10: 0 | AA10: 0 | AB10: 0 | AC10: 0 | AD10: 0 | AE10: 0 | AF10: 0 | AG10: 0 | AH10: 0 | AI10: 0 | AJ10: 0 | AK10: 0 | AL10: 0 | AM10: 0 | AN10: 0 | AO10: 0 | AP10: 0
A11: 1.01.02.03 | B11: Aplicações Financeiras Avaliadas ao Custo Amortizado | C11: =CONCATENATE(A11,B11) -> 1.01.02.03Aplicações Financeiras Avaliadas ao Custo Amortizado | D11: 0 | E11: 0 | F11: 0 | G11: 0 | H11: 0 | I11: 0 | J11: 0 | K11: 0 | L11: 0 | M11: 0 | N11: 0 | O11: 0 | P11: 0 | Q11: 0 | R11: 0 | S11: 0 | T11: 0 | U11: 0 | V11: 0 | W11: 0 | X11: 0 | Y11: 0 | Z11: 0 | AA11: 0 | AB11: 0 | AC11: 0 | AD11: 0 | AE11: 0 | AF11: 0 | AG11: 0 | AH11: 0 | AI11: 0 | AJ11: 0 | AK11: 0 | AL11: 0 | AM11: 0 | AN11: 0 | AO11: 0 | AP11: 0
A12: 1.01.03 | B12: Contas a Receber | C12: =CONCATENATE(A12,B12) -> 1.01.03Contas a Receber | D12: 1850701 | E12: 1737718 | F12: 1333705 | G12: 1544030 | H12: 1699403 | I12: 1777578 | J12: 1449118 | K12: 1714233 | L12: 1780765 | M12: 1609129 | N12: 1261050 | O12: 1526405 | P12: 1589570 | Q12: 2267301 | R12: 2053692 | S12: 2406460 | T12: 2466700 | U12: 2027779 | V12: 1731914 | W12: 2040574 | X12: 1749006 | Y12: 1824896 | Z12: 1405954 | AA12: 1528126 | AB12: 966336 | AC12: 1323161 | AD12: 1029650 | AE12: 1440886 | AF12: 1479216 | AG12: 1502342 | AH12: 1253826 | AI12: 1555906 | AJ12: 1470644 | AK12: 1306513 | AL12: 1064916 | AM12: 1141765 | AN12: 1118783 | AO12: 978340 | AP12: 835158
A13: 1.01.03.01 | B13: Clientes | C13: =CONCATENATE(A13,B13) -> 1.01.03.01Clientes | D13: 1850701 | E13: 1737718 | F13: 1333705 | G13: 1544030 | H13: 1699403 | I13: 1777578 | J13: 1449118 | K13: 1714233 | L13: 1780765 | M13: 1609129 | N13: 1261050 | O13: 1526405 | P13: 1589570 | Q13: 2267301 | R13: 2053692 | S13: 2406460 | T13: 2466700 | U13: 2027779 | V13: 1731914 | W13: 2040574 | X13: 1749006 | Y13: 1824896 | Z13: 1405954 | AA13: 1528126 | AB13: 966336 | AC13: 1323161 | AD13: 1029650 | AE13: 1440886 | AF13: 1479216 | AG13: 1502342 | AH13: 1253826 | AI13: 1555906 | AJ13: 1470644 | AK13: 1306513 | AL13: 1064916 | AM13: 1141765 | AN13: 1118783 | AO13: 978340 | AP13: 835158
A14: 1.01.03.02 | B14: Outras Contas a Receber | C14: =CONCATENATE(A14,B14) -> 1.01.03.02Outras Contas a Receber | D14: 0 | E14: 0 | F14: 0 | G14: 0 | H14: 0 | I14: 0 | J14: 0 | K14: 0 | L14: 0 | M14: 0 | N14: 0 | O14: 0 | P14: 0 | Q14: 0 | R14: 0 | S14: 0 | T14: 0 | U14: 0 | V14: 0 | W14: 0 | X14: 0 | Y14: 0 | Z14: 0 | AA14: 0 | AB14: 0 | AC14: 0 | AD14: 0 | AE14: 0 | AF14: 0 | AG14: 0 | AH14: 0 | AI14: 0 | AJ14: 0 | AK14: 0 | AL14: 0 | AM14: 0 | AN14: 0 | AO14: 0 | AP14: 0
... A67: 1.02.04.01.04 | B67: Outros Intangíveis | C67: =CONCATENATE(A67,B67) -> 1.02.04.01.04Outros Intangíveis | D67: 135898 | E67: 2052971 | F67: 160567 | G67: 160667 | H67: 171587 | I67: 173284 | J67: 186742 | K67: 185139 | L67: 183616 | M67: 171330 | N67: 174502 | O67: 178594 | P67: 181857 | Q67: 196633 | R67: 203856 | S67: 200668 | T67: 212325 | U67: 208003 | V67: 256368 | W67: 240008 | X67: 225516 | Y67: 2170229 | Z67: 243955 | AA67: 1754622 | AB67: 1751107 | AC67: 1742260 | AD67: 1631970 | AE67: 212312 | AF67: 197597 | AG67: 203195 | AH67: 204026 | AI67: 213074 | AJ67: 207339 | AK67: 180783 | AL67: 181230 | AM67: 175206 | AN67: 184446 | AO67: 178183 | AP67: 184470
A68: 1.02.04.02 | B68: Goodwill | C68: =CONCATENATE(A68,B68) -> 1.02.04.02Goodwill | D68: 0 | E68: 0 | F68: 0 | G68: 0 | H68: 0 | I68: 0 | J68: 0 | K68: 0 | L68: 0 | M68: 0 | N68: 0 | O68: 0 | P68: 0 | Q68: 0 | S68: 0 | T68: 0 | U68: 0 | V68: 0 | W68: 0 | X68: 0 | Y68: 0 | Z68: 0 | AA68: 0 | AB68: 0 | AC68: 0 | AD68: 0 | AE68: 0 | AF68: 0 | AG68: 0 | AH68: 0 | AI68: 0 | AJ68: 0 | AK68: 0 | AL68: 0 | AM68: 0 | AN68: 0 | AO68: 0 | AP68: 0
A69: 2 | B69: Passivo Total | C69: =CONCATENATE(A69,B69) -> 2Passivo Total | D69: 14927627 | E69: 14555533 | F69: 14392484 | G69: 14452673 | H69: 14920051 | I69: 15329139 | J69: 15961371 | K69: 15308507 | L69: 15293669 | M69: 14403303 | N69: 14534116 | O69: 15080242 | P69: 14330225 | Q69: 15467653 | R69: 15195455 | S69: 15197696 | T69: 14914335 | U69: 13552849 | V69: 14519530 | W69: 14431473 | X69: 13203278 | Y69: 13652232 | Z69: 12411803 | AA69: 13010400 | AB69: 11892587 | AC69: 11717177 | AD69: 9375411 | AE69: 10022525 | AF69: 9236750 | AG69: 9440143 | AH69: 9019190 | AI69: 9239909 | AJ69: 8905486 | AK69: 8510350 | AL69: 7922248 | AM69: 7671825 | AN69: 7892553 | AO69: 7424542 | AP69: 7057115
A70: 2.01 | B70: Passivo Circulante | C70: =CONCATENATE(A70,B70) -> 2.01Passivo Circulante | D70: 4120529 | E70: 3836016 | F70: 3498964 | G70: 3788562 | H70: 4128227 | I70: 4461073 | J70: 4306159 | K70: 4800188 | L70: 4708332 | M70: 4685928 | N70: 4617386 | O70: 5105334 | P70: 5134119 | Q70: 5655709 | R70: 4768463 | S70: 5076040 | T70: 4993647 | U70: 5201765 | V70: 5166728 | W70: 5251184 | X70: 4781777 | Y70: 6139477 | Z70: 4352451 | AA70: 4693039 | AB70: 3602714 | AC70: 3694293 | AD70: 2583618 | AE70: 2915325 | AF70: 2853138 | AG70: 3099445 | AH70: 3261829 | AI70: 3373065 | AJ70: 3205581 | AK70: 3109840 | AL70: 3060854 | AM70: 2814111 | AN70: 2889021 | AO70: 2264413 | AP70: 2521719
A71: 2.01.01 | B71: Obrigações Sociais e Trabalhistas | C71: =CONCATENATE(A71,B71) -> 2.01.01Obrigações Sociais e Trabalhistas | D71: 559457 | E71: 560309 | F71: 496288 | G71: 579471 | H71: 552854 | I71: 591797 | J71: 526158 | K71: 550070 | L71: 506597 | M71: 512995 | N71: 451023 | O71: 507656 | P71: 452827 | Q71: 559435 | R71: 502106 | S71: 536154 | T71: 473075 | U71: 432490 | V71: 507948 | W71: 536995 | X71: 441451 | Y71: 399131 | Z71: 318632 | AA71: 376733 | AB71: 351672 | AC71: 326755 | AD71: 322088 | AE71: 361974 | AF71: 326890 | AG71: 306076 | AH71: 328271 | AI71: 340311 | AJ71: 297134 | AK71: 250939 | AL71: 251936 | AM71: 257416 | AN71: 232666 | AO71: 234467 | AP71: 203829
A72: 2.01.01.01 | B72: Obrigações Sociais | C72: =CONCATENATE(A72,B72) -> 2.01.01.01Obrigações Sociais | D72: 0 | E72: 0 | F72: 0 | G72: 0 | H72: 0 | I72: 0 | J72: 0 | K72: 0 | L72: 0 | M72: 0 | N72: 0 | O72: 0 | P72: 0 | Q72: 0 | R72: 0 | S72: 0 | T72: 0 | U72: 0 | V72: 0 | W72: 0 | X72: 0 | Y72: 0 | Z72: 0 | AA72: 0 | AB72: 0 | AC72: 0 | AD72: 0 | AE72: 0 | AF72: 0 | AG72: 0 | AH72: 0 | AI72: 0 | AJ72: 0 | AK72: 0 | AL72: 0 | AM72: 0 | AN72: 0 | AO72: 0 | AP72: 0
A73: 2.01.01.02 | B73: Obrigações Trabalhistas | C73: =CONCATENATE(A73,B73) -> 2.01.01.02Obrigações Trabalhistas | D73: 559457 | E73: 560309 | F73: 496288 | G73: 579471 | H73: 552854 | I73: 591797 | J73: 526158 | K73: 550070 | L73: 506597 | M73: 512995 | N73: 451023 | O73: 507656 | P73: 452827 | Q73: 559435 | R73: 502106 | S73: 536154 | T73: 473075 | U73: 432490 | V73: 507948 | W73: 536995 | X73: 441451 | Y73: 399131 | Z73: 318632 | AA73: 376733 | AB73: 351672 | AC73: 326755 | AD73: 322088 | AE73: 361974 | AF73: 326890 | AG73: 306076 | AH73: 328271 | AI73: 340311 | AJ73: 297134 | AK73: 250939 | AL73: 251936 | AM73: 257416 | AN73: 232666 | AO73: 234467 | AP73: 203829
A74: 2.01.01.02.01 | B74: Obrigações trabalhistas e previdênciárias | C74: =CONCATENATE(A74,B74) -> 2.01.01.02.01Obrigações trabalhistas e previdênciárias | D74: 361409 | E74: 397926 | F74: 378708 | G74: 361146 | H74: 356664 | I74: 422106 | J74: 389381 | K74: 338798 | L74: 316823 | M74: 351716 | N74: 323370 | O74: 308747 | P74: 274066 | Q74: 407091 | R74: 382382 | S74: 339989 | T74: 299019 | U74: 286356 | V74: 395998 | W74: 361011 | X74: 294773 | Y74: 276056 | Z74: 236383 | AA74: 252905 | AB74: 254244 | AC74: 221478 | AD74: 239012 | AE74: 216525 | AF74: 194728 | AG74: 193602 | AH74: 235283 | AI74: 212423 | AJ74: 185339 | AK74: 158829 | AL74: 182667 | AM74: 152894 | AN74: 142521 | AO74: 163019 | AP74: 150110
A75: 2.01.01.02.02 | B75: Provisão de férias e encargos | C75: =CONCATENATE(A75,B75) -> 2.01.01.02.02Provisão de férias e encargos | D75: 198048 | E75: 162383 | F75: 117580 | G75: 218325 | H75: 196190 | I75: 169691 | J75: 136777 | K75: 211272 | L75: 189774 | M75: 161279 | N75: 127653 | O75: 198909 | P75: 178761 | Q75: 152344 | R75: 119724 | S75: 196165 | T75: 174056 | U75: 146134 | V75: 111950 | W75: 175984 | X75: 146678 | Y75: 123075 | Z75: 82249 | AA75: 123828 | AB75: 97428 | AC75: 105277 | AD75: 83076 | AE75: 145449 | AF75: 132162 | AG75: 112474 | AH75: 92988 | AI75: 127888 | AJ75: 111795 | AK75: 92110 | AL75: 69269 | AM75: 104522 | AN75: 90145 | AO75: 71448 | AP75: 53719
A76: 2.01.02 | B76: Fornecedores | C76: =CONCATENATE(A76,B76) -> 2.01.02Fornecedores | D76: 2522216 | E76: 2295142 | F76: 1950556 | G76: 2100209 | H76: 2441738 | I76: 2467337 | J76: 2263044 | K76: 2208094 | L76: 2292708 | M76: 2082011 | N76: 1906468 | O76: 2080949 | P76: 2085250 | Q76: 2273866 | R76: 2294570 | S76: 2388009 | T76: 2493077 | U76: 2009326 | V76: 2269458 | W76: 1974037 | X76: 1700511 | Y76: 1729247 | Z76: 1463594 | AA76: 1349412 | AB76: 919013 | AC76: 1436452 | AD76: 1126821 | AE76: 1228512 | AF76: 1246438 | AG76: 1367348 | AH76: 1316903 | AI76: 1372013 | AJ76: 1365829 | AK76: 1146239 | AL76: 1056299 | AM76: 955804 | AN76: 978150 | AO76: 853623 | AP76: 856084
A77: 2.01.02.01 | B77: Fornecedores Nacionais | C77: =CONCATENATE(A77,B77) -> 2.01.02.01Fornecedores Nacionais | D77: 529887 | E77: 492916 | F77: 375571 | G77: 472966 | H77: 504301 | I77: 521818 | J77: 415370 | K77: 490867 | L77: 410363 | M77: 393968 | N77: 373525 | O77: 435998 | P77: 421550 | Q77: 476842 | R77: 435017 | S77: 467415 | T77: 454618 | U77: 403753 | V77: 325748 | W77: 306071 | X77: 271032 | Y77: 271295 | Z77: 194509 | AA77: 186954 | AB77: 85994 | AC77: 174079 | AD77: 149658 | AE77: 154437 | AF77: 181410 | AG77: 149204 | AH77: 194036 | AI77: 166816 | AJ77: 163551 | AK77: 174799 | AL77: 158633 | AM77: 138559 | AN77: 143062 | AO77: 125937 | AP77: 100981
A78: 2.01.02.02 | B78: Fornecedores Estrangeiros | C78: =CONCATENATE(A78,B78) -> 2.01.02.02Fornecedores Estrangeiros | D78: 1992329 | E78: 1802226 | F78: 1574985 | G78: 1627243 | H78: 1937437 | I78: 1945519 | J78: 1847674 | K78: 1717227 | L78: 1882345 | M78: 1688043 | N78: 1532943 | O78: 1644951 | P78: 1663700 | Q78: 1797024 | R78: 1859553 | S78: 1920594 | T78: 2038459 | U78: 1605573 | V78: 1943710 | W78: 1667966 | X78: 1429479 | Y78: 1457952 | Z78: 1269085 | AA78: 1162458 | AB78: 833019 | AC78: 1262373 | AD78: 977163 | AE78: 1074075 | AF78: 1065028 | AG78: 1218144 | AH78: 1122867 | AI78: 1205197 | AJ78: 1202278 | AK78: 971440 | AL78: 897666 | AM78: 817245 | AN78: 835088 | AO78: 727686 | AP78: 755103
A79: 2.01.02.02.01 | B79: Fornecedores no exterior | C79: =CONCATENATE(A79,B79) -> 2.01.02.02.01Fornecedores no exterior | D79: 1992326 | E79: 1802223 | F79: 1574985 | G79: 1627243 | H79: 1937437 | I79: 1945517 | J79: 1847583 | K79: 1717227 | L79: 1882345 | M79: 1688043 | N79: 1532943 | O79: 1644951 | P79: 1663700 | Q79: 1797019 | R79: 1859238 | S79: 1920289 | T79: 2038457 | U79: 1605573 | V79: 1943710 | W79: 1667966 | X79: 1429477 | Y79: 1457952 | Z79: 1268978 | AA79: 1162458 | AB79: 833019 | AC79: 1262373 | AD79: 977163 | AE79: 1074031 | AF79: 1064973 | AG79: 1218138 | AH79: 1122861 | AI79: 1205197 | AJ79: 1202278 | AK79: 971440 | AL79: 897658 | AM79: 817245 | AN79: 835088 | AO79: 727657 | AP79: 755103
A80: 2.01.02.02.02 | B80: Partes relacionadas no exterior | C80: =CONCATENATE(A80,B80) -> 2.01.02.02.02Partes relacionadas no exterior | D80: 3 | E80: 3 | F80: 0 | G80: 0 | H80: 0 | I80: 2 | J80: 91 | K80: 0 | L80: 0 | M80: 0 | N80: 0 | O80: 0 | P80: 0 | Q80: 5 | R80: 315 | S80: 305 | T80: 2 | U80: 0 | V80: 0 | W80: 0 | X80: 2 | Y80: 0 | Z80: 107 | AA80: 0 | AB80: 0 | AC80: 0 | AD80: 0 | AE80: 44 | AF80: 55 | AG80: 6 | AH80: 6 | AI80: 0 | AJ80: 0 | AK80: 0 | AL80: 8 | AM80: 0 | AN80: 0 | AO80: 29 | AP80: 0
... A102: 2.01.05.02.05 | B102: Outras obrigações | C102: =CONCATENATE(A102,B102) -> 2.01.05.02.05Outras obrigações | D102: 503534 | E102: 427191 | F102: 427993 | G102: 406249 | H102: 476205 | I102: 556061 | J102: 540808 | K102: 512506 | L102: 461573 | M102: 387872 | N102: 421833 | O102: 489167 | P102: 499814 | Q102: 475057 | R102: 402259 | S102: 428519 | T102: 379848 | U102: 427852 | V102: 402553 | W102: 493690 | X102: 462058 | Y102: 436883 | Z102: 423213 | AA102: 360805 | AB102: 296446 | AC102: 245445 | AD102: 210561 | AE102: 248312 | AF102: 231278 | AG102: 251630 | AH102: 210381 | AI102: 185617 | AJ102: 199587 | AK102: 190927 | AL102: 161294 | AM102: 173176 | AN102: 147535 | AO102: 138895 | AP102: 135202
A103: 2.01.05.02.06 | B103: Instrumentos Financeiros Derivativos | C103: 2.01.05.02.06Instrumentos Financeiros a Pagar | D103: 0 | E103: 0 | F103: 1023 | G103: 2543 | H103: 10698 | I103: 219 | J103: 235 | K103: 8504 | L103: 722 | M103: 2247 | N103: 18662 | O103: 7067 | P103: 15783 | Q103: 14940 | R103: 16250 | S103: 10260 | T103: 14315 | U103: 14327 | V103: 0 | W103: 0 | X103: 0 | Y103: 0 | Z103: 0 | AA103: 0 | AB103: 0 | AC103: 0 | AD103: 0 | AE103: 0 | AF103: 0 | AG103: 0 | AH103: 0 | AI103: 0 | AJ103: 0 | AK103: 0 | AL103: 0 | AM103: 0 | AN103: 0 | AO103: 0 | AP103: 0
A104: 2.01.06 | B104: Provisões | C104: =CONCATENATE(A104,B104) -> 2.01.06Provisões | D104: 0 | E104: 0 | F104: 0 | G104: 0 | H104: 0 | I104: 0 | J104: 0 | K104: 0 | L104: 0 | M104: 0 | N104: 0 | O104: 0 | P104: 0 | Q104: 0 | R104: 0 | S104: 0 | T104: 0 | U104: 0 | V104: 0 | W104: 0 | X104: 0 | Y104: 0 | Z104: 0 | AA104: 0 | AB104: 0 | AC104: 0 | AD104: 0 | AE104: 0 | AF104: 0 | AG104: 0 | AH104: 0 | AI104: 0 | AJ104: 0 | AK104: 0 | AL104: 0 | AM104: 0 | AN104: 0 | AO104: 0 | AP104: 0
A105: 2.01.06.01 | B105: Provisões Fiscais Previdenciárias Trabalhistas e Cíveis | C105: =CONCATENATE(A105,B105) -> 2.01.06.01Provisões Fiscais Previdenciárias Trabalhistas e Cíveis | D105: 0 | E105: 0 | F105: 0 | G105: 0 | H105: 0 | I105: 0 | J105: 0 | K105: 0 | L105: 0 | M105: 0 | N105: 0 | O105: 0 | P105: 0 | Q105: 0 | R105: 0 | S105: 0 | T105: 0 | U105: 0 | V105: 0 | W105: 0 | X105: 0 | Y105: 0 | Z105: 0 | AA105: 0 | AB105: 0 | AC105: 0 | AD105: 0 | AE105: 0 | AF105: 0 | AG105: 0 | AH105: 0 | AI105: 0 | AJ105: 0 | AK105: 0 | AL105: 0 | AM105: 0 | AN105: 0 | AO105: 0 | AP105: 0
A106: 2.01.06.01.01 | B106: Provisões Fiscais | C106: =CONCATENATE(A106,B106) -> 2.01.06.01.01Provisões Fiscais | D106: 0 | E106: 0 | F106: 0 | G106: 0 | H106: 0 | I106: 0 | J106: 0 | K106: 0 | L106: 0 | M106: 0 | N106: 0 | O106: 0 | P106: 0 | Q106: 0 | R106: 0 | S106: 0 | T106: 0 | U106: 0 | V106: 0 | W106: 0 | X106: 0 | Y106: 0 | Z106: 0 | AA106: 0 | AB106: 0 | AC106: 0 | AD106: 0 | AE106: 0 | AF106: 0 | AG106: 0 | AH106: 0 | AI106: 0 | AJ106: 0 | AK106: 0 | AL106: 0 | AM106: 0 | AN106: 0 | AO106: 0 | AP106: 0
A107: 2.01.06.01.02 | B107: Provisões Previdenciárias e Trabalhistas | C107: =CONCATENATE(A107,B107) -> 2.01.06.01.02Provisões Previdenciárias e Trabalhistas | D107: 0 | E107: 0 | F107: 0 | G107: 0 | H107: 0 | I107: 0 | J107: 0 | K107: 0 | L107: 0 | M107: 0 | N107: 0 | O107: 0 | P107: 0 | Q107: 0 | R107: 0 | S107: 0 | T107: 0 | U107: 0 | V107: 0 | W107: 0 | X107: 0 | Y107: 0 | Z107: 0 | AA107: 0 | AB107: 0 | AC107: 0 | AD107: 0 | AE107: 0 | AF107: 0 | AG107: 0 | AH107: 0 | AI107: 0 | AJ107: 0 | AK107: 0 | AL107: 0 | AM107: 0 | AN107: 0 | AO107: 0 | AP107: 0
A108: 2.01.06.01.03 | B108: Provisões para Benefícios a Empregados | C108: =CONCATENATE(A108,B108) -> 2.01.06.01.03Provisões para Benefícios a Empregados | D108: 0 | E108: 0 | F108: 0 | G108: 0 | H108: 0 | I108: 0 | J108: 0 | K108: 0 | L108: 0 | M108: 0 | N108: 0 | O108: 0 | P108: 0 | Q108: 0 | R108: 0 | S108: 0 | T108: 0 | U108: 0 | V108: 0 | W108: 0 | X108: 0 | Y108: 0 | Z108: 0 | AA108: 0 | AB108: 0 | AC108: 0 | AD108: 0 | AE108: 0 | AF108: 0 | AG108: 0 | AH108: 0 | AI108: 0 | AJ108: 0 | AK108: 0 | AL108: 0 | AM108: 0 | AN108: 0 | AO108: 0 | AP108: 0
A109: 2.01.06.01.04 | B109: Provisões Cíveis | C109: =CONCATENATE(A109,B109) -> 2.01.06.01.04Provisões Cíveis | D109: 0 | E109: 0 | F109: 0 | G109: 0 | H109: 0 | I109: 0 | J109: 0 | K109: 0 | L109: 0 | M109: 0 | N109: 0 | O109: 0 | P109: 0 | Q109: 0 | R109: 0 | S109: 0 | T109: 0 | U109: 0 | V109: 0 | W109: 0 | X109: 0 | Y109: 0 | Z109: 0 | AA109: 0 | AB109: 0 | AC109: 0 | AD109: 0 | AE109: 0 | AF109: 0 | AG109: 0 | AH109: 0 | AI109: 0 | AJ109: 0 | AK109: 0 | AL109: 0 | AM109: 0 | AN109: 0 | AO109: 0 | AP109: 0
A110: 2.01.06.02 | B110: Outras Provisões | C110: =CONCATENATE(A110,B110) -> 2.01.06.02Outras Provisões | D110: 0 | E110: 0 | F110: 0 | G110: 0 | H110: 0 | I110: 0 | J110: 0 | K110: 0 | L110: 0 | M110: 0 | N110: 0 | O110: 0 | P110: 0 | Q110: 0 | R110: 0 | S110: 0 | T110: 0 | U110: 0 | V110: 0 | W110: 0 | X110: 0 | Y110: 0 | Z110: 0 | AA110: 0 | AB110: 0 | AC110: 0 | AD110: 0 | AE110: 0 | AF110: 0 | AG110: 0 | AH110: 0 | AI110: 0 | AJ110: 0 | AK110: 0 | AL110: 0 | AM110: 0 | AN110: 0 | AO110: 0 | AP110: 0
A111: 2.01.06.02.01 | B111: Provisões para Garantias | C111: =CONCATENATE(A111,B111) -> 2.01.06.02.01Provisões para Garantias | D111: 0 | E111: 0 | F111: 0 | G111: 0 | H111: 0 | I111: 0 | J111: 0 | K111: 0 | L111: 0 | M111: 0 | N111: 0 | O111: 0 | P111: 0 | Q111: 0 | R111: 0 | S111: 0 | T111: 0 | U111: 0 | V111: 0 | W111: 0 | X111: 0 | Y111: 0 | Z111: 0 | AA111: 0 | AB111: 0 | AC111: 0 | AD111: 0 | AE111: 0 | AF111: 0 | AG111: 0 | AH111: 0 | AI111: 0 | AJ111: 0 | AK111: 0 | AL111: 0 | AM111: 0 | AN111: 0 | AO111: 0 | AP111: 0
A112: 2.01.06.02.02 | B112: Provisões para Reestruturação | C112: =CONCATENATE(A112,B112) -> 2.01.06.02.02Provisões para Reestruturação | D112: 0 | E112: 0 | F112: 0 | G112: 0 | H112: 0 | I112: 0 | J112: 0 | K112: 0 | L112: 0 | M112: 0 | N112: 0 | O112: 0 | P112: 0 | Q112: 0 | R112: 0 | S112: 0 | T112: 0 | U112: 0 | V112: 0 | W112: 0 | X112: 0 | Y112: 0 | Z112: 0 | AA112: 0 | AB112: 0 | AC112: 0 | AD112: 0 | AE112: 0 | AF112: 0 | AG112: 0 | AH112: 0 | AI112: 0 | AJ112: 0 | AK112: 0 | AL112: 0 | AM112: 0 | AN112: 0 | AO112: 0 | AP112: 0
A113: 2.01.06.02.03 | B113: Provisões para Passivos Ambientais e de Desativação | C113: =CONCATENATE(A113,B113) -> 2.01.06.02.03Provisões para Passivos Ambientais e de Desativação | D113: 0 | E113: 0 | F113: 0 | G113: 0 | H113: 0 | I113: 0 | J113: 0 | K113: 0 | L113: 0 | M113: 0 | N113: 0 | O113: 0 | P113: 0 | Q113: 0 | R113: 0 | S113: 0 | T113: 0 | U113: 0 | V113: 0 | W113: 0 | X113: 0 | Y113: 0 | Z113: 0 | AA113: 0 | AB113: 0 | AC113: 0 | AD113: 0 | AE113: 0 | AF113: 0 | AG113: 0 | AH113: 0 | AI113: 0 | AJ113: 0 | AK113: 0 | AL113: 0 | AM113: 0 | AN113: 0 | AO113: 0 | AP113: 0
A114: 2.01.07 | B114: Passivos sobre Ativos Não-Correntes a Venda e Descontinuados | C114: =CONCATENATE(A114,B114) -> 2.01.07Passivos sobre Ativos Não-Correntes a Venda e Descontinuados | D114: 0 | E114: 0 | F114: 0 | G114: 0 | H114: 0 | I114: 0 | J114: 0 | K114: 0 | L114: 0 | M114: 0 | N114: 0 | O114: 0 | P114: 0 | Q114: 0 | R114: 0 | S114: 0 | T114: 0 | U114: 0 | V114: 0 | W114: 0 | X114: 0 | Y114: 0 | Z114: 0 | AA114: 0 | AB114: 0 | AC114: 0 | AD114: 0 | AE114: 0 | AF114: 0 | AG114: 0 | AH114: 0 | AI114: 0 | AJ114: 0 | AK114: 0 | AL114: 0 | AM114: 0 | AN114: 0 | AO114: 0 | AP114: 0
A115: 2.01.07.01 | B115: Passivos sobre Ativos Não-Correntes a Venda | C115: =CONCATENATE(A115,B115) -> 2.01.07.01Passivos sobre Ativos Não-Correntes a Venda | D115: 0 | E115: 0 | F115: 0 | G115: 0 | H115: 0 | I115: 0 | J115: 0 | K115: 0 | L115: 0 | M115: 0 | N115: 0 | O115: 0 | P115: 0 | Q115: 0 | R115: 0 | S115: 0 | T115: 0 | U115: 0 | V115: 0 | W115: 0 | X115: 0 | Y115: 0 | Z115: 0 | AA115: 0 | AB115: 0 | AC115: 0 | AD115: 0 | AE115: 0 | AF115: 0 | AG115: 0 | AH115: 0 | AI115: 0 | AJ115: 0 | AK115: 0 | AL115: 0 | AM115: 0 | AN115: 0 | AO115: 0 | AP115: 0
... A133: 2.02.02.02.04 | B133: Passivo a descoberto de controladas em conjunto | C133: =CONCATENATE(A133,B133) -> 2.02.02.02.04Passivo a descoberto de controladas em conjunto | D133: 0 | E133: 0 | F133: 0 | G133: 0 | H133: 0 | I133: 0 | J133: 0 | K133: 0 | L133: 0 | M133: 0 | N133: 0 | O133: 0 | P133: 0 | Q133: 0 | R133: 0 | S133: 0 | T133: 0 | U133: 0 | V133: 0 | W133: 0 | X133: 0 | Y133: 0 | Z133: 0 | AA133: 0 | AB133: 0 | AC133: 0 | AD133: 0 | AE133: 0 | AF133: 0 | AG133: 0 | AH133: 0 | AI133: 0 | AJ133: 0 | AK133: 0 | AL133: 0 | AM133: 0 | AN133: 0 | AO133: 0 | AP133: 0
A134: 2.02.02.02.05 | B134: Instrumentos Financeiros Derivativos | C134: 2.02.02.02.05Instrumento financeiro derivativo | D134: 0 | E134: 0 | F134: 0 | G134: 0 | H134: 0 | I134: 0 | J134: 0 | K134: 103 | L134: 206 | M134: 450 | N134: 489 | O134: 0 | P134: 0 | Q134: 0 | R134: 1591 | S134: 0 | T134: 5464 | U134: 1378 | V134: 0 | W134: 0 | X134: 0 | Y134: 0 | Z134: 0 | AA134: 0 | AB134: 0 | AC134: 0 | AD134: 0 | AE134: 0 | AF134: 0 | AG134: 0 | AH134: 0 | AI134: 0 | AJ134: 0 | AK134: 0 | AL134: 0 | AM134: 0 | AN134: 0 | AO134: 0 | AP134: 0
A135: 2.02.03 | B135: Tributos Diferidos | C135: =CONCATENATE(A135,B135) -> 2.02.03Tributos Diferidos | D135: 34595 | E135: 35498 | F135: 40968 | G135: 60833 | H135: 77302 | I135: 69199 | J135: 75899 | K135: 57485 | L135: 69025 | M135: 37286 | N135: 47568 | O135: 52221 | P135: 52507 | Q135: 19869 | R135: 42904 | S135: 82710 | T135: 109058 | U135: 88254 | V135: 120725 | W135: 166283 | X135: 160053 | Y135: 192230 | Z135: 175180 | AA135: 221660 | AB135: 203951 | AC135: 198721 | AD135: 174548 | AE135: 182911 | AF135: 165427 | AG135: 178767 | AH135: 199862 | AI135: 221847 | AJ135: 201689 | AK135: 163462 | AL135: 169030 | AM135: 176300 | AN135: 181786 | AO135: 164849 | AP135: 162883
A136: 2.02.03.01 | B136: Imposto de Renda e Contribuição Social Diferidos | C136: =CONCATENATE(A136,B136) -> 2.02.03.01Imposto de Renda e Contribuição Social Diferidos | D136: 34595 | E136: 35498 | F136: 40968 | G136: 60833 | H136: 77302 | I136: 69199 | J136: 75899 | K136: 57485 | L136: 69025 | M136: 37286 | N136: 47568 | O136: 52221 | P136: 52507 | Q136: 19869 | R136: 42904 | S136: 82710 | T136: 109058 | U136: 88254 | V136: 120725 | W136: 166283 | X136: 160053 | Y136: 192230 | Z136: 175180 | AA136: 221660 | AB136: 203951 | AC136: 198721 | AD136: 174548 | AE136: 182911 | AF136: 165427 | AG136: 178767 | AH136: 199862 | AI136: 221847 | AJ136: 201689 | AK136: 163462 | AL136: 169030 | AM136: 176300 | AN136: 181786 | AO136: 164849 | AP136: 162883
A137: 2.02.04 | B137: Provisões | C137: =CONCATENATE(A137,B137) -> 2.02.04Provisões | D137: 490595 | E137: 477026 | F137: 481791 | G137: 524919 | H137: 541437 | I137: 512474 | J137: 539953 | K137: 526062 | L137: 545462 | M137: 507107 | N137: 503187 | O137: 498874 | P137: 497350 | Q137: 514416 | R137: 540833 | S137: 594820 | T137: 612601 | U137: 604983 | V137: 707688 | W137: 777573 | X137: 729460 | Y137: 820999 | Z137: 781352 | AA137: 820057 | AB137: 762387 | AC137: 723865 | AD137: 599685 | AE137: 564615 | AF137: 543948 | AG137: 565369 | AH137: 576203 | AI137: 585951 | AJ137: 571701 | AK137: 536359 | AL137: 521900 | AM137: 494151 | AN137: 493815 | AO137: 449855 | AP137: 453807
A138: 2.02.04.01 | B138: Provisões Fiscais Previdenciárias Trabalhistas e Cíveis | C138: =CONCATENATE(A138,B138) -> 2.02.04.01Provisões Fiscais Previdenciárias Trabalhistas e Cíveis | D138: 65991 | E138: 45656 | F138: 42040 | G138: 61031 | H138: 62266 | I138: 61878 | J138: 62577 | K138: 65433 | L138: 85485 | M138: 83760 | N138: 78965 | O138: 78045 | P138: 79259 | Q138: 77939 | R138: 78574 | S138: 79580 | T138: 77558 | U138: 92759 | V138: 90893 | W138: 100176 | X138: 86108 | Y138: 90726 | Z138: 79423 | AA138: 104246 | AB138: 84136 | AC138: 82744 | AD138: 83753 | AE138: 86542 | AF138: 84568 | AG138: 101410 | AH138: 105150 | AI138: 111900 | AJ138: 104829 | AK138: 106686 | AL138: 100663 | AM138: 89573 | AN138: 80842 | AO138: 74973 | AP138: 70650
A139: 2.02.04.01.01 | B139: Provisões Fiscais | C139: =CONCATENATE(A139,B139) -> 2.02.04.01.01Provisões Fiscais | D139: 50481 | E139: 30512 | F139: 27699 | G139: 47452 | H139: 50326 | I139: 49490 | J139: 48633 | K139: 50516 | L139: 69051 | M139: 67204 | N139: 64760 | O139: 63171 | P139: 61069 | Q139: 59091 | R139: 59213 | S139: 57485 | T139: 55920 | U139: 58610 | V139: 56195 | W139: 55332 | X139: 54715 | Y139: 56470 | Z139: 53452 | AA139: 75998 | AB139: 55896 | AC139: 54570 | AD139: 50594 | AE139: 48448 | AF139: 46873 | AG139: 52892 | AH139: 51393 | AI139: 49515 | AJ139: 47144 | AK139: 44613 | AL139: 39362 | AM139: 38340 | AN139: 38815 | AO139: 36906 | AP139: 36380
A140: 2.02.04.01.02 | B140: Provisões Previdenciárias e Trabalhistas | C140: =CONCATENATE(A140,B140) -> 2.02.04.01.02Provisões Previdenciárias e Trabalhistas | D140: 15299 | E140: 14942 | F140: 14147 | G140: 13192 | H140: 11369 | I140: 11836 | J140: 13369 | K140: 14355 | L140: 15887 | M140: 16020 | N140: 13682 | O140: 14341 | P140: 17673 | Q140: 18333 | R140: 18804 | S140: 19649 | T140: 19389 | U140: 24027 | V140: 23727 | W140: 21107 | X140: 18874 | Y140: 20804 | Z140: 21217 | AA140: 23557 | AB140: 23593 | AC140: 23537 | AD140: 28628 | AE140: 33930 | AF140: 33699 | AG140: 36308 | AH140: 39767 | AI140: 46642 | AJ140: 41984 | AK140: 45806 | AL140: 44983 | AM140: 37308 | AN140: 30225 | AO140: 26267 | AP140: 23308
A141: 2.02.04.01.03 | B141: Provisões para Benefícios a Empregados | C141: =CONCATENATE(A141,B141) -> 2.02.04.01.03Provisões para Benefícios a Empregados | D141: 0 | E141: 0 | F141: 0 | G141: 0 | H141: 0 | I141: 0 | J141: 0 | K141: 0 | L141: 0 | M141: 0 | N141: 0 | O141: 0 | P141: 0 | Q141: 0 | R141: 0 | S141: 0 | T141: 0 | U141: 0 | V141: 0 | W141: 0 | X141: 0 | Y141: 0 | Z141: 0 | AA141: 0 | AB141: 0 | AC141: 0 | AD141: 0 | AE141: 0 | AF141: 0 | AG141: 0 | AH141: 0 | AI141: 0 | AJ141: 0 | AK141: 0 | AL141: 0 | AM141: 0 | AN141: 0 | AO141: 0 | AP141: 0
A142: 2.02.04.01.04 | B142: Provisões Cíveis | C142: =CONCATENATE(A142,B142) -> 2.02.04.01.04Provisões Cíveis | D142: 211 | E142: 202 | F142: 194 | G142: 387 | H142: 571 | I142: 552 | J142: 575 | K142: 562 | L142: 547 | M142: 536 | N142: 523 | O142: 533 | P142: 517 | Q142: 515 | R142: 557 | S142: 2446 | T142: 2249 | U142: 10122 | V142: 10971 | W142: 23737 | X142: 12519 | Y142: 13452 | Z142: 4754 | AA142: 4691 | AB142: 4647 | AC142: 4637 | AD142: 4531 | AE142: 4164 | AF142: 3996 | AG142: 12210 | AH142: 13990 | AI142: 15743 | AJ142: 15701 | AK142: 16267 | AL142: 16318 | AM142: 13925 | AN142: 11802 | AO142: 11800 | AP142: 10962
A143: 2.02.04.02 | B143: Outras Provisões | C143: =CONCATENATE(A143,B143) -> 2.02.04.02Outras Provisões | D143: 424604 | E143: 431370 | F143: 439751 | G143: 463888 | H143: 479171 | I143: 450596 | J143: 477376 | K143: 460629 | L143: 459977 | M143: 423347 | N143: 424222 | O143: 420829 | P143: 418091 | Q143: 436477 | R143: 462259 | S143: 515240 | T143: 535043 | U143: 512224 | V143: 616795 | W143: 677397 | X143: 643352 | Y143: 730273 | Z143: 701929 | AA143: 715811 | AB143: 678251 | AC143: 641121 | AD143: 515932 | AE143: 478073 | AF143: 459380 | AG143: 463959 | AH143: 471053 | AI143: 474051 | AJ143: 466872 | AK143: 429673 | AL143: 421237 | AM143: 404578 | AN143: 412973 | AO143: 374882 | AP143: 383157
A144: 2.02.04.02.01 | B144: Provisões para Garantias | C144: =CONCATENATE(A144,B144) -> 2.02.04.02.01Provisões para Garantias | D144: 0 | E144: 0 | F144: 0 | G144: 0 | H144: 0 | I144: 0 | J144: 0 | K144: 0 | L144: 0 | M144: 0 | N144: 0 | O144: 0 | P144: 0 | Q144: 0 | R144: 0 | S144: 0 | T144: 0 | U144: 0 | V144: 0 | W144: 0 | X144: 0 | Y144: 0 | Z144: 0 | AA144: 0 | AB144: 0 | AC144: 0 | AD144: 0 | AE144: 0 | AF144: 0 | AG144: 0 | AH144: 0 | AI144: 0 | AJ144: 0 | AK144: 0 | AL144: 0 | AM144: 0 | AN144: 0 | AO144: 0 | AP144: 0
A145: 2.02.04.02.02 | B145: Provisões para Reestruturação | C145: =CONCATENATE(A145,B145) -> 2.02.04.02.02Provisões para Reestruturação | D145: 0 | E145: 0 | F145: 0 | G145: 0 | H145: 0 | I145: 0 | J145: 0 | K145: 0 | L145: 0 | M145: 0 | N145: 0 | O145: 0 | P145: 0 | Q145: 0 | R145: 0 | S145: 0 | T145: 0 | U145: 0 | V145: 0 | W145: 0 | X145: 0 | Y145: 0 | Z145: 0 | AA145: 0 | AB145: 0 | AC145: 0 | AD145: 0 | AE145: 0 | AF145: 0 | AG145: 0 | AH145: 0 | AI145: 0 | AJ145: 0 | AK145: 0 | AL145: 0 | AM145: 0 | AN145: 0 | AO145: 0 | AP145: 0
A146: 2.02.04.02.03 | B146: Provisões para Passivos Ambientais e de Desativação | C146: =CONCATENATE(A146,B146) -> 2.02.04.02.03Provisões para Passivos Ambientais e de Desativação | D146: 0 | E146: 0 | F146: 0 | G146: 0 | H146: 0 | I146: 0 | J146: 0 | K146: 0 | L146: 0 | M146: 0 | N146: 0 | O146: 0 | P146: 0 | Q146: 0 | R146: 0 | S146: 0 | T146: 0 | U146: 0 | V146: 0 | W146: 0 | X146: 0 | Y146: 0 | Z146: 0 | AA146: 0 | AB146: 0 | AC146: 0 | AD146: 0 | AE146: 0 | AF146: 0 | AG146: 0 | AH146: 0 | AI146: 0 | AJ146: 0 | AK146: 0 | AL146: 0 | AM146: 0 | AN146: 0 | AO146: 0 | AP146: 0
... A186: 2.03.09 | B186: Participação dos Acionistas Não Controladores | C186: =CONCATENATE(A186,B186) -> 2.03.09Participação dos Acionistas Não Controladores | D186: 589269 | E186: 472080 | F186: 530026 | G186: 470119 | H186: 443826 | I186: 471407 | J186: 513077 | K186: 454207 | L186: 427762 | M186: 353851 | N186: 391403 | O186: 371386 | P186: 359318 | Q186: 351377 | R186: 373000 | S186: 321229 | T186: 310936 | U186: 285634 | V186: 356375 | W186: 340455 | X186: 293940 | Y186: 310990 | Z186: 340476 | AA186: 316749 | AB186: 282271 | AC186: 262518 | AD186: 268498 | AE186: 246757 | AF186: 215233 | AG186: 197020 | AH186: 276577 | AI186: 242045 | AJ186: 217404 | AK186: 176710 | AL186: 242652 | AM186: 207930 | AN186: 216744 | AO186: 181714 | AP186: 233092
G188: =G3-G69 -> 0 | H188: =H3-H69 -> 0 | I188: =I3-I69 -> 0 | J188: =J3-J69 -> 0 | K188: =K3-K69 -> 0 | L188: =L3-L69 -> 0 | M188: =M3-M69 -> 0 | N188: 0 | O188: 0 | P188: 0 | Q188: 0 | R188: 0 | S188: 0 | T188: 0 | U188: 0 | V188: 0 | W188: 0 | X188: 0 | Y188: 0 | Z188: 0 | AA188: 0 | AB188: 0 | AC188: 0 | AD188: 0 | AE188: 0 | AF188: 0 | AG188: 0 | AH188: 0 | AI188: 0 | AJ188: 0 | AK188: 0 | AL188: 0 | AM188: 0 | AN188: 0 | AO188: 0 | AP188: 0
G189: =SUM(G4,G27)-G3 -> 0 | H189: =SUM(H4,H27)-H3 -> 0 | I189: =SUM(I4,I27)-I3 -> 0 | J189: =SUM(J4,J27)-J3 -> 0 | K189: =SUM(K4,K27)-K3 -> 0 | L189: =SUM(L4,L27)-L3 -> 0 | M189: =SUM(M4,M27)-M3 -> 0 | N189: 0 | O189: 0 | P189: 0 | Q189: 0 | R189: 0 | S189: 0 | T189: 0 | U189: 0 | V189: 0 | W189: 0 | X189: 0 | Y189: 0 | Z189: 0 | AA189: 0 | AB189: 0 | AC189: 0 | AD189: 0 | AE189: 0 | AF189: 0 | AG189: 0 | AH189: 0 | AI189: 0 | AJ189: 0 | AK189: 0 | AL189: 0 | AM189: 0 | AN189: 0 | AO189: 0 | AP189: 0
G190: =SUM(G5,G6,G12,G15,G16,G17,G19,G20)-G4 -> 0 | H190: =SUM(H5,H6,H12,H15,H16,H17,H19,H20)-H4 -> 0 | I190: =SUM(I5,I6,I12,I15,I16,I17,I19,I20)-I4 -> 0 | J190: =SUM(J5,J6,J12,J15,J16,J17,J19,J20)-J4 -> 0 | K190: =SUM(K5,K6,K12,K15,K16,K17,K19,K20)-K4 -> 0 | L190: =SUM(L5,L6,L12,L15,L16,L17,L19,L20)-L4 -> 0 | M190: =SUM(M5,M6,M12,M15,M16,M17,M19,M20)-M4 -> 0 | N190: 0 | O190: 0 | P190: 0 | Q190: 0 | R190: 0 | S190: 0 | T190: 0 | U190: 0 | V190: 0 | W190: 0 | X190: 0 | Y190: 0 | Z190: 0 | AA190: 0 | AB190: 0 | AC190: 0 | AD190: 0 | AE190: 0 | AF190: 0 | AG190: 0 | AH190: 0 | AI190: 0 | AJ190: 0 | AK190: 0 | AL190: 0 | AM190: 0 | AN190: 0 | AO190: 0 | AP190: 0
G191: =SUM(G13:G14)-G12 -> 0 | H191: =SUM(H13:H14)-H12 -> 0 | I191: =SUM(I13:I14)-I12 -> 0 | J191: =SUM(J13:J14)-J12 -> 0 | K191: =SUM(K13:K14)-K12 -> 0 | L191: =SUM(L13:L14)-L12 -> 0 | M191: =SUM(M13:M14)-M12 -> 0 | N191: 0 | O191: 0 | P191: 0 | Q191: 0 | R191: 0 | S191: 0 | T191: 0 | U191: 0 | V191: 0 | W191: 0 | X191: 0 | Y191: 0 | Z191: 0 | AA191: 0 | AB191: 0 | AC191: 0 | AD191: 0 | AE191: 0 | AF191: 0 | AG191: 0 | AH191: 0 | AI191: 0 | AJ191: 0 | AK191: 0 | AL191: 0 | AM191: 0 | AN191: 0 | AO191: 0 | AP191: 0
G192: =SUM(G18)-G17 -> 0 | H192: =SUM(H18)-H17 -> 0 | I192: =SUM(I18)-I17 -> 0 | J192: =SUM(J18)-J17 -> 0 | K192: =SUM(K18)-K17 -> 0 | L192: =SUM(L18)-L17 -> 0 | M192: =SUM(M18)-M17 -> 0 | N192: 0 | O192: 0 | P192: 0 | Q192: 0 | R192: 0 | S192: 0 | T192: 0 | U192: 0 | V192: 0 | W192: 0 | X192: 0 | Y192: 0 | Z192: 0 | AA192: 0 | AB192: 0 | AC192: 0 | AD192: 0 | AE192: 0 | AF192: 0 | AG192: 0 | AH192: 0 | AI192: 0 | AJ192: 0 | AK192: 0 | AL192: 0 | AM192: 0 | AN192: 0 | AO192: 0 | AP192: 0
G193: =SUM(G21:G23)-G20 -> 0 | H193: =SUM(H21:H23)-H20 -> 0 | I193: =SUM(I21:I23)-I20 -> 0 | J193: =SUM(J21:J23)-J20 -> 0 | K193: =SUM(K21:K23)-K20 -> 0 | L193: =SUM(L21:L23)-L20 -> 0 | M193: =SUM(M21:M23)-M20 -> 0 | N193: 0 | O193: 0 | P193: 0 | Q193: 0 | R193: 0 | S193: 0 | T193: 0 | U193: 0 | V193: 0 | W193: 0 | X193: 0 | Y193: 0 | Z193: 0 | AA193: 0 | AB193: 0 | AC193: 0 | AD193: 0 | AE193: 0 | AF193: 0 | AG193: 0 | AH193: 0 | AI193: 0 | AJ193: 0 | AK193: 0 | AL193: 0 | AM193: 0 | AN193: 0 | AO193: 0 | AP193: 0
G194: =SUM(G24:G26)-G23 -> 0 | H194: =SUM(H24:H26)-H23 -> 0 | I194: =SUM(I24:I26)-I23 -> 0 | J194: =SUM(J24:J26)-J23 -> 0 | K194: =SUM(K24:K26)-K23 -> 0 | L194: =SUM(L24:L26)-L23 -> 0 | M194: =SUM(M24:M26)-M23 -> 0 | N194: 0 | O194: 0 | P194: 0 | Q194: 0 | R194: 0 | S194: 0 | T194: 0 | U194: 0 | V194: 0 | W194: 0 | X194: 0 | Y194: 0 | Z194: 0 | AA194: 0 | AB194: 0 | AC194: 0 | AD194: 0 | AE194: 0 | AF194: 0 | AG194: 0 | AH194: 0 | AI194: 0 | AJ194: 0 | AK194: 0 | AL194: 0 | AM194: 0 | AN194: 0 | AO194: 0 | AP194: 0
G195: =SUM(G28,G52,G58,G62)-G27 -> 0 | H195: =SUM(H28,H52,H58,H62)-H27 -> 0 | I195: =SUM(I28,I52,I58,I62)-I27 -> 0 | J195: =SUM(J28,J52,J58,J62)-J27 -> 0 | K195: =SUM(K28,K52,K58,K62)-K27 -> 0 | L195: =SUM(L28,L52,L58,L62)-L27 -> 0 | M195: =SUM(M28,M52,M58,M62)-M27 -> 0 | N195: 0 | O195: 0 | P195: 0 | Q195: 0 | R195: 0 | S195: 0 | T195: 0 | U195: 0 | V195: 0 | W195: 0 | X195: 0 | Y195: 0 | Z195: 0 | AA195: 0 | AB195: 0 | AC195: 0 | AD195: 0 | AE195: 0 | AF195: 0 | AG195: 0 | AH195: 0 | AI195: 0 | AJ195: 0 | AK195: 0 | AL195: 0 | AM195: 0 | AN195: 0 | AO195: 0 | AP195: 0
G196: =SUM(G29,G31,G32,G33,G36,G37,G38,G40,G41,G45)-G28 -> 0 | H196: =SUM(H29,H31,H32,H33,H36,H37,H38,H40,H41,H45)-H28 -> 0 | I196: =SUM(I29,I31,I32,I33,I36,I37,I38,I40,I41,I45)-I28 -> 0 | J196: =SUM(J29,J31,J32,J33,J36,J37,J38,J40,J41,J45)-J28 -> 0 | K196: =SUM(K29,K31,K32,K33,K36,K37,K38,K40,K41,K45)-K28 -> 0 | L196: =SUM(L29,L31,L32,L33,L36,L37,L38,L40,L41,L45)-L28 -> 0 | M196: =SUM(M29,M31,M32,M33,M36,M37,M38,M40,M41,M45)-M28 -> 0 | N196: 0 | O196: 0 | P196: 0 | Q196: 0 | R196: 0 | S196: 0 | T196: 0 | U196: 0 | V196: 0 | W196: 0 | X196: 0 | Y196: 0 | Z196: 0 | AA196: 0 | AB196: 0 | AC196: 0 | AD196: 0 | AE196: 0 | AF196: 0 | AG196: 0 | AH196: 0 | AI196: 0 | AJ196: 0 | AK196: 0 | AL196: 0 | AM196: 0 | AN196: 0 | AO196: 0 | AP196: 0
G197: =SUM(G39)-G38 -> 0 | H197: =SUM(H39)-H38 -> 0 | I197: =SUM(I39)-I38 -> 0 | J197: =SUM(J39)-J38 -> 0 | K197: =SUM(K39)-K38 -> 0 | L197: =SUM(L39)-L38 -> 0 | M197: =SUM(M39)-M38 -> 0 | N197: 0 | O197: 0 | P197: 0 | Q197: 0 | R197: 0 | S197: 0 | T197: 0 | U197: 0 | V197: 0 | W197: 0 | X197: 0 | Y197: 0 | Z197: 0 | AA197: 0 | AB197: 0 | AC197: 0 | AD197: 0 | AE197: 0 | AF197: 0 | AG197: 0 | AH197: 0 | AI197: 0 | AJ197: 0 | AK197: 0 | AL197: 0 | AM197: 0 | AN197: 0 | AO197: 0 | AP197: 0
G198: =SUM(G42:G44)-G41 -> 0 | H198: =SUM(H42:H44)-H41 -> 0 | I198: =SUM(I42:I44)-I41 -> 0 | J198: =SUM(J42:J44)-J41 -> 0 | K198: =SUM(K42:K44)-K41 -> 0 | L198: =SUM(L42:L44)-L41 -> 0 | M198: =SUM(M42:M44)-M41 -> 0 | N198: 0 | O198: 0 | P198: 0 | Q198: 0 | R198: 0 | S198: 0 | T198: 0 | U198: 0 | V198: 0 | W198: 0 | X198: 0 | Y198: 0 | Z198: 0 | AA198: 0 | AB198: 0 | AC198: 0 | AD198: 0 | AE198: 0 | AF198: 0 | AG198: 0 | AH198: 0 | AI198: 0 | AJ198: 0 | AK198: 0 | AL198: 0 | AM198: 0 | AN198: 0 | AO198: 0 | AP198: 0
G199: =SUM(G46:G51)-G45 -> 0 | H199: =SUM(H46:H51)-H45 -> 0 | I199: =SUM(I46:I51)-I45 -> 0 | J199: =SUM(J46:J51)-J45 -> 0 | K199: =SUM(K46:K51)-K45 -> 0 | L199: =SUM(L46:L51)-L45 -> 0 | M199: =SUM(M46:M51)-M45 -> 0 | N199: 0 | O199: 0 | P199: 0 | Q199: 0 | R199: 0 | S199: 0 | T199: 0 | U199: 0 | V199: 0 | W199: 0 | X199: 0 | Y199: 0 | Z199: 0 | AA199: 0 | AB199: 0 | AC199: 0 | AD199: 0 | AE199: 0 | AF199: 0 | AG199: 0 | AH199: 0 | AI199: 0 | AJ199: 0 | AK199: 0 | AL199: 0 | AM199: 0 | AN199: 0 | AO199: 0 | AP199: 0
G200: =SUM(G53,G57)-G52 -> 0 | H200: =SUM(H53,H57)-H52 -> 0 | I200: =SUM(I53,I57)-I52 -> 0 | J200: =SUM(J53,J57)-J52 -> 0 | K200: =SUM(K53,K57)-K52 -> 0 | L200: =SUM(L53,L57)-L52 -> 0 | M200: =SUM(M53,M57)-M52 -> 0 | N200: 0 | O200: 0 | P200: 0 | Q200: 0 | R200: 0 | S200: 0 | T200: 0 | U200: 0 | V200: 0 | W200: 0 | X200: 0 | Y200: 0 | Z200: 0 | AA200: 0 | AB200: 0 | AC200: 0 | AD200: 0 | AE200: 0 | AF200: 0 | AG200: 0 | AH200: 0 | AI200: 0 | AJ200: 0 | AK200: 0 | AL200: 0 | AM200: 0 | AN200: 0 | AO200: 0 | AP200: 0
G201: =SUM(G54:G56)-G53 -> 0 | H201: =SUM(H54:H56)-H53 -> 0 | I201: =SUM(I54:I56)-I53 -> 0 | J201: =SUM(J54:J56)-J53 -> 0 | K201: =SUM(K54:K56)-K53 -> 0 | L201: =SUM(L54:L56)-L53 -> 0 | M201: =SUM(M54:M56)-M53 -> 0 | N201: 0 | O201: 0 | P201: 0 | Q201: 0 | R201: 0 | S201: 0 | T201: 0 | U201: 0 | V201: 0 | W201: 0 | X201: 0 | Y201: 0 | Z201: 0 | AA201: 0 | AB201: 0 | AC201: 0 | AD201: 0 | AE201: 0 | AF201: 0 | AG201: 0 | AH201: 0 | AI201: 0 | AJ201: 0 | AK201: 0 | AL201: 0 | AM201: 0 | AN201: 0 | AO201: 0 | AP201: 0
G202: =SUM(G59:G61)-G58 -> 0 | H202: =SUM(H59:H61)-H58 -> 0 | I202: =SUM(I59:I61)-I58 -> 0 | J202: =SUM(J59:J61)-J58 -> 0 | K202: =SUM(K59:K61)-K58 -> 0 | L202: =SUM(L59:L61)-L58 -> 0 | M202: =SUM(M59:M61)-M58 -> 0 | N202: 0 | O202: 0 | P202: 0 | Q202: 0 | R202: 0 | S202: 0 | T202: 0 | U202: 0 | V202: 0 | W202: 0 | X202: 0 | Y202: 0 | Z202: 0 | AA202: 0 | AB202: 0 | AC202: 0 | AD202: 0 | AE202: 0 | AF202: 0 | AG202: 0 | AH202: 0 | AI202: 0 | AJ202: 0 | AK202: 0 | AL202: 0 | AM202: 0 | AN202: 0 | AO202: 0 | AP202: 0
G203: =SUM(G63,G68)-G62 -> 0 | H203: =SUM(H63,H68)-H62 -> 0 | I203: =SUM(I63,I68)-I62 -> 0 | J203: =SUM(J63,J68)-J62 -> 0 | K203: =SUM(K63,K68)-K62 -> 0 | L203: =SUM(L63,L68)-L62 -> 0 | M203: =SUM(M63,M68)-M62 -> 0 | N203: 0 | O203: 0 | P203: 0 | Q203: 0 | R203: 0 | S203: 0 | T203: 0 | U203: 0 | V203: 0 | W203: 0 | X203: 0 | Y203: 0 | Z203: 0 | AA203: 0 | AB203: 0 | AC203: 0 | AD203: 0 | AE203: 0 | AF203: 0 | AG203: 0 | AH203: 0 | AI203: 0 | AJ203: 0 | AK203: 0 | AL203: 0 | AM203: 0 | AN203: 0 | AO203: 0 | AP203: 0
G204: =SUM(G64:G67)-G63 -> 0 | H204: =SUM(H64:H67)-H63 -> 0 | I204: =SUM(I64:I67)-I63 -> 0 | J204: =SUM(J64:J67)-J63 -> 0 | K204: =SUM(K64:K67)-K63 -> 0 | L204: =SUM(L64:L67)-L63 -> 0 | M204: =SUM(M64:M67)-M63 -> 0 | N204: 0 | O204: 0 | P204: 0 | Q204: 0 | R204: 0 | S204: 0 | T204: 0 | U204: 0 | V204: 0 | W204: 0 | X204: 0 | Y204: 0 | Z204: 0 | AA204: 0 | AB204: 0 | AC204: 0 | AD204: 0 | AE204: 0 | AF204: 0 | AG204: 0 | AH204: 0 | AI204: 0 | AJ204: 0 | AK204: 0 | AL204: 0 | AM204: 0 | AN204: 0 | AO204: 0 | AP204: 0
G205: =SUM(G71,G76,G81,G86,G92,G104,G114)-G70 -> 0 | H205: =SUM(H71,H76,H81,H86,H92,H104,H114)-H70 -> 0 | I205: =SUM(I71,I76,I81,I86,I92,I104,I114)-I70 -> 0 | J205: =SUM(J71,J76,J81,J86,J92,J104,J114)-J70 -> 0 | K205: =SUM(K71,K76,K81,K86,K92,K104,K114)-K70 -> 0 | L205: =SUM(L71,L76,L81,L86,L92,L104,L114)-L70 -> 0 | M205: =SUM(M71,M76,M81,M86,M92,M104,M114)-M70 -> 0 | N205: 0 | O205: 0 | P205: 0 | Q205: 0 | R205: 0 | S205: 0 | T205: 0 | U205: 0 | V205: 0 | W205: 0 | X205: 0 | Y205: 0 | Z205: 0 | AA205: 0 | AB205: 0 | AC205: 0 | AD205: 0 | AE205: 0 | AF205: 0 | AG205: 0 | AH205: 0 | AI205: 0 | AJ205: 0 | AK205: 0 | AL205: 0 | AM205: 0 | AN205: 0 | AO205: 0 | AP205: 0
G206: =SUM(G72:G73)-G71 -> 0 | H206: =SUM(H72:H73)-H71 -> 0 | I206: =SUM(I72:I73)-I71 -> 0 | J206: =SUM(J72:J73)-J71 -> 0 | K206: =SUM(K72:K73)-K71 -> 0 | L206: =SUM(L72:L73)-L71 -> 0 | M206: =SUM(M72:M73)-M71 -> 0 | N206: 0 | O206: 0 | P206: 0 | Q206: 0 | R206: 0 | S206: 0 | T206: 0 | U206: 0 | V206: 0 | W206: 0 | X206: 0 | Y206: 0 | Z206: 0 | AA206: 0 | AB206: 0 | AC206: 0 | AD206: 0 | AE206: 0 | AF206: 0 | AG206: 0 | AH206: 0 | AI206: 0 | AJ206: 0 | AK206: 0 | AL206: 0 | AM206: 0 | AN206: 0 | AO206: 0 | AP206: 0
G207: =SUM(G74:G75)-G73 -> 0 | H207: =SUM(H74:H75)-H73 -> 0 | I207: =SUM(I74:I75)-I73 -> 0 | J207: =SUM(J74:J75)-J73 -> 0 | K207: =SUM(K74:K75)-K73 -> 0 | L207: =SUM(L74:L75)-L73 -> 0 | M207: =SUM(M74:M75)-M73 -> 0 | N207: 0 | O207: 0 | P207: 0 | Q207: 0 | R207: 0 | S207: 0 | T207: 0 | U207: 0 | V207: 0 | W207: 0 | X207: 0 | Y207: 0 | Z207: 0 | AA207: 0 | AB207: 0 | AC207: 0 | AD207: 0 | AE207: 0 | AF207: 0 | AG207: 0 | AH207: 0 | AI207: 0 | AJ207: 0 | AK207: 0 | AL207: 0 | AM207: 0 | AN207: 0 | AO207: 0 | AP207: 0
G208: =SUM(G77:G78)-G76 -> 0 | H208: =SUM(H77:H78)-H76 -> 0 | I208: =SUM(I77:I78)-I76 -> 0 | J208: =SUM(J77:J78)-J76 -> 0 | K208: =SUM(K77:K78)-K76 -> 0 | L208: =SUM(L77:L78)-L76 -> 0 | M208: =SUM(M77:M78)-M76 -> 0 | N208: 0 | O208: 0 | P208: 0 | Q208: 0 | R208: 0 | S208: 0 | T208: 0 | U208: 0 | V208: 0 | W208: 0 | X208: 0 | Y208: 0 | Z208: 0 | AA208: 0 | AB208: 0 | AC208: 0 | AD208: 0 | AE208: 0 | AF208: 0 | AG208: 0 | AH208: 0 | AI208: 0 | AJ208: 0 | AK208: 0 | AL208: 0 | AM208: 0 | AN208: 0 | AO208: 0 | AP208: 0
G209: =SUM(G79:G80)-G78 -> 0 | H209: =SUM(H79:H80)-H78 -> 0 | I209: =SUM(I79:I80)-I78 -> 0 | J209: =SUM(J79:J80)-J78 -> 0 | K209: =SUM(K79:K80)-K78 -> 0 | L209: =SUM(L79:L80)-L78 -> 0 | M209: =SUM(M79:M80)-M78 -> 0 | N209: 0 | O209: 0 | P209: 0 | Q209: 0 | R209: 0 | S209: 0 | T209: 0 | U209: 0 | V209: 0 | W209: 0 | X209: 0 | Y209: 0 | Z209: 0 | AA209: 0 | AB209: 0 | AC209: 0 | AD209: 0 | AE209: 0 | AF209: 0 | AG209: 0 | AH209: 0 | AI209: 0 | AJ209: 0 | AK209: 0 | AL209: 0 | AM209: 0 | AN209: 0 | AO209: 0 | AP209: 0
G210: =SUM(G87,G90,G91)-G86 -> 0 | H210: =SUM(H87,H90,H91)-H86 -> 0 | I210: =SUM(I87,I90,I91)-I86 -> 0 | J210: =SUM(J87,J90,J91)-J86 -> 0 | K210: =SUM(K87,K90,K91)-K86 -> 0 | L210: =SUM(L87,L90,L91)-L86 -> 0 | M210: =SUM(M87,M90,M91)-M86 -> 0 | N210: 0 | O210: 0 | P210: 0 | Q210: 0 | R210: 0 | S210: 0 | T210: 0 | U210: 0 | V210: 0 | W210: 0 | X210: 0 | Y210: 0 | Z210: 0 | AA210: 0 | AB210: 0 | AC210: 0 | AD210: 0 | AE210: 0 | AF210: 0 | AG210: 0 | AH210: 0 | AI210: 0 | AJ210: 0 | AK210: 0 | AL210: 0 | AM210: 0 | AN210: 0 | AO210: 0 | AP210: 0
G211: =SUM(G88:G89)-G87 -> 0 | H211: =SUM(H88:H89)-H87 -> 0 | I211: =SUM(I88:I89)-I87 -> 0 | J211: =SUM(J88:J89)-J87 -> 0 | K211: =SUM(K88:K89)-K87 -> 0 | L211: =SUM(L88:L89)-L87 -> 0 | M211: =SUM(M88:M89)-M87 -> 0 | N211: 0 | O211: 0 | P211: 0 | Q211: 0 | R211: 0 | S211: 0 | T211: 0 | U211: 0 | V211: 0 | W211: 0 | X211: 0 | Y211: 0 | Z211: 0 | AA211: 0 | AB211: 0 | AC211: 0 | AD211: 0 | AE211: 0 | AF211: 0 | AG211: 0 | AH211: 0 | AI211: 0 | AJ211: 0 | AK211: 0 | AL211: 0 | AM211: 0 | AN211: 0 | AO211: 0 | AP211: 0
G212: =SUM(G93,G97)-G92 -> 0 | H212: =SUM(H93,H97)-H92 -> 0 | I212: =SUM(I93,I97)-I92 -> 0 | J212: =SUM(J93,J97)-J92 -> 0 | K212: =SUM(K93,K97)-K92 -> 0 | L212: =SUM(L93,L97)-L92 -> 0 | M212: =SUM(M93,M97)-M92 -> 0 | N212: 0 | O212: 0 | P212: 0 | Q212: 0 | R212: 0 | S212: 0 | T212: 0 | U212: 0 | V212: 0 | W212: 0 | X212: 0 | Y212: 0 | Z212: 0 | AA212: 0 | AB212: 0 | AC212: 0 | AD212: 0 | AE212: 0 | AF212: 0 | AG212: 0 | AH212: 0 | AI212: 0 | AJ212: 0 | AK212: 0 | AL212: 0 | AM212: 0 | AN212: 0 | AO212: 0 | AP212: 0
G213: =SUM(G94:G96)-G93 -> 0 | H213: =SUM(H94:H96)-H93 -> 0 | I213: =SUM(I94:I96)-I93 -> 0 | J213: =SUM(J94:J96)-J93 -> 0 | K213: =SUM(K94:K96)-K93 -> 0 | L213: =SUM(L94:L96)-L93 -> 0 | M213: =SUM(M94:M96)-M93 -> 0 | N213: 0 | O213: 0 | P213: 0 | Q213: 0 | R213: 0 | S213: 0 | T213: 0 | U213: 0 | V213: 0 | W213: 0 | X213: 0 | Y213: 0 | Z213: 0 | AA213: 0 | AB213: 0 | AC213: 0 | AD213: 0 | AE213: 0 | AF213: 0 | AG213: 0 | AH213: 0 | AI213: 0 | AJ213: 0 | AK213: 0 | AL213: 0 | AM213: 0 | AN213: 0 | AO213: 0 | AP213: 0
G214: =SUM(G98:G103)-G97 -> 0 | H214: =SUM(H98:H103)-H97 -> 0 | I214: =SUM(I98:I103)-I97 -> 0 | J214: =SUM(J98:J103)-J97 -> 0 | K214: =SUM(K98:K103)-K97 -> 0 | L214: =SUM(L98:L103)-L97 -> 0 | M214: =SUM(M98:M103)-M97 -> 0 | N214: 0 | O214: 0 | P214: 0 | Q214: 0 | R214: 0 | S214: 0 | T214: 0 | U214: 0 | V214: 0 | W214: 0 | X214: 0 | Y214: 0 | Z214: 0 | AA214: 0 | AB214: 0 | AC214: 0 | AD214: 0 | AE214: 0 | AF214: 0 | AG214: 0 | AH214: 0 | AI214: 0 | AJ214: 0 | AK214: 0 | AL214: 0 | AM214: 0 | AN214: 0 | AO214: 0 | AP214: 0
G215: =SUM(G118,G124,G135,G137,G148,G151)-G117 -> 0 | H215: =SUM(H118,H124,H135,H137,H148,H151)-H117 -> 0 | I215: =SUM(I118,I124,I135,I137,I148,I151)-I117 -> 0 | J215: =SUM(J118,J124,J135,J137,J148,J151)-J117 -> 0 | K215: =SUM(K118,K124,K135,K137,K148,K151)-K117 -> 0 | L215: =SUM(L118,L124,L135,L137,L148,L151)-L117 -> 0 | M215: =SUM(M118,M124,M135,M137,M148,M151)-M117 -> 0 | N215: 0 | O215: 0 | P215: 0 | Q215: 0 | R215: 0 | S215: 0 | T215: 0 | U215: 0 | V215: 0 | W215: 0 | X215: 0 | Y215: 0 | Z215: 0 | AA215: 0 | AB215: 0 | AC215: 0 | AD215: 0 | AE215: 0 | AF215: 0 | AG215: 0 | AH215: 0 | AI215: 0 | AJ215: 0 | AK215: 0 | AL215: 0 | AM215: 0 | AN215: 0 | AO215: 0 | AP215: 0
G216: =SUM(G119,G122,G123)-G118 -> 0 | H216: =SUM(H119,H122,H123)-H118 -> 0 | I216: =SUM(I119,I122,I123)-I118 -> 0 | J216: =SUM(J119,J122,J123)-J118 -> 0 | K216: =SUM(K119,K122,K123)-K118 -> 0 | L216: =SUM(L119,L122,L123)-L118 -> 0 | M216: =SUM(M119,M122,M123)-M118 -> 0 | N216: 0 | O216: 0 | P216: 0 | Q216: 0 | R216: 0 | S216: 0 | T216: 0 | U216: 0 | V216: 0 | W216: 0 | X216: 0 | Y216: 0 | Z216: 0 | AA216: 0 | AB216: 0 | AC216: 0 | AD216: 0 | AE216: 0 | AF216: 0 | AG216: 0 | AH216: 0 | AI216: 0 | AJ216: 0 | AK216: 0 | AL216: 0 | AM216: 0 | AN216: 0 | AO216: 0 | AP216: 0
G217: =SUM(G120:G121)-G119 -> 0 | H217: =SUM(H120:H121)-H119 -> 0 | I217: =SUM(I120:I121)-I119 -> 0 | J217: =SUM(J120:J121)-J119 -> 0 | K217: =SUM(K120:K121)-K119 -> 0 | L217: =SUM(L120:L121)-L119 -> 0 | M217: =SUM(M120:M121)-M119 -> 0 | N217: 0 | O217: 0 | P217: 0 | Q217: 0 | R217: 0 | S217: 0 | T217: 0 | U217: 0 | V217: 0 | W217: 0 | X217: 0 | Y217: 0 | Z217: 0 | AA217: 0 | AB217: 0 | AC217: 0 | AD217: 0 | AE217: 0 | AF217: 0 | AG217: 0 | AH217: 0 | AI217: 0 | AJ217: 0 | AK217: 0 | AL217: 0 | AM217: 0 | AN217: 0 | AO217: 0 | AP217: 0
G218: =SUM(G125,G129)-G124 -> 0 | H218: =SUM(H125,H129)-H124 -> 0 | I218: =SUM(I125,I129)-I124 -> 0 | J218: =SUM(J125,J129)-J124 -> 0 | K218: =SUM(K125,K129)-K124 -> 0 | L218: =SUM(L125,L129)-L124 -> 0 | M218: =SUM(M125,M129)-M124 -> 0 | N218: 0 | O218: 0 | P218: 0 | Q218: 0 | R218: 0 | S218: 0 | T218: 0 | U218: 0 | V218: 0 | W218: 0 | X218: 0 | Y218: 0 | Z218: 0 | AA218: 0 | AB218: 0 | AC218: 0 | AD218: 0 | AE218: 0 | AF218: 0 | AG218: 0 | AH218: 0 | AI218: 0 | AJ218: 0 | AK218: 0 | AL218: 0 | AM218: 0 | AN218: 0 | AO218: 0 | AP218: 0
G219: =SUM(G130:G134)-G129 -> 0 | H219: =SUM(H130:H134)-H129 -> 0 | I219: =SUM(I130:I134)-I129 -> 0 | J219: =SUM(J130:J134)-J129 -> 0 | K219: =SUM(K130:K134)-K129 -> 0 | L219: =SUM(L130:L134)-L129 -> 0 | M219: =SUM(M130:M134)-M129 -> 0 | N219: 0 | O219: 0 | P219: 0 | Q219: 0 | R219: 0 | S219: 0 | T219: 0 | U219: 0 | V219: 0 | W219: 0 | X219: 0 | Y219: 0 | Z219: 0 | AA219: 0 | AB219: 0 | AC219: 0 | AD219: 0 | AE219: 0 | AF219: 0 | AG219: 0 | AH219: 0 | AI219: 0 | AJ219: 0 | AK219: 0 | AL219: 0 | AM219: 0 | AN219: 0 | AO219: 0 | AP219: 0
G220: =SUM(G136)-G135 -> 0 | H220: =SUM(H136)-H135 -> 0 | I220: =SUM(I136)-I135 -> 0 | J220: =SUM(J136)-J135 -> 0 | K220: =SUM(K136)-K135 -> 0 | L220: =SUM(L136)-L135 -> 0 | M220: =SUM(M136)-M135 -> 0 | N220: 0 | O220: 0 | P220: 0 | Q220: 0 | R220: 0 | S220: 0 | T220: 0 | U220: 0 | V220: 0 | W220: 0 | X220: 0 | Y220: 0 | Z220: 0 | AA220: 0 | AB220: 0 | AC220: 0 | AD220: 0 | AE220: 0 | AF220: 0 | AG220: 0 | AH220: 0 | AI220: 0 | AJ220: 0 | AK220: 0 | AL220: 0 | AM220: 0 | AN220: 0 | AO220: 0 | AP220: 0
G221: =SUM(G138,G143)-G137 -> 0 | H221: =SUM(H138,H143)-H137 -> 0 | I221: =SUM(I138,I143)-I137 -> 0 | J221: =SUM(J138,J143)-J137 -> 0 | K221: =SUM(K138,K143)-K137 -> 0 | L221: =SUM(L138,L143)-L137 -> 0 | M221: =SUM(M138,M143)-M137 -> 0 | N221: 0 | O221: 0 | P221: 0 | Q221: 0 | R221: 0 | S221: 0 | T221: 0 | U221: 0 | V221: 0 | W221: 0 | X221: 0 | Y221: 0 | Z221: 0 | AA221: 0 | AB221: 0 | AC221: 0 | AD221: 0 | AE221: 0 | AF221: 0 | AG221: 0 | AH221: 0 | AI221: 0 | AJ221: 0 | AK221: 0 | AL221: 0 | AM221: 0 | AN221: 0 | AO221: 0 | AP221: 0
G222: =SUM(G139:G142)-G138 -> 0 | H222: =SUM(H139:H142)-H138 -> 0 | I222: =SUM(I139:I142)-I138 -> 0 | J222: =SUM(J139:J142)-J138 -> 0 | K222: =SUM(K139:K142)-K138 -> 0 | L222: =SUM(L139:L142)-L138 -> 0 | M222: =SUM(M139:M142)-M138 -> 0 | N222: 0 | O222: 0 | P222: 0 | Q222: 0 | R222: 0 | S222: 0 | T222: 0 | U222: 0 | V222: 0 | W222: 0 | X222: 0 | Y222: 0 | Z222: 0 | AA222: 0 | AB222: 0 | AC222: 0 | AD222: 0 | AE222: 0 | AF222: 0 | AG222: 0 | AH222: 0 | AI222: 0 | AJ222: 0 | AK222: 0 | AL222: 0 | AM222: 0 | AN222: 0 | AO222: 0 | AP222: 0
G223: =SUM(G144:G147)-G143 -> 0 | H223: =SUM(H144:H147)-H143 -> 0 | I223: =SUM(I144:I147)-I143 -> 0 | J223: =SUM(J144:J147)-J143 -> 0 | K223: =SUM(K144:K147)-K143 -> 0 | L223: =SUM(L144:L147)-L143 -> 0 | M223: =SUM(M144:M147)-M143 -> 0 | N223: 0 | O223: 0 | P223: 0 | Q223: 0 | R223: 0 | S223: 0 | T223: 0 | U223: 0 | V223: 0 | W223: 0 | X223: 0 | Y223: 0 | Z223: 0 | AA223: 0 | AB223: 0 | AC223: 0 | AD223: 0 | AE223: 0 | AF223: 0 | AG223: 0 | AH223: 0 | AI223: 0 | AJ223: 0 | AK223: 0 | AL223: 0 | AM223: 0 | AN223: 0 | AO223: 0 | AP223: 0
G224: =SUM(G156,G157,G165,G166,G177,G178,G181,G183,G186)-G155 -> 0 | H224: =SUM(H156,H157,H165,H166,H177,H178,H181,H183,H186)-H155 -> 0 | I224: =SUM(I156,I157,I165,I166,I177,I178,I181,I183,I186)-I155 -> 0 | J224: =SUM(J156,J157,J165,J166,J177,J178,J181,J183,J186)-J155 -> 0 | K224: =SUM(K156,K157,K165,K166,K177,K178,K181,K183,K186)-K155 -> 0 | L224: =SUM(L156,L157,L165,L166,L177,L178,L181,L183,L186)-L155 -> 0 | M224: =SUM(M156,M157,M165,M166,M177,M178,M181,M183,M186)-M155 -> 0 | N224: 0 | O224: 0 | P224: 0 | Q224: 0 | R224: 0 | S224: 0 | T224: 0 | U224: 0 | V224: 0 | W224: 0 | X224: 0 | Y224: 0 | Z224: 0 | AA224: 0 | AB224: 0 | AC224: 0 | AD224: 0 | AE224: 0 | AF224: 0 | AG224: 0 | AH224: 0 | AI224: 0 | AJ224: 0 | AK224: 0 | AL224: 0 | AM224: 0 | AN224: 0 | AO224: 0 | AP224: 0
G225: =SUM(G158:G164)-G157 -> 0 | H225: =SUM(H158:H164)-H157 -> 0 | I225: =SUM(I158:I164)-I157 -> 0 | J225: =SUM(J158:J164)-J157 -> 0 | K225: =SUM(K158:K164)-K157 -> 0 | L225: =SUM(L158:L164)-L157 -> 0 | M225: =SUM(M158:M164)-M157 -> 0 | N225: 0 | O225: 0 | P225: 0 | Q225: 0 | R225: 0 | S225: 0 | T225: 0 | U225: 0 | V225: 0 | W225: 0 | X225: 0 | Y225: 0 | Z225: 0 | AA225: 0 | AB225: 0 | AC225: 0 | AD225: 0 | AE225: 0 | AF225: 0 | AG225: 0 | AH225: 0 | AI225: 0 | AJ225: 0 | AK225: 0 | AL225: 0 | AM225: 0 | AN225: 0 | AO225: 0 | AP225: 0
G226: =SUM(G167:G176)-G166 -> 0 | H226: =SUM(H167:H176)-H166 -> 0 | I226: =SUM(I167:I176)-I166 -> 0 | J226: =SUM(J167:J176)-J166 -> 0 | K226: =SUM(K167:K176)-K166 -> 0 | L226: =SUM(L167:L176)-L166 -> 0 | M226: =SUM(M167:M176)-M166 -> 0 | N226: 0 | O226: 0 | P226: 0 | Q226: 0 | R226: 0 | S226: 0 | T226: 0 | U226: 0 | V226: 0 | W226: 0 | X226: 0 | Y226: 0 | Z226: 0 | AA226: 0 | AB226: 0 | AC226: 0 | AD226: 0 | AE226: 0 | AF226: 0 | AG226: 0 | AH226: 0 | AI226: 0 | AJ226: 0 | AK226: 0 | AL226: 0 | AM226: 0 | AN226: 0 | AO226: 0 | AP226: 0
G227: =SUM(G179:G180)-G178 -> 0 | H227: =SUM(H179:H180)-H178 -> 0 | I227: =SUM(I179:I180)-I178 -> 0 | J227: =SUM(J179:J180)-J178 -> 0 | K227: =SUM(K179:K180)-K178 -> 0 | L227: =SUM(L179:L180)-L178 -> 0 | M227: =SUM(M179:M180)-M178 -> 0 | N227: 0 | O227: 0 | P227: 0 | Q227: 0 | R227: 0 | S227: 0 | T227: 0 | U227: 0 | V227: 0 | W227: 0 | X227: 0 | Y227: 0 | Z227: 0 | AA227: 0 | AB227: 0 | AC227: 0 | AD227: 0 | AE227: 0 | AF227: 0 | AG227: 0 | AH227: 0 | AI227: 0 | AJ227: 0 | AK227: 0 | AL227: 0 | AM227: 0 | AN227: 0 | AO227: 0 | AP227: 0
G228: =SUM(G182)-G181 -> 0 | H228: =SUM(H182)-H181 -> 0 | I228: =SUM(I182)-I181 -> 0 | J228: =SUM(J182)-J181 -> 0 | K228: =SUM(K182)-K181 -> 0 | L228: =SUM(L182)-L181 -> 0 | M228: =SUM(M182)-M181 -> 0 | N228: 0 | O228: 0 | P228: 0 | Q228: 0 | R228: 0 | S228: 0 | T228: 0 | U228: 0 | V228: 0 | W228: 0 | X228: 0 | Y228: 0 | Z228: 0 | AA228: 0 | AB228: 0 | AC228: 0 | AD228: 0 | AE228: 0 | AF228: 0 | AG228: 0 | AH228: 0 | AI228: 0 | AJ228: 0 | AK228: 0 | AL228: 0 | AM228: 0 | AN228: 0 | AO228: 0 | AP228: 0
G229: =SUM(G184:G185)-G183 -> 0 | H229: =SUM(H184:H185)-H183 -> 0 | I229: =SUM(I184:I185)-I183 -> 0 | J229: =SUM(J184:J185)-J183 -> 0 | K229: =SUM(K184:K185)-K183 -> 0 | L229: =SUM(L184:L185)-L183 -> 0 | M229: =SUM(M184:M185)-M183 -> 0 | N229: 0 | O229: 0 | P229: 0 | Q229: 0 | R229: 0 | S229: 0 | T229: 0 | U229: 0 | V229: 0 | W229: 0 | X229: 0 | Y229: 0 | Z229: 0 | AA229: 0 | AB229: 0 | AC229: 0 | AD229: 0 | AE229: 0 | AF229: 0 | AG229: 0 | AH229: 0 | AI229: 0 | AJ229: 0 | AK229: 0 | AL229: 0 | AM229: 0 | AN229: 0 | AO229: 0 | AP229: 0

Sheet P&L - Consolidado
D1: Acumulado | E1: 2T26 | F1: 1T26 | G1: Acumulado | H1: 4T25 | I1: Acumulado | J1: 3T25 | K1: Acumulado | L1: 2T25 | M1: 1T25 | N1: Acumulado | O1: 4T24 | P1: Acumulado | Q1: 3T24 | R1: Acumulado | S1: 2T24 | T1: 1T24 | U1: Acumulado | V1: 4T23 | W1: Acumulado | X1: 3T23 | Y1: Acumulado | Z1: 2T23 | AA1: 1T23 | AB1: Acumulado | AC1: 4T22 | AD1: Acumulado | AE1: 3T22 | AF1: Acumulado | AG1: 2T22 | AH1: 1T22 | AI1: Acumulado | AJ1: 4T21 | AK1: Acumulado | AL1: 3T21 | AM1: Acumulado | AN1: 2T21 | AO1: 1T21 | AP1: Acumulado | AQ1: 4T20 | AR1: Acumulado | AS1: 3T20 | AT1: Acumulado | AU1: 2T20 | AV1: 1T20 | AW1: Acumulado | AX1: 4T19 | AY1: Acumulado | AZ1: 3T19 | BA1: Acumulado | BB1: 2T19 | BC1: 1T19 | BD1: Acumulado | BE1: 4T18 | BF1: Acumulado | BG1: 3T18 | BH1: Acumulado | BI1: 2T18 | BJ1: 1T18 | BK1: Acumulado | BL1: 4T17 | BM1: Acumulado | BN1: 3T17 | BO1: Acumulado | BP1: 2T17 | BQ1: 1T17 | BR1: Acumulado
A2: Codigo Conta | B2: Descricao Conta | D2: 46203 | E2: 46203 | F2: 46112 | G2: 46022 | H2: 46022 | I2: 45930 | J2: 45930 | K2: 45838 | L2: 45838 | M2: 45747 | N2: 45657 | O2: 45657 | P2: 45565 | Q2: 45565 | R2: 45473 | S2: 45473 | T2: 45382 | U2: 45291 | V2: 45291 | W2: 45199 | X2: 45199 | Y2: 45107 | Z2: 45107 | AA2: 45016 | AB2: 44926 | AC2: 44926 | AD2: 44834 | AE2: 44834 | AF2: 44742 | AG2: 44742 | AH2: 44651 | AI2: 44561 | AJ2: 44561 | AK2: 44469 | AL2: 44469 | AM2: 44377 | AN2: 44377 | AO2: 44286 | AP2: 44196 | AQ2: 44196 | AR2: 44104 | AS2: 44104 | AT2: 44012 | AU2: 44012 | AV2: 43921 | AW2: 43830 | AX2: 43830 | AY2: 43738 | AZ2: 43738 | BA2: 43646 | BB2: 43646 | BC2: 43555 | BD2: 43465 | BE2: 43465 | BF2: 43373 | BG2: 43373 | BH2: 43281 | BI2: 43281 | BJ2: 43190 | BK2: 43100 | BL2: 43100 | BM2: 43008 | BN2: 43008 | BO2: 42916 | BP2: 42916 | BQ2: 42825 | BR2: 42735
A3: 3.01 | B3: Receita de Venda de Bens e/ou Serviços | C3: 3.01Receita de Venda de Bens e/ou Serviços | D3: 7819803 | E3: 4012470 | F3: 3807333 | G3: 15366537 | H3: =G3-I3 -> 3519120 | I3: 11847417 | J3: 3802399 | K3: =L3+M3 -> 8045018 | L3: 4106968 | M3: 3938050 | N3: 15331813 | O3: 3909106 | P3: 11422707 | Q3: 3982373 | R3: 7440334 | S3: 3844568 | T3: 3595766 | U3: 14955220 | V3: 3483501 | W3: 11471719 | X3: 3672363 | Y3: 7799356 | Z3: 3801203 | AA3: 3998153 | AB3: 16947869 | AC3: 4159955 | AD3: 12787914 | AE3: 4318339 | AF3: 8469575 | AG3: 4192384 | AH3: 4277191 | AI3: 13688367 | AJ3: 3787410 | AK3: 9900957 | AL3: 3583978 | AM3: 6316979 | AN3: 3183883 | AO3: 3133096 | AP3: 8760568 | AQ3: 2849408 | AR3: 5911160 | AS3: 2514756 | AT3: 3396404 | AU3: 1171844 | AV3: 2224560 | AW3: 10016395 | AX3: 2338634 | AY3: 7677761 | AZ3: 2542311 | BA3: 5135450 | BB3: 2667331 | BC3: 2468119 | BD3: 9616299 | BE3: 2455752 | BF3: 7160547 | BG3: 2617310 | BH3: 4543237 | BI3: 2399485 | BJ3: 2143752 | BK3: 7487940 | BL3: 1954644 | BM3: 5533296 | BN3: 1932451 | BO3: 3600845 | BP3: 1901809 | BQ3: 1699036 | BR3: 6816454
A4: 3.02 | B4: Custo dos Bens e/ou Serviços Vendidos | C4: 3.02Custo dos Bens e/ou Serviços Vendidos | D4: -6892722 | E4: -3526927 | F4: -3365795 | G4: -13515765 | H4: =G4-I4 -> -3107012 | I4: -10408753 | J4: -3342084 | K4: =L4+M4 -> -7066669 | L4: -3572351 | M4: -3494318 | N4: -13510380 | O4: -3426095 | P4: -10084285 | Q4: -3504636 | R4: -6579649 | S4: -3368012 | T4: -3211637 | U4: -13446975 | V4: -3103262 | W4: -10343713 | X4: -3310171 | Y4: -7033542 | Z4: -3376475 | AA4: -3657067 | AB4: -15139227 | AC4: -3835919 | AD4: -11303308 | AE4: -3979383 | AF4: -7323925 | AG4: -3657734 | AH4: -3666191 | AI4: -11984244 | AJ4: -3409312 | AK4: -8574932 | AL4: -3088387 | AM4: -5486545 | AN4: -2763165 | AO4: -2723380 | AP4: -8195255 | AQ4: -2587790 | AR4: -5607465 | AS4: -2259081 | AT4: -3348384 | AU4: -1308180 | AV4: -2040204 | AW4: -8831177 | AX4: -2110991 | AY4: -6720186 | AZ4: -2219621 | BA4: -4500565 | BB4: -2330756 | BC4: -2169809 | BD4: -8298023 | BE4: -2149503 | BF4: -6148520 | BG4: -2237928 | BH4: -3910592 | BI4: -2061693 | BJ4: -1848899 | BK4: -6332962 | BL4: -1659083 | BM4: -4673879 | BN4: -1614021 | BO4: -3059858 | BP4: -1603601 | BQ4: -1456257 | BR4: -5844666
A5: 3.03 | B5: Resultado Bruto | C5: 3.03Resultado Bruto | D5: 927081 | E5: 485543 | F5: 441538 | G5: 1850772 | H5: =G5-I5 -> 412108 | I5: 1438664 | J5: 460315 | K5: =L5+M5 -> 978349 | L5: 534617 | M5: 443732 | N5: 1821433 | O5: 483011 | P5: 1338422 | Q5: 477737 | R5: 860685 | S5: 476556 | T5: 384129 | U5: 1508245 | V5: 380239 | W5: 1128006 | X5: 362192 | Y5: 765814 | Z5: 424728 | AA5: 341086 | AB5: 1808642 | AC5: 324036 | AD5: 1484606 | AE5: 338956 | AF5: 1145650 | AG5: 534650 | AH5: 611000 | AI5: 1704123 | AJ5: 378098 | AK5: 1326025 | AL5: 495591 | AM5: 830434 | AN5: 420718 | AO5: 409716 | AP5: 565313 | AQ5: 261618 | AR5: 303695 | AS5: 255675 | AT5: 48020 | AU5: -136336 | AV5: 184356 | AW5: 1185218 | AX5: 227643 | AY5: 957575 | AZ5: 322690 | BA5: 634885 | BB5: 336575 | BC5: 298310 | BD5: 1318276 | BE5: 306249 | BF5: 1012027 | BG5: 379382 | BH5: 632645 | BI5: 337792 | BJ5: 294853 | BK5: 1154978 | BL5: 295561 | BM5: 859417 | BN5: 318430 | BO5: 540987 | BP5: 298208 | BQ5: 242779 | BR5: 971788
A6: 3.04 | B6: Despesas/Receitas Operacionais | C6: 3.04Despesas/Receitas Operacionais | D6: -424545 | E6: -201830 | F6: -222715 | G6: -908858 | H6: =G6-I6 -> -215991 | I6: -692867 | J6: -238403 | K6: =L6+M6 -> -454464 | L6: -227761 | M6: -226703 | N6: -800397 | O6: -235862 | P6: -564535 | Q6: -171173 | R6: -393362 | S6: -210123 | T6: -183239 | U6: -725669 | V6: -206954 | W6: -518715 | X6: -164286 | Y6: -354429 | Z6: -179103 | AA6: -175326 | AB6: -562958 | AC6: -157645 | AD6: -405313 | AE6: -93459 | AF6: -311854 | AG6: -120755 | AH6: -191099 | AI6: -422638 | AJ6: -128649 | AK6: -293989 | AL6: -140927 | AM6: -153062 | AN6: 33573 | AO6: -186635 | AP6: -750034 | AQ6: -271280 | AR6: -478754 | AS6: -184196 | AT6: -294558 | AU6: -195698 | AV6: -98860 | AW6: -508963 | AX6: -123544 | AY6: -385419 | AZ6: -95953 | BA6: -289466 | BB6: -134923 | BC6: -154543 | BD6: -616783 | BE6: -161598 | BF6: -455185 | BG6: -159660 | BH6: -295525 | BI6: -147800 | BJ6: -147725 | BK6: -658422 | BL6: -179896 | BM6: -478526 | BN6: -174444 | BO6: -304082 | BP6: -177349 | BQ6: -126733 | BR6: -492466
A7: 3.04.01 | B7: Despesas com Vendas | C7: 3.04.01Despesas com Vendas | D7: -37082 | E7: -15375 | F7: -21707 | G7: -81429 | H7: =G7-I7 -> -13183 | I7: -68246 | J7: -21768 | K7: =L7+M7 -> -46478 | L7: -26065 | M7: -20413 | N7: -76150 | O7: -19572 | P7: -56578 | Q7: -18907 | R7: -37671 | S7: -19866 | T7: -17805 | U7: -81674 | V7: -21137 | W7: -60537 | X7: -20410 | Y7: -40127 | Z7: -22335 | AA7: -17792 | AB7: -96095 | AC7: -26358 | AD7: -69737 | AE7: -27130 | AF7: -42607 | AG7: -21290 | AH7: -21317 | AI7: -78486 | AJ7: -24517 | AK7: -53969 | AL7: -19100 | AM7: -34869 | AN7: -12457 | AO7: -22412 | AP7: -61812 | AQ7: -23221 | AR7: -38591 | AS7: -11754 | AT7: -26837 | AU7: -13579 | AV7: -13258 | AW7: -53778 | AX7: -13310 | AY7: -40468 | AZ7: -17453 | BA7: -23015 | BB7: -9142 | BC7: -13873 | BD7: -75359 | BE7: -38707 | BF7: -36652 | BG7: -17172 | BH7: -19480 | BI7: -10382 | BJ7: -9098 | BK7: -162157 | BL7: -41857 | BM7: -120300 | BN7: -42465 | BO7: -77835 | BP7: -42283 | BQ7: -35552 | BR7: -150931
A8: 3.04.02 | B8: Despesas Gerais e Administrativas | C8: 3.04.02Despesas Gerais e Administrativas | D8: -387077 | E8: -198465 | F8: -188612 | G8: -823538 | H8: =G8-I8 -> -211433 | I8: -612105 | J8: -188462 | K8: =L8+M8 -> -423643 | L8: -217955 | M8: -205688 | N8: -722385 | O8: -216671 | P8: -505714 | Q8: -173767 | R8: -331947 | S8: -171355 | T8: -160592 | U8: -675905 | V8: -175415 | W8: -500490 | X8: -162860 | Y8: -337630 | Z8: -170563 | AA8: -167067 | AB8: -646494 | AC8: -183690 | AD8: -462804 | AE8: -154943 | AF8: -307861 | AG8: -160323 | AH8: -147538 | AI8: -662343 | AJ8: -180285 | AK8: -482058 | AL8: -155917 | AM8: -326141 | AN8: -166679 | AO8: -159462 | AP8: -501831 | AQ8: -142684 | AR8: -359147 | AS8: -123363 | AT8: -235784 | AU8: -118786 | AV8: -116998 | AW8: -502054 | AX8: -131495 | AY8: -370559 | AZ8: -119442 | BA8: -251117 | BB8: -124016 | BC8: -127101 | BD8: -494228 | BE8: -121746 | BF8: -372482 | BG8: -125636 | BH8: -246846 | BI8: -127585 | BJ8: -119261 | BK8: -398808 | BL8: -118323 | BM8: -280485 | BN8: -87190 | BO8: -193295 | BP8: -99136 | BQ8: -94159 | BR8: -384373
